{"lastUpdated":"2026-04-27T07:55:01.567Z","buyRegion":10000049,"sellRegion":10000041,"buyRegionName":"Khanid","sellRegionName":"Syndicate","opportunities":[{"typeId":4871,"itemName":"Large Compact Pb-Acid Cap Battery","buyPrice":1,"sellPrice":20000,"profitPerUnit":19999,"buyStation":"Irmalin VIII - Moon 13 - Royal Khanid Navy Testing Facilities","sellStation":"98Q-8O VII - Moon 16 - Intaki Commerce Trading Post","roi":1999900,"volumeAvailable":2,"maxProfit":39998},{"typeId":16329,"itemName":"Upgraded EM Coating I","buyPrice":1.01,"sellPrice":1000,"profitPerUnit":998.99,"buyStation":"Irmalin VIII - Moon 13 - Royal Khanid Navy Testing Facilities","sellStation":"98Q-8O VII - Moon 16 - Intaki Commerce Trading Post","roi":98909.9,"volumeAvailable":1,"maxProfit":998.99},{"typeId":16345,"itemName":"Upgraded Layered Coating I","buyPrice":1.01,"sellPrice":1000,"profitPerUnit":998.99,"buyStation":"Irmalin VIII - Moon 13 - Royal Khanid Navy Testing Facilities","sellStation":"98Q-8O VII - Moon 16 - Intaki Commerce Trading Post","roi":98909.9,"volumeAvailable":1,"maxProfit":998.99},{"typeId":4471,"itemName":"Small Infectious Scoped Energy Neutralizer","buyPrice":1.01,"sellPrice":1000,"profitPerUnit":998.99,"buyStation":"Kihtaled VIII - Royal Khanid Navy Assembly Plant","sellStation":"GRNJ-3 III - Intaki Space Police Testing Facilities","roi":98909.9,"volumeAvailable":1,"maxProfit":998.99},{"typeId":2254,"itemName":"Temperate Command Center","buyPrice":50000,"sellPrice":10000000,"profitPerUnit":9950000,"buyStation":"Gehi IX - Moon 4 - Royal Khanid Navy Assembly Plant","sellStation":"D85-VD VII - Intaki Bank Vault","roi":19900,"volumeAvailable":2,"maxProfit":19900000},{"typeId":2254,"itemName":"Temperate Command Center","buyPrice":70000,"sellPrice":10000000,"profitPerUnit":9930000,"buyStation":"Irmalin VIII - Moon 13 - Royal Khanid Navy Testing Facilities","sellStation":"D85-VD VII - Intaki Bank Vault","roi":14185.71,"volumeAvailable":2,"maxProfit":19860000},{"typeId":2254,"itemName":"Temperate Command Center","buyPrice":100000,"sellPrice":10000000,"profitPerUnit":9900000,"buyStation":"Badivefi VIII - Moon 10 - Royal Khanid Navy Logistic Support","sellStation":"D85-VD VII - Intaki Bank Vault","roi":9900,"volumeAvailable":2,"maxProfit":19800000},{"typeId":1223,"itemName":"Bistot","buyPrice":62.01,"sellPrice":3000,"profitPerUnit":2937.99,"buyStation":"Irmalin VIII - Moon 13 - Royal Khanid Navy Testing Facilities","sellStation":"98Q-8O VII - Moon 16 - Intaki Commerce Trading Post","roi":4737.93,"volumeAvailable":645,"maxProfit":1895003.55},{"typeId":2254,"itemName":"Temperate Command Center","buyPrice":333400,"sellPrice":10000000,"profitPerUnit":9666600,"buyStation":"Agil VI - Moon 2 - CONCORD Logistic Support","sellStation":"D85-VD VII - Intaki Bank Vault","roi":2899.4,"volumeAvailable":1,"maxProfit":9666600},{"typeId":3841,"itemName":"Large Shield Extender II","buyPrice":15210,"sellPrice":390000,"profitPerUnit":374790,"buyStation":"Irmalin VIII - Moon 13 - Royal Khanid Navy Testing Facilities","sellStation":"PC9-AY III - Intaki Commerce Trading Post","roi":2464.1,"volumeAvailable":2,"maxProfit":749580},{"typeId":2254,"itemName":"Temperate Command Center","buyPrice":400000,"sellPrice":10000000,"profitPerUnit":9600000,"buyStation":"Parses VI - Moon 11 - Royal Khanid Navy Assembly Plant","sellStation":"D85-VD VII - Intaki Bank Vault","roi":2400,"volumeAvailable":2,"maxProfit":19200000},{"typeId":22291,"itemName":"Ballistic Control System II","buyPrice":105100,"sellPrice":350100,"profitPerUnit":245000,"buyStation":"Irmalin VIII - Moon 13 - Royal Khanid Navy Testing Facilities","sellStation":"31-MLU IX - Moon 1 - Thukker Mix Factory","roi":233.11,"volumeAvailable":1,"maxProfit":245000},{"typeId":16383,"itemName":"Prototype Compact Thermal Armor Hardener I","buyPrice":33400,"sellPrice":100000,"profitPerUnit":66600,"buyStation":"Kihtaled VIII - Moon 17 - CONCORD Bureau","sellStation":"98Q-8O VII - Moon 16 - Intaki Commerce Trading Post","roi":199.4,"volumeAvailable":2,"maxProfit":133200},{"typeId":7409,"itemName":"Dual 250mm 'Scout' Accelerator Cannon","buyPrice":98980,"sellPrice":250000,"profitPerUnit":151020,"buyStation":"Khanid Prime V - Moon 1 - Khanid Innovation Factory","sellStation":"98Q-8O VII - Moon 16 - Intaki Commerce Trading Post","roi":152.58,"volumeAvailable":4,"maxProfit":604080},{"typeId":34,"itemName":"Tritanium","buyPrice":2,"sellPrice":4.5,"profitPerUnit":2.5,"buyStation":"Arzieh V - Moon 3 - Royal Khanid Navy Testing Facilities","sellStation":"5-FGQI V - Moon 13 - Intaki Syndicate Academy","roi":125,"volumeAvailable":271597,"maxProfit":678992.5},{"typeId":34,"itemName":"Tritanium","buyPrice":2,"sellPrice":4.5,"profitPerUnit":2.5,"buyStation":"Baratar X - Moon 9 - Royal Khanid Navy Logistic Support","sellStation":"5-FGQI V - Moon 13 - Intaki Syndicate Academy","roi":125,"volumeAvailable":100002,"maxProfit":250005},{"typeId":34,"itemName":"Tritanium","buyPrice":2.13,"sellPrice":4.5,"profitPerUnit":2.37,"buyStation":"Irmalin VIII - Moon 13 - Royal Khanid Navy Testing Facilities","sellStation":"5-FGQI V - Moon 13 - Intaki Syndicate Academy","roi":111.27,"volumeAvailable":243583,"maxProfit":577291.71},{"typeId":54781,"itemName":"StrikeSnipe Ultra S","buyPrice":500,"sellPrice":1000,"profitPerUnit":500,"buyStation":"Irmalin VIII - Moon 13 - Royal Khanid Navy Testing Facilities","sellStation":"TXW-EI IX - Moon 2 - Intaki Bank Depository","roi":100,"volumeAvailable":1,"maxProfit":500},{"typeId":21898,"itemName":"Republic Fleet EMP S","buyPrice":100.1,"sellPrice":200,"profitPerUnit":99.9,"buyStation":"Agil VI - Moon 2 - CONCORD Logistic Support","sellStation":"FD-MLJ VII - Moon 2 - Intaki Bank Depository","roi":99.8,"volumeAvailable":80,"maxProfit":7992},{"typeId":7623,"itemName":"Regulated Electron Phase Cannon I","buyPrice":25890,"sellPrice":50000,"profitPerUnit":24110,"buyStation":"Kihtaled VIII - Moon 17 - CONCORD Bureau","sellStation":"98Q-8O VII - Moon 16 - Intaki Commerce Trading Post","roi":93.12,"volumeAvailable":1,"maxProfit":24110},{"typeId":34,"itemName":"Tritanium","buyPrice":2.43,"sellPrice":4.5,"profitPerUnit":2.07,"buyStation":"Gehi IX - Moon 4 - Royal Khanid Navy Assembly Plant","sellStation":"5-FGQI V - Moon 13 - Intaki Syndicate Academy","roi":85.19,"volumeAvailable":271597,"maxProfit":562205.79},{"typeId":34,"itemName":"Tritanium","buyPrice":2.46,"sellPrice":4.5,"profitPerUnit":2.04,"buyStation":"Zephan VIII - Moon 1 - Khanid Transport Storage","sellStation":"5-FGQI V - Moon 13 - Intaki Syndicate Academy","roi":82.93,"volumeAvailable":271597,"maxProfit":554057.88},{"typeId":35,"itemName":"Pyerite","buyPrice":13.8,"sellPrice":25,"profitPerUnit":11.2,"buyStation":"Irmalin VIII - Moon 13 - Royal Khanid Navy Testing Facilities","sellStation":"98Q-8O VII - Moon 16 - Intaki Commerce Trading Post","roi":81.16,"volumeAvailable":67245,"maxProfit":753144},{"typeId":6173,"itemName":"Optical Compact Tracking Computer","buyPrice":1421,"sellPrice":2500,"profitPerUnit":1079,"buyStation":"Badivefi VIII - Moon 10 - Royal Khanid Navy Logistic Support","sellStation":"FD-MLJ VII - Moon 4 - Intaki Space Police Assembly Plant","roi":75.93,"volumeAvailable":96,"maxProfit":103584},{"typeId":35,"itemName":"Pyerite","buyPrice":15.01,"sellPrice":25,"profitPerUnit":9.99,"buyStation":"Kihtaled VIII - Moon 7 - Royal Khanid Navy Assembly Plant","sellStation":"98Q-8O VII - Moon 16 - Intaki Commerce Trading Post","roi":66.56,"volumeAvailable":241912,"maxProfit":2416700.88},{"typeId":35,"itemName":"Pyerite","buyPrice":15.96,"sellPrice":25,"profitPerUnit":9.04,"buyStation":"Parses VI - Moon 11 - Royal Khanid Navy Assembly Plant","sellStation":"98Q-8O VII - Moon 16 - Intaki Commerce Trading Post","roi":56.64,"volumeAvailable":241912,"maxProfit":2186884.48},{"typeId":36,"itemName":"Mexallon","buyPrice":50,"sellPrice":76,"profitPerUnit":26,"buyStation":"Irmalin VIII - Moon 13 - Royal Khanid Navy Testing Facilities","sellStation":"I0AB-R VI - Intaki Space Police Assembly Plant","roi":52,"volumeAvailable":20284,"maxProfit":527384},{"typeId":36,"itemName":"Mexallon","buyPrice":50,"sellPrice":76,"profitPerUnit":26,"buyStation":"Arzieh V - Moon 3 - Royal Khanid Navy Testing Facilities","sellStation":"I0AB-R VI - Intaki Space Police Assembly Plant","roi":52,"volumeAvailable":19463,"maxProfit":506038},{"typeId":34,"itemName":"Tritanium","buyPrice":3.06,"sellPrice":4.5,"profitPerUnit":1.44,"buyStation":"Khanid Prime V - Moon 1 - Khanid Innovation Factory","sellStation":"5-FGQI V - Moon 13 - Intaki Syndicate Academy","roi":47.06,"volumeAvailable":182769,"maxProfit":263187.36},{"typeId":17889,"itemName":"Hydrogen Isotopes","buyPrice":700,"sellPrice":1000,"profitPerUnit":300,"buyStation":"Vezila IV - Royal Khanid Navy Assembly Plant","sellStation":"CIS-7X IX - Moon 6 - Intaki Syndicate Bureau","roi":42.86,"volumeAvailable":1,"maxProfit":300},{"typeId":35,"itemName":"Pyerite","buyPrice":17.95,"sellPrice":25,"profitPerUnit":7.05,"buyStation":"Zephan VIII - Moon 1 - Khanid Transport Storage","sellStation":"98Q-8O VII - Moon 16 - Intaki Commerce Trading Post","roi":39.28,"volumeAvailable":241912,"maxProfit":1705479.6},{"typeId":35,"itemName":"Pyerite","buyPrice":19,"sellPrice":25,"profitPerUnit":6,"buyStation":"Badivefi VI - Moon 2 - Royal Khanid Navy Logistic Support","sellStation":"98Q-8O VII - Moon 16 - Intaki Commerce Trading Post","roi":31.58,"volumeAvailable":241912,"maxProfit":1451472},{"typeId":34,"itemName":"Tritanium","buyPrice":3.5,"sellPrice":4.5,"profitPerUnit":1,"buyStation":"Danera IV - Moon 1 - Royal Khanid Navy Assembly Plant","sellStation":"5-FGQI V - Moon 13 - Intaki Syndicate Academy","roi":28.57,"volumeAvailable":271597,"maxProfit":271597},{"typeId":34,"itemName":"Tritanium","buyPrice":3.5,"sellPrice":4.5,"profitPerUnit":1,"buyStation":"Parses VI - Moon 11 - Royal Khanid Navy Assembly Plant","sellStation":"5-FGQI V - Moon 13 - Intaki Syndicate Academy","roi":28.57,"volumeAvailable":271597,"maxProfit":271597},{"typeId":3687,"itemName":"Electronic Parts","buyPrice":699,"sellPrice":894.37,"profitPerUnit":195.37,"buyStation":"Irmalin VIII - Moon 13 - Royal Khanid Navy Testing Facilities","sellStation":"VSIG-K V - Moon 8 - TransStellar Shipping Storage","roi":27.95,"volumeAvailable":7610,"maxProfit":1486765.7},{"typeId":36,"itemName":"Mexallon","buyPrice":60,"sellPrice":76,"profitPerUnit":16,"buyStation":"Ashi VI - Moon 5 - Khanid Transport Storage","sellStation":"I0AB-R VI - Intaki Space Police Assembly Plant","roi":26.67,"volumeAvailable":2022,"maxProfit":32352},{"typeId":9852,"itemName":"Tobacco","buyPrice":44.4,"sellPrice":55.2,"profitPerUnit":10.8,"buyStation":"Kihtaled VIII - Royal Khanid Navy Assembly Plant","sellStation":"0EK-NJ V - Caldari Navy Anchorage","roi":24.32,"volumeAvailable":74,"maxProfit":799.2},{"typeId":9852,"itemName":"Tobacco","buyPrice":44.4,"sellPrice":55.2,"profitPerUnit":10.8,"buyStation":"Badivefi VI - Moon 2 - Royal Khanid Navy Logistic Support","sellStation":"0EK-NJ V - Caldari Navy Anchorage","roi":24.32,"volumeAvailable":74,"maxProfit":799.2},{"typeId":2048,"itemName":"Damage Control II","buyPrice":161300,"sellPrice":200100,"profitPerUnit":38800,"buyStation":"Irmalin VIII - Moon 13 - Royal Khanid Navy Testing Facilities","sellStation":"6-CZ49 VI - Moon 6 - Intaki Syndicate Bureau","roi":24.05,"volumeAvailable":1,"maxProfit":38800},{"typeId":3687,"itemName":"Electronic Parts","buyPrice":750.1,"sellPrice":894.37,"profitPerUnit":144.27,"buyStation":"Khanid Prime V - Moon 1 - Khanid Innovation Factory","sellStation":"VSIG-K V - Moon 8 - TransStellar Shipping Storage","roi":19.23,"volumeAvailable":7,"maxProfit":1009.89},{"typeId":3687,"itemName":"Electronic Parts","buyPrice":750.1,"sellPrice":894.37,"profitPerUnit":144.27,"buyStation":"Kihtaled VIII - Moon 7 - Royal Khanid Navy Assembly Plant","sellStation":"VSIG-K V - Moon 8 - TransStellar Shipping Storage","roi":19.23,"volumeAvailable":12,"maxProfit":1731.24},{"typeId":35,"itemName":"Pyerite","buyPrice":21,"sellPrice":25,"profitPerUnit":4,"buyStation":"Chamemi VI - Moon 1 - Royal Khanid Navy Assembly Plant","sellStation":"98Q-8O VII - Moon 16 - Intaki Commerce Trading Post","roi":19.05,"volumeAvailable":24366,"maxProfit":97464},{"typeId":35,"itemName":"Pyerite","buyPrice":21,"sellPrice":25,"profitPerUnit":4,"buyStation":"Danera III - Moon 3 - Khanid Transport Storage","sellStation":"98Q-8O VII - Moon 16 - Intaki Commerce Trading Post","roi":19.05,"volumeAvailable":241912,"maxProfit":967648},{"typeId":38,"itemName":"Nocxium","buyPrice":860,"sellPrice":1000,"profitPerUnit":140,"buyStation":"Irmalin VIII - Moon 13 - Royal Khanid Navy Testing Facilities","sellStation":"98Q-8O VII - Moon 16 - Intaki Commerce Trading Post","roi":16.28,"volumeAvailable":3481,"maxProfit":487340},{"typeId":37,"itemName":"Isogen","buyPrice":193,"sellPrice":220,"profitPerUnit":27,"buyStation":"Irmalin VIII - Moon 13 - Royal Khanid Navy Testing Facilities","sellStation":"98Q-8O VII - Moon 16 - Intaki Commerce Trading Post","roi":13.99,"volumeAvailable":9062,"maxProfit":244674},{"typeId":37,"itemName":"Isogen","buyPrice":194,"sellPrice":220,"profitPerUnit":26,"buyStation":"Gehi IX - Moon 4 - Royal Khanid Navy Assembly Plant","sellStation":"98Q-8O VII - Moon 16 - Intaki Commerce Trading Post","roi":13.4,"volumeAvailable":11314,"maxProfit":294164},{"typeId":37,"itemName":"Isogen","buyPrice":194,"sellPrice":220,"profitPerUnit":26,"buyStation":"Zephan VIII - Moon 1 - Khanid Transport Storage","sellStation":"98Q-8O VII - Moon 16 - Intaki Commerce Trading Post","roi":13.4,"volumeAvailable":20000,"maxProfit":520000},{"typeId":9852,"itemName":"Tobacco","buyPrice":48.76,"sellPrice":55.2,"profitPerUnit":6.44,"buyStation":"Palas II - Royal Khanid Navy Assembly Plant","sellStation":"0EK-NJ V - Caldari Navy Anchorage","roi":13.21,"volumeAvailable":74,"maxProfit":476.56},{"typeId":34,"itemName":"Tritanium","buyPrice":3.98,"sellPrice":4.5,"profitPerUnit":0.52,"buyStation":"Bashyam X - Moon 7 - Khanid Transport Storage","sellStation":"5-FGQI V - Moon 13 - Intaki Syndicate Academy","roi":13.07,"volumeAvailable":271597,"maxProfit":141230.44},{"typeId":37,"itemName":"Isogen","buyPrice":195,"sellPrice":220,"profitPerUnit":25,"buyStation":"Parses VI - Moon 11 - Royal Khanid Navy Assembly Plant","sellStation":"98Q-8O VII - Moon 16 - Intaki Commerce Trading Post","roi":12.82,"volumeAvailable":7793,"maxProfit":194825},{"typeId":30371,"itemName":"Fullerite-C60","buyPrice":3900,"sellPrice":4400,"profitPerUnit":500,"buyStation":"Neyi VII - Moon 7 - CONCORD Academy","sellStation":"98Q-8O VII - Moon 16 - Intaki Commerce Trading Post","roi":12.82,"volumeAvailable":1000,"maxProfit":500000},{"typeId":17889,"itemName":"Hydrogen Isotopes","buyPrice":888,"sellPrice":1000,"profitPerUnit":112,"buyStation":"Agil VI - Moon 2 - CONCORD Logistic Support","sellStation":"CIS-7X IX - Moon 6 - Intaki Syndicate Bureau","roi":12.61,"volumeAvailable":20000,"maxProfit":2240000},{"typeId":34,"itemName":"Tritanium","buyPrice":4,"sellPrice":4.5,"profitPerUnit":0.5,"buyStation":"Badivefi VI - Moon 2 - Royal Khanid Navy Logistic Support","sellStation":"5-FGQI V - Moon 13 - Intaki Syndicate Academy","roi":12.5,"volumeAvailable":271597,"maxProfit":135798.5},{"typeId":34,"itemName":"Tritanium","buyPrice":4,"sellPrice":4.5,"profitPerUnit":0.5,"buyStation":"Agil VI - Moon 2 - CONCORD Logistic Support","sellStation":"5-FGQI V - Moon 13 - Intaki Syndicate Academy","roi":12.5,"volumeAvailable":271597,"maxProfit":135798.5},{"typeId":34,"itemName":"Tritanium","buyPrice":4,"sellPrice":4.5,"profitPerUnit":0.5,"buyStation":"Danera III - Moon 3 - Khanid Transport Storage","sellStation":"5-FGQI V - Moon 13 - Intaki Syndicate Academy","roi":12.5,"volumeAvailable":271597,"maxProfit":135798.5},{"typeId":2185,"itemName":"Hammerhead II","buyPrice":400000,"sellPrice":450000,"profitPerUnit":50000,"buyStation":"Gehi IX - Moon 4 - Royal Khanid Navy Assembly Plant","sellStation":"35-RK9 IX - Moon 4 - Intaki Syndicate Bureau","roi":12.5,"volumeAvailable":6,"maxProfit":300000},{"typeId":34,"itemName":"Tritanium","buyPrice":4.03,"sellPrice":4.5,"profitPerUnit":0.47,"buyStation":"Chamemi VI - Moon 1 - Royal Khanid Navy Assembly Plant","sellStation":"5-FGQI V - Moon 13 - Intaki Syndicate Academy","roi":11.66,"volumeAvailable":271597,"maxProfit":127650.59},{"typeId":10690,"itemName":"125mm Carbide Railgun I","buyPrice":4485,"sellPrice":5000,"profitPerUnit":515,"buyStation":"Kihtaled VIII - Moon 17 - CONCORD Bureau","sellStation":"98Q-8O VII - Moon 16 - Intaki Commerce Trading Post","roi":11.48,"volumeAvailable":1,"maxProfit":515},{"typeId":38,"itemName":"Nocxium","buyPrice":900,"sellPrice":1000,"profitPerUnit":100,"buyStation":"Khanid Prime V - Moon 1 - Khanid Innovation Factory","sellStation":"98Q-8O VII - Moon 16 - Intaki Commerce Trading Post","roi":11.11,"volumeAvailable":3059,"maxProfit":305900},{"typeId":34,"itemName":"Tritanium","buyPrice":4.09,"sellPrice":4.5,"profitPerUnit":0.41,"buyStation":"Ibani VI - Moon 15 - Khanid Transport Storage","sellStation":"5-FGQI V - Moon 13 - Intaki Syndicate Academy","roi":10.02,"volumeAvailable":271597,"maxProfit":111354.77},{"typeId":34,"itemName":"Tritanium","buyPrice":4.09,"sellPrice":4.5,"profitPerUnit":0.41,"buyStation":"Kahah I - Khanid Transport Storage","sellStation":"5-FGQI V - Moon 13 - Intaki Syndicate Academy","roi":10.02,"volumeAvailable":271597,"maxProfit":111354.77},{"typeId":34,"itemName":"Tritanium","buyPrice":4.09,"sellPrice":4.5,"profitPerUnit":0.41,"buyStation":"Vezila IV - Royal Khanid Navy Assembly Plant","sellStation":"5-FGQI V - Moon 13 - Intaki Syndicate Academy","roi":10.02,"volumeAvailable":271597,"maxProfit":111354.77},{"typeId":36,"itemName":"Mexallon","buyPrice":69.69,"sellPrice":76,"profitPerUnit":6.31,"buyStation":"Badivefi VI - Moon 2 - Royal Khanid Navy Logistic Support","sellStation":"I0AB-R VI - Intaki Space Police Assembly Plant","roi":9.05,"volumeAvailable":65000,"maxProfit":410150},{"typeId":34,"itemName":"Tritanium","buyPrice":4.15,"sellPrice":4.5,"profitPerUnit":0.35,"buyStation":"Kihtaled VIII - CONCORD Bureau","sellStation":"5-FGQI V - Moon 13 - Intaki Syndicate Academy","roi":8.43,"volumeAvailable":271597,"maxProfit":95058.95},{"typeId":30370,"itemName":"Fullerite-C50","buyPrice":4400,"sellPrice":4750,"profitPerUnit":350,"buyStation":"Irmalin VIII - Moon 13 - Royal Khanid Navy Testing Facilities","sellStation":"98Q-8O VII - Moon 16 - Intaki Commerce Trading Post","roi":7.95,"volumeAvailable":700,"maxProfit":245000},{"typeId":38,"itemName":"Nocxium","buyPrice":939.3,"sellPrice":1000,"profitPerUnit":60.7,"buyStation":"Zephan VIII - Moon 1 - Khanid Transport Storage","sellStation":"98Q-8O VII - Moon 16 - Intaki Commerce Trading Post","roi":6.46,"volumeAvailable":3653,"maxProfit":221737.1},{"typeId":34,"itemName":"Tritanium","buyPrice":4.24,"sellPrice":4.5,"profitPerUnit":0.26,"buyStation":"Palas VII - Moon 11 - Royal Khanid Navy Assembly Plant","sellStation":"5-FGQI V - Moon 13 - Intaki Syndicate Academy","roi":6.13,"volumeAvailable":271597,"maxProfit":70615.22},{"typeId":1228,"itemName":"Scordite","buyPrice":18.9,"sellPrice":20,"profitPerUnit":1.1,"buyStation":"Badivefi VI - Moon 2 - Royal Khanid Navy Logistic Support","sellStation":"98Q-8O VII - Moon 16 - Intaki Commerce Trading Post","roi":5.82,"volumeAvailable":6034,"maxProfit":6637.4},{"typeId":4393,"itemName":"Drone Damage Amplifier I","buyPrice":95990,"sellPrice":100000,"profitPerUnit":4010,"buyStation":"Irmalin VIII - Moon 13 - Royal Khanid Navy Testing Facilities","sellStation":"98Q-8O VII - Moon 16 - Intaki Commerce Trading Post","roi":4.18,"volumeAvailable":10,"maxProfit":40100},{"typeId":35,"itemName":"Pyerite","buyPrice":24,"sellPrice":25,"profitPerUnit":1,"buyStation":"Palas II - Royal Khanid Navy Assembly Plant","sellStation":"98Q-8O VII - Moon 16 - Intaki Commerce Trading Post","roi":4.17,"volumeAvailable":241912,"maxProfit":241912},{"typeId":567,"itemName":"Dual 150mm Railgun I","buyPrice":97000,"sellPrice":100000,"profitPerUnit":3000,"buyStation":"Badivefi VIII - Moon 10 - Royal Khanid Navy Logistic Support","sellStation":"98Q-8O VII - Moon 16 - Intaki Commerce Trading Post","roi":3.09,"volumeAvailable":10,"maxProfit":30000},{"typeId":4393,"itemName":"Drone Damage Amplifier I","buyPrice":99000,"sellPrice":100000,"profitPerUnit":1000,"buyStation":"Badivefi VI - Moon 2 - Royal Khanid Navy Logistic Support","sellStation":"98Q-8O VII - Moon 16 - Intaki Commerce Trading Post","roi":1.01,"volumeAvailable":10,"maxProfit":10000}]}