{"lastUpdated":"2026-04-27T07:55:01.546Z","buyRegion":10000022,"sellRegion":10000042,"buyRegionName":"Stain","sellRegionName":"Metropolis","opportunities":[{"typeId":25598,"itemName":"Tripped Power Circuit","buyPrice":1000,"sellPrice":3709,"profitPerUnit":2709,"buyStation":"HM-UVD VII - Moon 5 - True Creations Shipyard","sellStation":"Hek VIII - Moon 12 - Boundless Creation Factory","roi":270.9,"volumeAvailable":923,"maxProfit":2500407},{"typeId":25598,"itemName":"Tripped Power Circuit","buyPrice":1006,"sellPrice":3709,"profitPerUnit":2703,"buyStation":"A4UG-O VII - Moon 16 - True Creations Shipyard","sellStation":"Hek VIII - Moon 12 - Boundless Creation Factory","roi":268.69,"volumeAvailable":7,"maxProfit":18921},{"typeId":9826,"itemName":"Carbon","buyPrice":111.1,"sellPrice":385.88,"profitPerUnit":274.78,"buyStation":"4GQ-XQ IX - Moon 1 - True Creations Shipyard","sellStation":"Hilfhurmur X - Wiyrkomi Corporation Factory","roi":247.33,"volumeAvailable":4,"maxProfit":1099.12},{"typeId":25601,"itemName":"Fried Interface Circuit","buyPrice":1003,"sellPrice":3406,"profitPerUnit":2403,"buyStation":"A4UG-O VII - Moon 16 - True Creations Shipyard","sellStation":"Hek VIII - Moon 12 - Boundless Creation Factory","roi":239.58,"volumeAvailable":6,"maxProfit":14418},{"typeId":11317,"itemName":"800mm Rolled Tungsten Compact Plates","buyPrice":100000,"sellPrice":283200,"profitPerUnit":183200,"buyStation":"T-8UOF VII - Moon 2 - True Power Logistic Support","sellStation":"Nakugard V - Republic University","roi":183.2,"volumeAvailable":1,"maxProfit":183200},{"typeId":16671,"itemName":"Titanium Carbide","buyPrice":50,"sellPrice":115,"profitPerUnit":65,"buyStation":"HM-UVD VII - Moon 5 - True Creations Shipyard","sellStation":"Elgoi VI - Moon 1 - Eifyr and Co. Biotech Production","roi":130,"volumeAvailable":10000,"maxProfit":650000},{"typeId":33195,"itemName":"Spatial Attunement Unit","buyPrice":3500,"sellPrice":7514,"profitPerUnit":4014,"buyStation":"A4UG-O VII - Moon 16 - True Creations Shipyard","sellStation":"Hek VIII - Moon 12 - Boundless Creation Factory","roi":114.69,"volumeAvailable":3,"maxProfit":12042},{"typeId":25597,"itemName":"Damaged Artificial Neural Network","buyPrice":100,"sellPrice":191,"profitPerUnit":91,"buyStation":"A4UG-O VII - Moon 16 - True Creations Shipyard","sellStation":"Hek VIII - Moon 12 - Boundless Creation Factory","roi":91,"volumeAvailable":7,"maxProfit":637},{"typeId":3771,"itemName":"Ectoplasm","buyPrice":720,"sellPrice":1177.2,"profitPerUnit":457.2,"buyStation":"DSS-EZ IV - Moon 1 - True Power Refinery","sellStation":"Elgoi VI - Moon 1 - Eifyr and Co. Biotech Production","roi":63.5,"volumeAvailable":9624,"maxProfit":4400092.8},{"typeId":16275,"itemName":"Strontium Clathrates","buyPrice":2500,"sellPrice":3450,"profitPerUnit":950,"buyStation":"KP-FQ1 III - True Creations Assembly Plant","sellStation":"Eram VIII - Moon 17 - The Leisure Group Development Studio","roi":38,"volumeAvailable":551,"maxProfit":523450},{"typeId":20411,"itemName":"Datacore - High Energy Physics","buyPrice":75000,"sellPrice":94540,"profitPerUnit":19540,"buyStation":"HM-UVD VII - Moon 5 - True Creations Shipyard","sellStation":"Hek VIII - Moon 12 - Boundless Creation Factory","roi":26.05,"volumeAvailable":128,"maxProfit":2501120},{"typeId":35661,"itemName":"500MN Y-T8 Compact Microwarpdrive","buyPrice":405100,"sellPrice":501000,"profitPerUnit":95900,"buyStation":"RLDS-R I - True Creations Shipyard","sellStation":"Nakugard V - Republic University","roi":23.67,"volumeAvailable":2,"maxProfit":191800},{"typeId":38,"itemName":"Nocxium","buyPrice":800,"sellPrice":980.9,"profitPerUnit":180.9,"buyStation":"4GQ-XQ IX - Moon 1 - True Creations Shipyard","sellStation":"Ryddinjorn VI - Moon 2 - Pator Tech School","roi":22.61,"volumeAvailable":1,"maxProfit":180.9},{"typeId":25611,"itemName":"Current Pump","buyPrice":58000,"sellPrice":71070,"profitPerUnit":13070,"buyStation":"O5Y3-W VI - Moon 1 - True Power Logistic Support","sellStation":"Hek VIII - Moon 12 - Boundless Creation Factory","roi":22.53,"volumeAvailable":13,"maxProfit":169910},{"typeId":20413,"itemName":"Datacore - Laser Physics","buyPrice":75000,"sellPrice":91700,"profitPerUnit":16700,"buyStation":"HM-UVD VII - Moon 5 - True Creations Shipyard","sellStation":"Hek VIII - Moon 12 - Boundless Creation Factory","roi":22.27,"volumeAvailable":51,"maxProfit":851700},{"typeId":3683,"itemName":"Oxygen","buyPrice":250,"sellPrice":302.6,"profitPerUnit":52.6,"buyStation":"HM-UVD VII - Moon 5 - True Creations Shipyard","sellStation":"Hek VIII - Moon 12 - Boundless Creation Factory","roi":21.04,"volumeAvailable":12011,"maxProfit":631778.6},{"typeId":34,"itemName":"Tritanium","buyPrice":3,"sellPrice":3.35,"profitPerUnit":0.35,"buyStation":"I-ME3L V - Moon 1 - True Creations Testing Facilities","sellStation":"Ryddinjorn VI - Moon 2 - Pator Tech School","roi":11.67,"volumeAvailable":1,"maxProfit":0.35},{"typeId":16272,"itemName":"Heavy Water","buyPrice":100,"sellPrice":111,"profitPerUnit":11,"buyStation":"TG-Z23 III - Moon 8 - True Power Logistic Support","sellStation":"Olbra I - Pator Tech School","roi":11,"volumeAvailable":8834,"maxProfit":97174},{"typeId":16272,"itemName":"Heavy Water","buyPrice":100,"sellPrice":111,"profitPerUnit":11,"buyStation":"I-ME3L V - Moon 1 - True Creations Testing Facilities","sellStation":"Olbra I - Pator Tech School","roi":11,"volumeAvailable":8834,"maxProfit":97174},{"typeId":16272,"itemName":"Heavy Water","buyPrice":100,"sellPrice":111,"profitPerUnit":11,"buyStation":"4GQ-XQ IX - Moon 1 - True Creations Shipyard","sellStation":"Olbra I - Pator Tech School","roi":11,"volumeAvailable":8834,"maxProfit":97174},{"typeId":11285,"itemName":"Cap Booster 200","buyPrice":5000,"sellPrice":5500,"profitPerUnit":500,"buyStation":"4GQ-XQ IX - Moon 1 - True Creations Shipyard","sellStation":"Arlulf III - Moon 11 - Republic Justice Department Law School","roi":10,"volumeAvailable":30,"maxProfit":15000},{"typeId":17889,"itemName":"Hydrogen Isotopes","buyPrice":500,"sellPrice":544.2,"profitPerUnit":44.2,"buyStation":"ZG8Q-N VII - Moon 6 - True Creations Testing Facilities","sellStation":"Odebeinn V - Moon 5 - Kaalakiota Corporation Factory","roi":8.84,"volumeAvailable":2818,"maxProfit":124555.6},{"typeId":7171,"itemName":"Tachyon Modulated Energy Beam I","buyPrice":500000,"sellPrice":521300,"profitPerUnit":21300,"buyStation":"RLDS-R I - True Creations Shipyard","sellStation":"Nakugard V - Republic University","roi":4.26,"volumeAvailable":1,"maxProfit":21300},{"typeId":16273,"itemName":"Liquid Ozone","buyPrice":70,"sellPrice":72.01,"profitPerUnit":2.01,"buyStation":"KP-FQ1 III - True Creations Assembly Plant","sellStation":"Eram VIII - Moon 17 - The Leisure Group Development Studio","roi":2.87,"volumeAvailable":3,"maxProfit":6.03},{"typeId":37,"itemName":"Isogen","buyPrice":300,"sellPrice":307.5,"profitPerUnit":7.5,"buyStation":"I-ME3L V - Moon 1 - True Creations Testing Facilities","sellStation":"Hek VIII - Moon 12 - Boundless Creation Factory","roi":2.5,"volumeAvailable":8534,"maxProfit":64005},{"typeId":5839,"itemName":"IFFA Compact Damage Control","buyPrice":2990000,"sellPrice":3054000,"profitPerUnit":64000,"buyStation":"4GQ-XQ IX - Moon 1 - True Creations Shipyard","sellStation":"Hek VIII - Moon 12 - Boundless Creation Factory","roi":2.14,"volumeAvailable":2,"maxProfit":128000},{"typeId":22778,"itemName":"Warp Disrupt Probe","buyPrice":75100,"sellPrice":76000,"profitPerUnit":900,"buyStation":"W-VXL9 IV - Moon 21 - True Creations Assembly Plant","sellStation":"Hek VIII - Moon 12 - Boundless Creation Factory","roi":1.2,"volumeAvailable":15,"maxProfit":13500},{"typeId":12565,"itemName":"Conflagration S","buyPrice":60980,"sellPrice":61030,"profitPerUnit":50,"buyStation":"4GQ-XQ IX - Moon 1 - True Creations Shipyard","sellStation":"Hek VIII - Moon 12 - Boundless Creation Factory","roi":0.08,"volumeAvailable":9,"maxProfit":450}]}