{"lastUpdated":"2026-04-27T07:55:00.839Z","buyRegion":10000043,"sellRegion":10000001,"buyRegionName":"Domain","sellRegionName":"Derelik","opportunities":[{"typeId":211,"itemName":"Inferno Light Missile","buyPrice":0.02,"sellPrice":5,"profitPerUnit":4.98,"buyStation":"Deepari II - Imperial Academy","sellStation":"Kasrasi IX - Moon 7 - DED Assembly Plant","roi":24900,"volumeAvailable":100,"maxProfit":498},{"typeId":244,"itemName":"Xray S","buyPrice":1.01,"sellPrice":102,"profitPerUnit":100.99,"buyStation":"Horir III - Moon 1 - Imperial Academy","sellStation":"Faspera I - Ammatar Fleet Testing Facilities","roi":9999.01,"volumeAvailable":1,"maxProfit":100.99},{"typeId":182,"itemName":"Titanium Sabot S","buyPrice":0.03,"sellPrice":1,"profitPerUnit":0.97,"buyStation":"Nakri V - Moon 5 - Sarum Family Assembly Plant","sellStation":"Gelhan V - Moon 10 - DED Logistic Support","roi":3233.33,"volumeAvailable":100,"maxProfit":97},{"typeId":6527,"itemName":"Ta3 Compact Ship Scanner","buyPrice":107.2,"sellPrice":2500,"profitPerUnit":2392.8,"buyStation":"Amarr VIII (Oris) - Emperor Family Academy","sellStation":"Kasrasi IX - Moon 7 - DED Assembly Plant","roi":2232.09,"volumeAvailable":1,"maxProfit":2392.8},{"typeId":5649,"itemName":"Mark I Compact Reinforced Bulkheads","buyPrice":150.1,"sellPrice":2500,"profitPerUnit":2349.9,"buyStation":"Amarr VIII (Oris) - Emperor Family Academy","sellStation":"Kasrasi IX - Moon 7 - DED Assembly Plant","roi":1565.56,"volumeAvailable":2,"maxProfit":4699.8},{"typeId":3828,"itemName":"Construction Blocks","buyPrice":509.3,"sellPrice":6750,"profitPerUnit":6240.7,"buyStation":"Ziriert VIII - Moon 3 - Zoar and Sons Factory","sellStation":"Kasrasi IX - Moon 7 - DED Assembly Plant","roi":1225.35,"volumeAvailable":16,"maxProfit":99851.2},{"typeId":9842,"itemName":"Miniature Electronics","buyPrice":502.4,"sellPrice":5984,"profitPerUnit":5481.6,"buyStation":"Ziriert VIII - Moon 3 - Zoar and Sons Factory","sellStation":"Kasrasi IX - Moon 7 - DED Assembly Plant","roi":1091.08,"volumeAvailable":2,"maxProfit":10963.2},{"typeId":46300,"itemName":"Lavish Vanadinite","buyPrice":35,"sellPrice":395.9,"profitPerUnit":360.9,"buyStation":"Amarr VIII (Oris) - Emperor Family Academy","sellStation":"Sasta VI - Moon 3 - Ammatar Fleet Assembly Plant","roi":1031.14,"volumeAvailable":74,"maxProfit":26706.6},{"typeId":15626,"itemName":"Republic Fleet Midshipman Insignia II","buyPrice":812.2,"sellPrice":8000,"profitPerUnit":7187.8,"buyStation":"Penirgman IX - Moon 3 - Ministry of Internal Order Assembly Plant","sellStation":"Hothomouh VII - Moon 2 - Ammatar Fleet Assembly Plant","roi":884.98,"volumeAvailable":10,"maxProfit":71878},{"typeId":243,"itemName":"Ultraviolet S","buyPrice":11.01,"sellPrice":100,"profitPerUnit":88.99,"buyStation":"Horir III - Moon 1 - Imperial Academy","sellStation":"Faspera I - Ammatar Fleet Testing Facilities","roi":808.27,"volumeAvailable":2,"maxProfit":177.98},{"typeId":5869,"itemName":"Suppressed Targeting System I","buyPrice":394.6,"sellPrice":2500,"profitPerUnit":2105.4,"buyStation":"Amarr VIII (Oris) - Emperor Family Academy","sellStation":"Kasrasi IX - Moon 7 - DED Assembly Plant","roi":533.55,"volumeAvailable":1,"maxProfit":2105.4},{"typeId":5869,"itemName":"Suppressed Targeting System I","buyPrice":394.7,"sellPrice":2500,"profitPerUnit":2105.3,"buyStation":"Amarr VI (Zorast) - Moon 2 - Theology Council Tribunal","sellStation":"Kasrasi IX - Moon 7 - DED Assembly Plant","roi":533.39,"volumeAvailable":1,"maxProfit":2105.3},{"typeId":19812,"itemName":"Parallel Enduring Target Painter","buyPrice":416.3,"sellPrice":2500,"profitPerUnit":2083.7,"buyStation":"Amarr VIII (Oris) - Emperor Family Academy","sellStation":"Kasrasi IX - Moon 7 - DED Assembly Plant","roi":500.53,"volumeAvailable":13,"maxProfit":27088.1},{"typeId":5869,"itemName":"Suppressed Targeting System I","buyPrice":454.2,"sellPrice":2500,"profitPerUnit":2045.8,"buyStation":"Youl VII - Moon 10 - Amarr Navy Logistic Support","sellStation":"Kasrasi IX - Moon 7 - DED Assembly Plant","roi":450.42,"volumeAvailable":1,"maxProfit":2045.8},{"typeId":16683,"itemName":"Ferrogel","buyPrice":1281,"sellPrice":6911,"profitPerUnit":5630,"buyStation":"Bahromab V - Ministry of Assessment Bureau Offices","sellStation":"Sasta VI - Moon 3 - Ammatar Fleet Assembly Plant","roi":439.5,"volumeAvailable":1,"maxProfit":5630},{"typeId":22542,"itemName":"Mining Laser Upgrade I","buyPrice":15000,"sellPrice":65000,"profitPerUnit":50000,"buyStation":"Misaba V - Moon 3 - Zoar and Sons Factory","sellStation":"Dysa II - Ammatar Fleet Assembly Plant","roi":333.33,"volumeAvailable":1,"maxProfit":50000},{"typeId":3689,"itemName":"Mechanical Parts","buyPrice":1482,"sellPrice":5771,"profitPerUnit":4289,"buyStation":"Bahromab V - Ministry of Assessment Bureau Offices","sellStation":"Kasrasi IX - Moon 7 - DED Assembly Plant","roi":289.41,"volumeAvailable":5,"maxProfit":21445},{"typeId":6527,"itemName":"Ta3 Compact Ship Scanner","buyPrice":719.9,"sellPrice":2500,"profitPerUnit":1780.1,"buyStation":"Misaba V - Moon 3 - Zoar and Sons Factory","sellStation":"Kasrasi IX - Moon 7 - DED Assembly Plant","roi":247.27,"volumeAvailable":1,"maxProfit":1780.1},{"typeId":15625,"itemName":"Republic Fleet Midshipman Insignia I","buyPrice":1394,"sellPrice":4500,"profitPerUnit":3106,"buyStation":"Penirgman IX - Moon 3 - Ministry of Internal Order Assembly Plant","sellStation":"Hasateem VI - Moon 12 - Thukker Mix Factory","roi":222.81,"volumeAvailable":7,"maxProfit":21742},{"typeId":15628,"itemName":"Republic Fleet Private Insignia I","buyPrice":7022,"sellPrice":20000,"profitPerUnit":12978,"buyStation":"Penirgman IX - Moon 3 - Ministry of Internal Order Assembly Plant","sellStation":"Hasateem VI - Moon 12 - Thukker Mix Factory","roi":184.82,"volumeAvailable":2,"maxProfit":25956},{"typeId":17368,"itemName":"Station Warehouse Container","buyPrice":2000000,"sellPrice":5000000,"profitPerUnit":3000000,"buyStation":"Misaba V - Moon 3 - Zoar and Sons Factory","sellStation":"Tidacha VIII - Moon 13 - Ammatar Consulate Bureau","roi":150,"volumeAvailable":1,"maxProfit":3000000},{"typeId":17368,"itemName":"Station Warehouse Container","buyPrice":2201000,"sellPrice":5000000,"profitPerUnit":2799000,"buyStation":"Sharhelund VIII - Moon 5 - Sarum Family Assembly Plant","sellStation":"Tidacha VIII - Moon 13 - Ammatar Consulate Bureau","roi":127.17,"volumeAvailable":1,"maxProfit":2799000},{"typeId":17368,"itemName":"Station Warehouse Container","buyPrice":2222000,"sellPrice":5000000,"profitPerUnit":2778000,"buyStation":"Sieh II - Moon 1 - Joint Harvesting Plantation","sellStation":"Tidacha VIII - Moon 13 - Ammatar Consulate Bureau","roi":125.02,"volumeAvailable":1,"maxProfit":2778000},{"typeId":22542,"itemName":"Mining Laser Upgrade I","buyPrice":29000,"sellPrice":65000,"profitPerUnit":36000,"buyStation":"Joppaya IX - Moon 9 - Ardishapur Family Bureau","sellStation":"Dysa II - Ammatar Fleet Assembly Plant","roi":124.14,"volumeAvailable":4,"maxProfit":144000},{"typeId":6527,"itemName":"Ta3 Compact Ship Scanner","buyPrice":1131,"sellPrice":2500,"profitPerUnit":1369,"buyStation":"Bhizheba IX - Moon 1 - Amarr Navy Logistic Support","sellStation":"Kasrasi IX - Moon 7 - DED Assembly Plant","roi":121.04,"volumeAvailable":3,"maxProfit":4107},{"typeId":202,"itemName":"Mjolnir Cruise Missile","buyPrice":5.01,"sellPrice":10.55,"profitPerUnit":5.54,"buyStation":"Ziriert VIII - Moon 3 - Zoar and Sons Factory","sellStation":"Podion VIII - Moon 15 - Nefantar Miner Association Mining Outpost","roi":110.58,"volumeAvailable":100,"maxProfit":554},{"typeId":41,"itemName":"Garbage","buyPrice":14,"sellPrice":28.34,"profitPerUnit":14.34,"buyStation":"Zhilshinou IX - Imperial Armaments Factory","sellStation":"Irshah VIII - Moon 9 - Trust Partners Trading Post","roi":102.43,"volumeAvailable":5050,"maxProfit":72417},{"typeId":41,"itemName":"Garbage","buyPrice":14,"sellPrice":28.34,"profitPerUnit":14.34,"buyStation":"Ziriert VIII - Moon 12 - Imperial Armaments Factory","sellStation":"Irshah VIII - Moon 9 - Trust Partners Trading Post","roi":102.43,"volumeAvailable":5050,"maxProfit":72417},{"typeId":41,"itemName":"Garbage","buyPrice":14,"sellPrice":28.34,"profitPerUnit":14.34,"buyStation":"Safizon II - Moon 1 - Amarr Navy Assembly Plant","sellStation":"Irshah VIII - Moon 9 - Trust Partners Trading Post","roi":102.43,"volumeAvailable":70,"maxProfit":1003.8},{"typeId":41,"itemName":"Garbage","buyPrice":14,"sellPrice":28.34,"profitPerUnit":14.34,"buyStation":"Youl VII - Moon 10 - Amarr Navy Logistic Support","sellStation":"Irshah VIII - Moon 9 - Trust Partners Trading Post","roi":102.43,"volumeAvailable":70,"maxProfit":1003.8},{"typeId":41,"itemName":"Garbage","buyPrice":14,"sellPrice":28.34,"profitPerUnit":14.34,"buyStation":"Sharhelund VI - Moon 3 - Amarr Navy Assembly Plant","sellStation":"Irshah VIII - Moon 9 - Trust Partners Trading Post","roi":102.43,"volumeAvailable":70,"maxProfit":1003.8},{"typeId":41,"itemName":"Garbage","buyPrice":14,"sellPrice":28.34,"profitPerUnit":14.34,"buyStation":"Zaimeth IX - Moon 15 - Amarr Navy Assembly Plant","sellStation":"Irshah VIII - Moon 9 - Trust Partners Trading Post","roi":102.43,"volumeAvailable":70,"maxProfit":1003.8},{"typeId":41,"itemName":"Garbage","buyPrice":14,"sellPrice":28.34,"profitPerUnit":14.34,"buyStation":"Nalu VII - Moon 7 - DED Testing Facilities","sellStation":"Irshah VIII - Moon 9 - Trust Partners Trading Post","roi":102.43,"volumeAvailable":65,"maxProfit":932.1},{"typeId":41,"itemName":"Garbage","buyPrice":14,"sellPrice":28.34,"profitPerUnit":14.34,"buyStation":"Sahdil III - DED Logistic Support","sellStation":"Irshah VIII - Moon 9 - Trust Partners Trading Post","roi":102.43,"volumeAvailable":65,"maxProfit":932.1},{"typeId":41,"itemName":"Garbage","buyPrice":14.02,"sellPrice":28.34,"profitPerUnit":14.32,"buyStation":"Akhragan VIII - Moon 3 - Imperial Armaments Factory","sellStation":"Irshah VIII - Moon 9 - Trust Partners Trading Post","roi":102.14,"volumeAvailable":5050,"maxProfit":72316},{"typeId":41,"itemName":"Garbage","buyPrice":14.03,"sellPrice":28.34,"profitPerUnit":14.31,"buyStation":"Ana IX - Moon 19 - Imperial Armaments Factory","sellStation":"Irshah VIII - Moon 9 - Trust Partners Trading Post","roi":102,"volumeAvailable":5050,"maxProfit":72265.5},{"typeId":41,"itemName":"Garbage","buyPrice":14.03,"sellPrice":28.34,"profitPerUnit":14.31,"buyStation":"Mikhir V - Moon 10 - Imperial Armaments Factory","sellStation":"Irshah VIII - Moon 9 - Trust Partners Trading Post","roi":102,"volumeAvailable":5050,"maxProfit":72265.5},{"typeId":41,"itemName":"Garbage","buyPrice":14.03,"sellPrice":28.34,"profitPerUnit":14.31,"buyStation":"Mikhir V - Moon 23 - Imperial Armaments Factory","sellStation":"Irshah VIII - Moon 9 - Trust Partners Trading Post","roi":102,"volumeAvailable":5050,"maxProfit":72265.5},{"typeId":17368,"itemName":"Station Warehouse Container","buyPrice":2480000,"sellPrice":5000000,"profitPerUnit":2520000,"buyStation":"Isamm IX - Moon 15 - Imperial Chancellor Bureau Offices","sellStation":"Tidacha VIII - Moon 13 - Ammatar Consulate Bureau","roi":101.61,"volumeAvailable":1,"maxProfit":2520000},{"typeId":41,"itemName":"Garbage","buyPrice":14.14,"sellPrice":28.34,"profitPerUnit":14.2,"buyStation":"Khopa VII - Moon 3 - Imperial Armaments Factory","sellStation":"Irshah VIII - Moon 9 - Trust Partners Trading Post","roi":100.42,"volumeAvailable":5050,"maxProfit":71710},{"typeId":41,"itemName":"Garbage","buyPrice":14.15,"sellPrice":28.34,"profitPerUnit":14.19,"buyStation":"Hoshoun VII - Moon 17 - Imperial Armaments Warehouse","sellStation":"Irshah VIII - Moon 9 - Trust Partners Trading Post","roi":100.28,"volumeAvailable":5050,"maxProfit":71659.5},{"typeId":41,"itemName":"Garbage","buyPrice":14.15,"sellPrice":28.34,"profitPerUnit":14.19,"buyStation":"Ebtesham V - Amarr Navy Assembly Plant","sellStation":"Irshah VIII - Moon 9 - Trust Partners Trading Post","roi":100.28,"volumeAvailable":70,"maxProfit":993.3},{"typeId":41,"itemName":"Garbage","buyPrice":14.15,"sellPrice":28.34,"profitPerUnit":14.19,"buyStation":"Ebtesham VI - Moon 2 - Amarr Navy Assembly Plant","sellStation":"Irshah VIII - Moon 9 - Trust Partners Trading Post","roi":100.28,"volumeAvailable":70,"maxProfit":993.3},{"typeId":41,"itemName":"Garbage","buyPrice":14.15,"sellPrice":28.34,"profitPerUnit":14.19,"buyStation":"Hisoufad X - Moon 15 - Amarr Navy Assembly Plant","sellStation":"Irshah VIII - Moon 9 - Trust Partners Trading Post","roi":100.28,"volumeAvailable":70,"maxProfit":993.3},{"typeId":41,"itemName":"Garbage","buyPrice":14.15,"sellPrice":28.34,"profitPerUnit":14.19,"buyStation":"Erzoh V - Moon 14 - Amarr Navy Testing Facilities","sellStation":"Irshah VIII - Moon 9 - Trust Partners Trading Post","roi":100.28,"volumeAvailable":70,"maxProfit":993.3},{"typeId":41,"itemName":"Garbage","buyPrice":14.15,"sellPrice":28.34,"profitPerUnit":14.19,"buyStation":"Esteban VIII - Moon 4 - DED Logistic Support","sellStation":"Irshah VIII - Moon 9 - Trust Partners Trading Post","roi":100.28,"volumeAvailable":65,"maxProfit":922.35},{"typeId":41,"itemName":"Garbage","buyPrice":14.15,"sellPrice":28.34,"profitPerUnit":14.19,"buyStation":"Jesoyeh IX - Moon 15 - Amarr Navy Testing Facilities","sellStation":"Irshah VIII - Moon 9 - Trust Partners Trading Post","roi":100.28,"volumeAvailable":70,"maxProfit":993.3},{"typeId":17368,"itemName":"Station Warehouse Container","buyPrice":2498000,"sellPrice":5000000,"profitPerUnit":2502000,"buyStation":"Bashakru IV - Ministry of Internal Order Assembly Plant","sellStation":"Tidacha VIII - Moon 13 - Ammatar Consulate Bureau","roi":100.16,"volumeAvailable":1,"maxProfit":2502000},{"typeId":17368,"itemName":"Station Warehouse Container","buyPrice":2498000,"sellPrice":5000000,"profitPerUnit":2502000,"buyStation":"Jarshitsan VIII - Moon 8 - Carthum Conglomerate Factory","sellStation":"Tidacha VIII - Moon 13 - Ammatar Consulate Bureau","roi":100.16,"volumeAvailable":1,"maxProfit":2502000},{"typeId":17368,"itemName":"Station Warehouse Container","buyPrice":2500000,"sellPrice":5000000,"profitPerUnit":2500000,"buyStation":"Amarr VIII (Oris) - Emperor Family Academy","sellStation":"Tidacha VIII - Moon 13 - Ammatar Consulate Bureau","roi":100,"volumeAvailable":1,"maxProfit":2500000},{"typeId":41,"itemName":"Garbage","buyPrice":14.19,"sellPrice":28.34,"profitPerUnit":14.15,"buyStation":"Mamenkhanar IX - Moon 11 - DED Logistic Support","sellStation":"Irshah VIII - Moon 9 - Trust Partners Trading Post","roi":99.72,"volumeAvailable":65,"maxProfit":919.75},{"typeId":41,"itemName":"Garbage","buyPrice":14.35,"sellPrice":28.34,"profitPerUnit":13.99,"buyStation":"Yuhelia V - Moon 1 - Imperial Armaments Factory","sellStation":"Irshah VIII - Moon 9 - Trust Partners Trading Post","roi":97.49,"volumeAvailable":5050,"maxProfit":70649.5},{"typeId":41,"itemName":"Garbage","buyPrice":14.35,"sellPrice":28.34,"profitPerUnit":13.99,"buyStation":"Mamet IV - Moon 10 - Imperial Armaments Factory","sellStation":"Irshah VIII - Moon 9 - Trust Partners Trading Post","roi":97.49,"volumeAvailable":5050,"maxProfit":70649.5},{"typeId":41,"itemName":"Garbage","buyPrice":14.35,"sellPrice":28.34,"profitPerUnit":13.99,"buyStation":"Mamet V - Moon 7 - Imperial Armaments Factory","sellStation":"Irshah VIII - Moon 9 - Trust Partners Trading Post","roi":97.49,"volumeAvailable":5050,"maxProfit":70649.5},{"typeId":41,"itemName":"Garbage","buyPrice":14.35,"sellPrice":28.34,"profitPerUnit":13.99,"buyStation":"Bhizheba IX - Moon 1 - Amarr Navy Logistic Support","sellStation":"Irshah VIII - Moon 9 - Trust Partners Trading Post","roi":97.49,"volumeAvailable":70,"maxProfit":979.3},{"typeId":41,"itemName":"Garbage","buyPrice":14.36,"sellPrice":28.34,"profitPerUnit":13.98,"buyStation":"Ziona V - Moon 1 - Imperial Armaments Warehouse","sellStation":"Irshah VIII - Moon 9 - Trust Partners Trading Post","roi":97.35,"volumeAvailable":5050,"maxProfit":70599},{"typeId":2464,"itemName":"Hornet I","buyPrice":5000,"sellPrice":9750,"profitPerUnit":4750,"buyStation":"Afivad IX - Moon 2 - HZO Refinery","sellStation":"Alkez VI - Moon 1 - Nurtura Plantation","roi":95,"volumeAvailable":10,"maxProfit":47500},{"typeId":2454,"itemName":"Hobgoblin I","buyPrice":777.1,"sellPrice":1500,"profitPerUnit":722.9,"buyStation":"Bahromab V - Ministry of Assessment Bureau Offices","sellStation":"Kasrasi IX - Moon 7 - DED Assembly Plant","roi":93.03,"volumeAvailable":2,"maxProfit":1445.8},{"typeId":9826,"itemName":"Carbon","buyPrice":200,"sellPrice":385.88,"profitPerUnit":185.88,"buyStation":"Amarr VIII (Oris) - Emperor Family Academy","sellStation":"Uplingur III - Moon 8 - Nurtura Plantation","roi":92.94,"volumeAvailable":78,"maxProfit":14498.64},{"typeId":17368,"itemName":"Station Warehouse Container","buyPrice":2600000,"sellPrice":5000000,"profitPerUnit":2400000,"buyStation":"Ealur IX - Moon 16 - Aliastra Warehouse","sellStation":"Tidacha VIII - Moon 13 - Ammatar Consulate Bureau","roi":92.31,"volumeAvailable":1,"maxProfit":2400000},{"typeId":17368,"itemName":"Station Warehouse Container","buyPrice":2650000,"sellPrice":5000000,"profitPerUnit":2350000,"buyStation":"Joppaya IX - Moon 9 - Ardishapur Family Bureau","sellStation":"Tidacha VIII - Moon 13 - Ammatar Consulate Bureau","roi":88.68,"volumeAvailable":1,"maxProfit":2350000},{"typeId":6160,"itemName":"F-90 Compact Sensor Booster","buyPrice":1064,"sellPrice":2000,"profitPerUnit":936,"buyStation":"Mista V - Moon 4 - Ishukone Corporation Factory","sellStation":"Kasrasi IX - Moon 7 - DED Assembly Plant","roi":87.97,"volumeAvailable":2,"maxProfit":1872},{"typeId":41,"itemName":"Garbage","buyPrice":15.26,"sellPrice":28.34,"profitPerUnit":13.08,"buyStation":"Penirgman IV - Imperial Armaments Factory","sellStation":"Irshah VIII - Moon 9 - Trust Partners Trading Post","roi":85.71,"volumeAvailable":5050,"maxProfit":66054},{"typeId":17368,"itemName":"Station Warehouse Container","buyPrice":2800000,"sellPrice":5000000,"profitPerUnit":2200000,"buyStation":"Ahala VIII - Core Complexion Inc. Warehouse","sellStation":"Tidacha VIII - Moon 13 - Ammatar Consulate Bureau","roi":78.57,"volumeAvailable":1,"maxProfit":2200000},{"typeId":41,"itemName":"Garbage","buyPrice":15.88,"sellPrice":28.34,"profitPerUnit":12.46,"buyStation":"Penirgman IX - Moon 13 - Imperial Armaments Factory","sellStation":"Irshah VIII - Moon 9 - Trust Partners Trading Post","roi":78.46,"volumeAvailable":5050,"maxProfit":62923},{"typeId":41,"itemName":"Garbage","buyPrice":15.88,"sellPrice":28.34,"profitPerUnit":12.46,"buyStation":"Penirgman V - Imperial Armaments Factory","sellStation":"Irshah VIII - Moon 9 - Trust Partners Trading Post","roi":78.46,"volumeAvailable":5050,"maxProfit":62923},{"typeId":2464,"itemName":"Hornet I","buyPrice":5548,"sellPrice":9750,"profitPerUnit":4202,"buyStation":"Amarr VIII (Oris) - Emperor Family Academy","sellStation":"Alkez VI - Moon 1 - Nurtura Plantation","roi":75.74,"volumeAvailable":10,"maxProfit":42020},{"typeId":2464,"itemName":"Hornet I","buyPrice":5550,"sellPrice":9750,"profitPerUnit":4200,"buyStation":"Aghesi VI - Moon 10 - Ministry of Assessment Bureau Offices","sellStation":"Alkez VI - Moon 1 - Nurtura Plantation","roi":75.68,"volumeAvailable":10,"maxProfit":42000},{"typeId":2464,"itemName":"Hornet I","buyPrice":5550,"sellPrice":9750,"profitPerUnit":4200,"buyStation":"Amarr VIII (Oris) - Moon 4 - Expert Distribution Retail Center","sellStation":"Alkez VI - Moon 1 - Nurtura Plantation","roi":75.68,"volumeAvailable":4,"maxProfit":16800},{"typeId":17368,"itemName":"Station Warehouse Container","buyPrice":2857000,"sellPrice":5000000,"profitPerUnit":2143000,"buyStation":"Bashakru VII - Moon 5 - Ardishapur Family Bureau","sellStation":"Tidacha VIII - Moon 13 - Ammatar Consulate Bureau","roi":75.01,"volumeAvailable":1,"maxProfit":2143000},{"typeId":3647,"itemName":"Holoreels","buyPrice":175,"sellPrice":302.5,"profitPerUnit":127.5,"buyStation":"Amarr VIII (Oris) - Emperor Family Academy","sellStation":"Yuzier VII - Trust Partners Trading Post","roi":72.86,"volumeAvailable":10,"maxProfit":1275},{"typeId":15598,"itemName":"Caldari Navy Midshipman Insignia III","buyPrice":8999,"sellPrice":15000,"profitPerUnit":6001,"buyStation":"Amarr VIII (Oris) - Emperor Family Academy","sellStation":"Ibaria III - Thukker Mix Warehouse","roi":66.69,"volumeAvailable":2,"maxProfit":12002},{"typeId":2464,"itemName":"Hornet I","buyPrice":6000,"sellPrice":9750,"profitPerUnit":3750,"buyStation":"Chaven VIII - Moon 1 - Imperial Academy","sellStation":"Alkez VI - Moon 1 - Nurtura Plantation","roi":62.5,"volumeAvailable":10,"maxProfit":37500},{"typeId":22542,"itemName":"Mining Laser Upgrade I","buyPrice":41000,"sellPrice":65000,"profitPerUnit":24000,"buyStation":"Akhragan VIII - Moon 5 - Ministry of Internal Order Logistic Support","sellStation":"Dysa II - Ammatar Fleet Assembly Plant","roi":58.54,"volumeAvailable":4,"maxProfit":96000},{"typeId":15591,"itemName":"Federation Navy Sergeant Major Insignia I","buyPrice":19170,"sellPrice":30000,"profitPerUnit":10830,"buyStation":"Jesoyeh IX - Moon 7 - HZO Refinery Mining Outpost","sellStation":"Serad IV - Moon 12 - Ammatar Fleet Logistic Support","roi":56.49,"volumeAvailable":1,"maxProfit":10830},{"typeId":17368,"itemName":"Station Warehouse Container","buyPrice":3251000,"sellPrice":5000000,"profitPerUnit":1749000,"buyStation":"Akhragan VII - Imperial Chancellor Bureau Offices","sellStation":"Tidacha VIII - Moon 13 - Ammatar Consulate Bureau","roi":53.8,"volumeAvailable":1,"maxProfit":1749000},{"typeId":22542,"itemName":"Mining Laser Upgrade I","buyPrice":42670,"sellPrice":65000,"profitPerUnit":22330,"buyStation":"Deepari II - Imperial Academy","sellStation":"Dysa II - Ammatar Fleet Assembly Plant","roi":52.33,"volumeAvailable":4,"maxProfit":89320},{"typeId":16273,"itemName":"Liquid Ozone","buyPrice":79,"sellPrice":120,"profitPerUnit":41,"buyStation":"Misaba V - Moon 3 - Zoar and Sons Factory","sellStation":"Jarizza II - Moon 1 - Ammatar Fleet Assembly Plant","roi":51.9,"volumeAvailable":46979,"maxProfit":1926139},{"typeId":15591,"itemName":"Federation Navy Sergeant Major Insignia I","buyPrice":20000,"sellPrice":30000,"profitPerUnit":10000,"buyStation":"Amarr VIII (Oris) - Emperor Family Academy","sellStation":"Serad IV - Moon 12 - Ammatar Fleet Logistic Support","roi":50,"volumeAvailable":1,"maxProfit":10000},{"typeId":3713,"itemName":"Vitoc","buyPrice":8378.16,"sellPrice":12071.4,"profitPerUnit":3693.24,"buyStation":"Mikhir V - Moon 8 - Amarr Civil Service Bureau Offices","sellStation":"Berta VI - Moon 19 - Ammatar Consulate Bureau","roi":44.08,"volumeAvailable":22,"maxProfit":81251.28},{"typeId":3713,"itemName":"Vitoc","buyPrice":8378.03,"sellPrice":12071.4,"profitPerUnit":3693.37,"buyStation":"Akila IX - Moon 6 - Amarr Civil Service Archives","sellStation":"Berta VI - Moon 19 - Ammatar Consulate Bureau","roi":44.08,"volumeAvailable":22,"maxProfit":81254.14},{"typeId":3713,"itemName":"Vitoc","buyPrice":8378.12,"sellPrice":12071.4,"profitPerUnit":3693.28,"buyStation":"Yeeramoun VII - Moon 5 - Amarr Civil Service Information Center","sellStation":"Berta VI - Moon 19 - Ammatar Consulate Bureau","roi":44.08,"volumeAvailable":22,"maxProfit":81252.16},{"typeId":3713,"itemName":"Vitoc","buyPrice":8378.11,"sellPrice":12071.4,"profitPerUnit":3693.29,"buyStation":"Yeeramoun VII - Moon 2 - Amarr Civil Service Bureau Offices","sellStation":"Berta VI - Moon 19 - Ammatar Consulate Bureau","roi":44.08,"volumeAvailable":22,"maxProfit":81252.38},{"typeId":3713,"itemName":"Vitoc","buyPrice":8378.09,"sellPrice":12071.4,"profitPerUnit":3693.31,"buyStation":"Etav VIII - Moon 14 - Amarr Civil Service Bureau Offices","sellStation":"Berta VI - Moon 19 - Ammatar Consulate Bureau","roi":44.08,"volumeAvailable":22,"maxProfit":81252.82},{"typeId":3713,"itemName":"Vitoc","buyPrice":8378.18,"sellPrice":12071.4,"profitPerUnit":3693.22,"buyStation":"Bashakru IV - Ministry of Internal Order Assembly Plant","sellStation":"Berta VI - Moon 19 - Ammatar Consulate Bureau","roi":44.08,"volumeAvailable":22,"maxProfit":81250.84},{"typeId":3713,"itemName":"Vitoc","buyPrice":8378.02,"sellPrice":12071.4,"profitPerUnit":3693.38,"buyStation":"Akila VII - Moon 12 - Amarr Civil Service Archives","sellStation":"Berta VI - Moon 19 - Ammatar Consulate Bureau","roi":44.08,"volumeAvailable":22,"maxProfit":81254.36},{"typeId":3713,"itemName":"Vitoc","buyPrice":8378.07,"sellPrice":12071.4,"profitPerUnit":3693.33,"buyStation":"Etav IX - Amarr Civil Service Information Center","sellStation":"Berta VI - Moon 19 - Ammatar Consulate Bureau","roi":44.08,"volumeAvailable":22,"maxProfit":81253.26},{"typeId":3713,"itemName":"Vitoc","buyPrice":8378.97,"sellPrice":12071.4,"profitPerUnit":3692.43,"buyStation":"Akhragan V - Moon 1 - Amarr Civil Service Bureau Offices","sellStation":"Berta VI - Moon 19 - Ammatar Consulate Bureau","roi":44.07,"volumeAvailable":22,"maxProfit":81233.46},{"typeId":3713,"itemName":"Vitoc","buyPrice":8379.12,"sellPrice":12071.4,"profitPerUnit":3692.28,"buyStation":"Shuria IV - Moon 1 - Ministry of Internal Order Logistic Support","sellStation":"Berta VI - Moon 19 - Ammatar Consulate Bureau","roi":44.07,"volumeAvailable":22,"maxProfit":81230.16},{"typeId":3713,"itemName":"Vitoc","buyPrice":8378.98,"sellPrice":12071.4,"profitPerUnit":3692.42,"buyStation":"Akhragan VIII - Moon 5 - Ministry of Internal Order Logistic Support","sellStation":"Berta VI - Moon 19 - Ammatar Consulate Bureau","roi":44.07,"volumeAvailable":22,"maxProfit":81233.24},{"typeId":3713,"itemName":"Vitoc","buyPrice":8379.06,"sellPrice":12071.4,"profitPerUnit":3692.34,"buyStation":"Penirgman VII - Ministry of Internal Order Assembly Plant","sellStation":"Berta VI - Moon 19 - Ammatar Consulate Bureau","roi":44.07,"volumeAvailable":22,"maxProfit":81231.48},{"typeId":3713,"itemName":"Vitoc","buyPrice":8379.15,"sellPrice":12071.4,"profitPerUnit":3692.25,"buyStation":"Shuria X - Moon 10 - Amarr Civil Service Bureau Offices","sellStation":"Berta VI - Moon 19 - Ammatar Consulate Bureau","roi":44.06,"volumeAvailable":22,"maxProfit":81229.5},{"typeId":3713,"itemName":"Vitoc","buyPrice":8379.14,"sellPrice":12071.4,"profitPerUnit":3692.26,"buyStation":"Ziona VI - Moon 8 - Amarr Civil Service Bureau Offices","sellStation":"Berta VI - Moon 19 - Ammatar Consulate Bureau","roi":44.06,"volumeAvailable":22,"maxProfit":81229.72},{"typeId":3713,"itemName":"Vitoc","buyPrice":8379.21,"sellPrice":12071.4,"profitPerUnit":3692.19,"buyStation":"Sahda II - Amarr Civil Service Information Center","sellStation":"Berta VI - Moon 19 - Ammatar Consulate Bureau","roi":44.06,"volumeAvailable":22,"maxProfit":81228.18},{"typeId":3713,"itemName":"Vitoc","buyPrice":8379.23,"sellPrice":12071.4,"profitPerUnit":3692.17,"buyStation":"Sahda IV - Moon 14 - Amarr Civil Service Bureau Offices","sellStation":"Berta VI - Moon 19 - Ammatar Consulate Bureau","roi":44.06,"volumeAvailable":22,"maxProfit":81227.74},{"typeId":3713,"itemName":"Vitoc","buyPrice":8379.17,"sellPrice":12071.4,"profitPerUnit":3692.23,"buyStation":"Shuria X - Moon 16 - Ministry of Internal Order Assembly Plant","sellStation":"Berta VI - Moon 19 - Ammatar Consulate Bureau","roi":44.06,"volumeAvailable":22,"maxProfit":81229.06},{"typeId":3713,"itemName":"Vitoc","buyPrice":8379.32,"sellPrice":12071.4,"profitPerUnit":3692.08,"buyStation":"Penirgman IX - Moon 3 - Ministry of Internal Order Assembly Plant","sellStation":"Berta VI - Moon 19 - Ammatar Consulate Bureau","roi":44.06,"volumeAvailable":22,"maxProfit":81225.76},{"typeId":3713,"itemName":"Vitoc","buyPrice":8379.28,"sellPrice":12071.4,"profitPerUnit":3692.12,"buyStation":"Orkashu VI - Moon 7 - Ministry of Internal Order Assembly Plant","sellStation":"Berta VI - Moon 19 - Ammatar Consulate Bureau","roi":44.06,"volumeAvailable":22,"maxProfit":81226.64},{"typeId":16273,"itemName":"Liquid Ozone","buyPrice":86.77,"sellPrice":120,"profitPerUnit":33.23,"buyStation":"Amarr VIII (Oris) - Emperor Family Academy","sellStation":"Jarizza II - Moon 1 - Ammatar Fleet Assembly Plant","roi":38.3,"volumeAvailable":54676,"maxProfit":1816883.48},{"typeId":3713,"itemName":"Vitoc","buyPrice":8821.77,"sellPrice":12071.4,"profitPerUnit":3249.63,"buyStation":"Penirgman VI - Ministry of Internal Order Assembly Plant","sellStation":"Berta VI - Moon 19 - Ammatar Consulate Bureau","roi":36.84,"volumeAvailable":22,"maxProfit":71491.86},{"typeId":24495,"itemName":"Scourge Fury Light Missile","buyPrice":59,"sellPrice":80,"profitPerUnit":21,"buyStation":"Misaba V - Moon 3 - Zoar and Sons Factory","sellStation":"Sooma X - CONCORD Academy","roi":35.59,"volumeAvailable":3690,"maxProfit":77490},{"typeId":3647,"itemName":"Holoreels","buyPrice":225.01,"sellPrice":302.5,"profitPerUnit":77.49,"buyStation":"Eba VIII - Moon 9 - Amarr Certified News Publisher","sellStation":"Yuzier VII - Trust Partners Trading Post","roi":34.44,"volumeAvailable":4827,"maxProfit":374044.23},{"typeId":3647,"itemName":"Holoreels","buyPrice":225,"sellPrice":302.5,"profitPerUnit":77.5,"buyStation":"Artoun VII - Moon 2 - Amarr Certified News Development Studio","sellStation":"Yuzier VII - Trust Partners Trading Post","roi":34.44,"volumeAvailable":4827,"maxProfit":374092.5},{"typeId":3647,"itemName":"Holoreels","buyPrice":225,"sellPrice":302.5,"profitPerUnit":77.5,"buyStation":"Pelkia III - Moon 2 - Amarr Certified News Publisher","sellStation":"Yuzier VII - Trust Partners Trading Post","roi":34.44,"volumeAvailable":4827,"maxProfit":374092.5},{"typeId":3647,"itemName":"Holoreels","buyPrice":225,"sellPrice":302.5,"profitPerUnit":77.5,"buyStation":"Sakhti IX - Moon 7 - Amarr Certified News Development Studio","sellStation":"Yuzier VII - Trust Partners Trading Post","roi":34.44,"volumeAvailable":4827,"maxProfit":374092.5},{"typeId":3647,"itemName":"Holoreels","buyPrice":225.01,"sellPrice":302.5,"profitPerUnit":77.49,"buyStation":"Mabnen VII - Moon 5 - Impetus Development Studio","sellStation":"Yuzier VII - Trust Partners Trading Post","roi":34.44,"volumeAvailable":5644,"maxProfit":437353.56},{"typeId":3647,"itemName":"Holoreels","buyPrice":225,"sellPrice":302.5,"profitPerUnit":77.5,"buyStation":"Faswiba VII - Moon 4 - The Scope Development Studio","sellStation":"Yuzier VII - Trust Partners Trading Post","roi":34.44,"volumeAvailable":5644,"maxProfit":437410},{"typeId":3647,"itemName":"Holoreels","buyPrice":225,"sellPrice":302.5,"profitPerUnit":77.5,"buyStation":"Faswiba VIII - Moon 3 - The Scope Publisher","sellStation":"Yuzier VII - Trust Partners Trading Post","roi":34.44,"volumeAvailable":5644,"maxProfit":437410},{"typeId":3647,"itemName":"Holoreels","buyPrice":225.05,"sellPrice":302.5,"profitPerUnit":77.45,"buyStation":"Toshabia VI - Moon 1 - The Scope Development Studio","sellStation":"Yuzier VII - Trust Partners Trading Post","roi":34.41,"volumeAvailable":5644,"maxProfit":437127.8},{"typeId":3647,"itemName":"Holoreels","buyPrice":225.1,"sellPrice":302.5,"profitPerUnit":77.4,"buyStation":"Mabnen V - Moon 16 - Impetus Development Studio","sellStation":"Yuzier VII - Trust Partners Trading Post","roi":34.38,"volumeAvailable":5644,"maxProfit":436845.6},{"typeId":3647,"itemName":"Holoreels","buyPrice":225.1,"sellPrice":302.5,"profitPerUnit":77.4,"buyStation":"Mabnen VIII - Moon 2 - The Scope Development Studio","sellStation":"Yuzier VII - Trust Partners Trading Post","roi":34.38,"volumeAvailable":5644,"maxProfit":436845.6},{"typeId":9852,"itemName":"Tobacco","buyPrice":44.44,"sellPrice":59.34,"profitPerUnit":14.9,"buyStation":"Penirgman IX - Moon 7 - Modern Finances Depository","sellStation":"Hasateem V - Moon 11 - Imperial Armaments Factory","roi":33.53,"volumeAvailable":42234,"maxProfit":629286.6},{"typeId":9852,"itemName":"Tobacco","buyPrice":44.44,"sellPrice":59.34,"profitPerUnit":14.9,"buyStation":"Penirgman V - Moon 2 - Modern Finances Depository","sellStation":"Hasateem V - Moon 11 - Imperial Armaments Factory","roi":33.53,"volumeAvailable":42234,"maxProfit":629286.6},{"typeId":24495,"itemName":"Scourge Fury Light Missile","buyPrice":60,"sellPrice":80,"profitPerUnit":20,"buyStation":"Amarr VIII (Oris) - Emperor Family Academy","sellStation":"Sooma X - CONCORD Academy","roi":33.33,"volumeAvailable":10000,"maxProfit":200000},{"typeId":16273,"itemName":"Liquid Ozone","buyPrice":90,"sellPrice":120,"profitPerUnit":30,"buyStation":"Bagodan VIII - Moon 4 - HZO Refinery Mineral Reserve","sellStation":"Jarizza II - Moon 1 - Ammatar Fleet Assembly Plant","roi":33.33,"volumeAvailable":1928,"maxProfit":57840},{"typeId":15597,"itemName":"Caldari Navy Midshipman Insignia II","buyPrice":6000,"sellPrice":8000,"profitPerUnit":2000,"buyStation":"Amarr VIII (Oris) - Emperor Family Academy","sellStation":"Hasateem VI - Moon 12 - Thukker Mix Factory","roi":33.33,"volumeAvailable":6,"maxProfit":12000},{"typeId":15587,"itemName":"Federation Navy Midshipman Insignia I","buyPrice":3383,"sellPrice":4500,"profitPerUnit":1117,"buyStation":"Jesoyeh IX - Moon 7 - HZO Refinery Mining Outpost","sellStation":"Hasateem VI - Moon 12 - Thukker Mix Factory","roi":33.02,"volumeAvailable":8,"maxProfit":8936},{"typeId":3647,"itemName":"Holoreels","buyPrice":227.5,"sellPrice":302.5,"profitPerUnit":75,"buyStation":"Bika V - Moon 1 - CreoDron Warehouse","sellStation":"Yuzier VII - Trust Partners Trading Post","roi":32.97,"volumeAvailable":10,"maxProfit":750},{"typeId":15994,"itemName":"Federation Navy Sergeant Insignia II","buyPrice":18890,"sellPrice":25000,"profitPerUnit":6110,"buyStation":"Jesoyeh IX - Moon 7 - HZO Refinery Mining Outpost","sellStation":"Futzchag IX - Moon 9 - Thukker Mix Factory","roi":32.35,"volumeAvailable":3,"maxProfit":18330},{"typeId":16118,"itemName":"CONCORD Officer Emblem","buyPrice":49500,"sellPrice":65000,"profitPerUnit":15500,"buyStation":"Amarr VIII (Oris) - Emperor Family Academy","sellStation":"Hasateem VI - Moon 12 - Thukker Mix Factory","roi":31.31,"volumeAvailable":3,"maxProfit":46500},{"typeId":17888,"itemName":"Nitrogen Isotopes","buyPrice":510.3,"sellPrice":666.5,"profitPerUnit":156.2,"buyStation":"Ziriert VIII - Moon 3 - Zoar and Sons Factory","sellStation":"Podion VIII - Moon 15 - Nefantar Miner Association Mining Outpost","roi":30.61,"volumeAvailable":1632,"maxProfit":254918.4},{"typeId":8295,"itemName":"Type-D Restrained Shield Flux Coil","buyPrice":1549,"sellPrice":2000,"profitPerUnit":451,"buyStation":"Ashab VII - Moon 16 - Civic Court Accounting","sellStation":"Kasrasi IX - Moon 7 - DED Assembly Plant","roi":29.12,"volumeAvailable":1,"maxProfit":451},{"typeId":8295,"itemName":"Type-D Restrained Shield Flux Coil","buyPrice":1555,"sellPrice":2000,"profitPerUnit":445,"buyStation":"Amarr VIII (Oris) - Emperor Family Academy","sellStation":"Kasrasi IX - Moon 7 - DED Assembly Plant","roi":28.62,"volumeAvailable":4,"maxProfit":1780},{"typeId":25597,"itemName":"Damaged Artificial Neural Network","buyPrice":256.2,"sellPrice":325,"profitPerUnit":68.8,"buyStation":"Amarr VIII (Oris) - Emperor Family Academy","sellStation":"Kasrasi IX - Moon 7 - DED Assembly Plant","roi":26.85,"volumeAvailable":28,"maxProfit":1926.4},{"typeId":22542,"itemName":"Mining Laser Upgrade I","buyPrice":51980,"sellPrice":65000,"profitPerUnit":13020,"buyStation":"Amarr VIII (Oris) - Emperor Family Academy","sellStation":"Dysa II - Ammatar Fleet Assembly Plant","roi":25.05,"volumeAvailable":4,"maxProfit":52080},{"typeId":41,"itemName":"Garbage","buyPrice":22.75,"sellPrice":28.34,"profitPerUnit":5.59,"buyStation":"Hamse IX - Moon 13 - Imperial Armaments Factory","sellStation":"Irshah VIII - Moon 9 - Trust Partners Trading Post","roi":24.57,"volumeAvailable":5050,"maxProfit":28229.5},{"typeId":43,"itemName":"Antibiotics","buyPrice":305,"sellPrice":375.5,"profitPerUnit":70.5,"buyStation":"Amarr VIII (Oris) - Emperor Family Academy","sellStation":"Ibaria III - Thukker Mix Warehouse","roi":23.11,"volumeAvailable":10,"maxProfit":705},{"typeId":15597,"itemName":"Caldari Navy Midshipman Insignia II","buyPrice":6500,"sellPrice":8000,"profitPerUnit":1500,"buyStation":"Penirgman IX - Moon 3 - Ministry of Internal Order Assembly Plant","sellStation":"Hasateem VI - Moon 12 - Thukker Mix Factory","roi":23.08,"volumeAvailable":5,"maxProfit":7500},{"typeId":43,"itemName":"Antibiotics","buyPrice":305.5,"sellPrice":375.5,"profitPerUnit":70,"buyStation":"Ruchy II - Moon 8 - Core Complexion Inc. Storage","sellStation":"Ibaria III - Thukker Mix Warehouse","roi":22.91,"volumeAvailable":8437,"maxProfit":590590},{"typeId":1403,"itemName":"Inertial Stabilizers I","buyPrice":11000,"sellPrice":13500,"profitPerUnit":2500,"buyStation":"Chaven VIII - Moon 1 - Imperial Academy","sellStation":"Kasrasi IX - Moon 7 - DED Assembly Plant","roi":22.73,"volumeAvailable":84,"maxProfit":210000},{"typeId":43,"itemName":"Antibiotics","buyPrice":306.91,"sellPrice":375.5,"profitPerUnit":68.59,"buyStation":"Ebtesham VI - Moon 15 - Expert Distribution Warehouse","sellStation":"Ibaria III - Thukker Mix Warehouse","roi":22.35,"volumeAvailable":6989,"maxProfit":479375.51},{"typeId":43,"itemName":"Antibiotics","buyPrice":306.91,"sellPrice":375.5,"profitPerUnit":68.59,"buyStation":"Ahala VII - Moon 1 - Core Complexion Inc. Warehouse","sellStation":"Ibaria III - Thukker Mix Warehouse","roi":22.35,"volumeAvailable":8437,"maxProfit":578693.83},{"typeId":43,"itemName":"Antibiotics","buyPrice":306.93,"sellPrice":375.5,"profitPerUnit":68.57,"buyStation":"Ahala VIII - Core Complexion Inc. Warehouse","sellStation":"Ibaria III - Thukker Mix Warehouse","roi":22.34,"volumeAvailable":8437,"maxProfit":578525.09},{"typeId":43,"itemName":"Antibiotics","buyPrice":307.3,"sellPrice":375.5,"profitPerUnit":68.2,"buyStation":"Penirgman IX - Moon 3 - Ministry of Internal Order Assembly Plant","sellStation":"Ibaria III - Thukker Mix Warehouse","roi":22.19,"volumeAvailable":10,"maxProfit":682},{"typeId":43,"itemName":"Antibiotics","buyPrice":307.4,"sellPrice":375.5,"profitPerUnit":68.1,"buyStation":"Akhragan VIII - Moon 2 - Core Complexion Inc. Storage","sellStation":"Ibaria III - Thukker Mix Warehouse","roi":22.15,"volumeAvailable":8437,"maxProfit":574559.7},{"typeId":15999,"itemName":"Caldari Navy Captain Insignia V","buyPrice":41000,"sellPrice":50000,"profitPerUnit":9000,"buyStation":"Amarr VIII (Oris) - Emperor Family Academy","sellStation":"Hasateem VI - Moon 12 - Thukker Mix Factory","roi":21.95,"volumeAvailable":21,"maxProfit":189000},{"typeId":43,"itemName":"Antibiotics","buyPrice":308.2,"sellPrice":375.5,"profitPerUnit":67.3,"buyStation":"Bhizheba VIII - Moon 5 - Expert Distribution Warehouse","sellStation":"Ibaria III - Thukker Mix Warehouse","roi":21.84,"volumeAvailable":6989,"maxProfit":470359.7},{"typeId":43,"itemName":"Antibiotics","buyPrice":308.2,"sellPrice":375.5,"profitPerUnit":67.3,"buyStation":"Akhragan V - Core Complexion Inc. Warehouse","sellStation":"Ibaria III - Thukker Mix Warehouse","roi":21.84,"volumeAvailable":8437,"maxProfit":567810.1},{"typeId":43,"itemName":"Antibiotics","buyPrice":308.2,"sellPrice":375.5,"profitPerUnit":67.3,"buyStation":"Eba VIII - Moon 4 - Expert Distribution Retail Center","sellStation":"Ibaria III - Thukker Mix Warehouse","roi":21.84,"volumeAvailable":6989,"maxProfit":470359.7},{"typeId":43,"itemName":"Antibiotics","buyPrice":308.2,"sellPrice":375.5,"profitPerUnit":67.3,"buyStation":"Mabnen V - Moon 5 - Expert Distribution Warehouse","sellStation":"Ibaria III - Thukker Mix Warehouse","roi":21.84,"volumeAvailable":6989,"maxProfit":470359.7},{"typeId":43,"itemName":"Antibiotics","buyPrice":308.73,"sellPrice":375.5,"profitPerUnit":66.77,"buyStation":"Knophtikoo IV - Moon 19 - Core Complexion Inc. Storage","sellStation":"Ibaria III - Thukker Mix Warehouse","roi":21.63,"volumeAvailable":8437,"maxProfit":563338.49},{"typeId":43,"itemName":"Antibiotics","buyPrice":308.81,"sellPrice":375.5,"profitPerUnit":66.69,"buyStation":"Nifshed X - Moon 1 - Chemal Tech Warehouse","sellStation":"Ibaria III - Thukker Mix Warehouse","roi":21.6,"volumeAvailable":8437,"maxProfit":562663.53},{"typeId":43,"itemName":"Antibiotics","buyPrice":309.45,"sellPrice":375.5,"profitPerUnit":66.05,"buyStation":"Artoun IX - Moon 1 - Expert Distribution Warehouse","sellStation":"Ibaria III - Thukker Mix Warehouse","roi":21.34,"volumeAvailable":6989,"maxProfit":461623.45},{"typeId":43,"itemName":"Antibiotics","buyPrice":309.45,"sellPrice":375.5,"profitPerUnit":66.05,"buyStation":"Gosalav IV - Core Complexion Inc. Storage","sellStation":"Ibaria III - Thukker Mix Warehouse","roi":21.34,"volumeAvailable":8437,"maxProfit":557263.85},{"typeId":43,"itemName":"Antibiotics","buyPrice":309.45,"sellPrice":375.5,"profitPerUnit":66.05,"buyStation":"Ziona VI - Moon 11 - Core Complexion Inc. Factory","sellStation":"Ibaria III - Thukker Mix Warehouse","roi":21.34,"volumeAvailable":8437,"maxProfit":557263.85},{"typeId":43,"itemName":"Antibiotics","buyPrice":309.45,"sellPrice":375.5,"profitPerUnit":66.05,"buyStation":"Ziona VI - Moon 6 - Core Complexion Inc. Storage","sellStation":"Ibaria III - Thukker Mix Warehouse","roi":21.34,"volumeAvailable":8437,"maxProfit":557263.85},{"typeId":43,"itemName":"Antibiotics","buyPrice":309.45,"sellPrice":375.5,"profitPerUnit":66.05,"buyStation":"Hizhara IX - Moon 5 - Core Complexion Inc. Factory","sellStation":"Ibaria III - Thukker Mix Warehouse","roi":21.34,"volumeAvailable":8437,"maxProfit":557263.85},{"typeId":43,"itemName":"Antibiotics","buyPrice":309.45,"sellPrice":375.5,"profitPerUnit":66.05,"buyStation":"Arera VIII - Moon 16 - Core Complexion Inc. Factory","sellStation":"Ibaria III - Thukker Mix Warehouse","roi":21.34,"volumeAvailable":8437,"maxProfit":557263.85},{"typeId":43,"itemName":"Antibiotics","buyPrice":309.45,"sellPrice":375.5,"profitPerUnit":66.05,"buyStation":"Abaim VIII - Moon 4 - Core Complexion Inc. Factory","sellStation":"Ibaria III - Thukker Mix Warehouse","roi":21.34,"volumeAvailable":8437,"maxProfit":557263.85},{"typeId":43,"itemName":"Antibiotics","buyPrice":309.45,"sellPrice":375.5,"profitPerUnit":66.05,"buyStation":"Abaim XI - Moon 1 - Core Complexion Inc. Factory","sellStation":"Ibaria III - Thukker Mix Warehouse","roi":21.34,"volumeAvailable":8437,"maxProfit":557263.85},{"typeId":43,"itemName":"Antibiotics","buyPrice":309.45,"sellPrice":375.5,"profitPerUnit":66.05,"buyStation":"Abaim XI - Moon 3 - Core Complexion Inc. Factory","sellStation":"Ibaria III - Thukker Mix Warehouse","roi":21.34,"volumeAvailable":8437,"maxProfit":557263.85},{"typeId":43,"itemName":"Antibiotics","buyPrice":309.45,"sellPrice":375.5,"profitPerUnit":66.05,"buyStation":"Gosalav IV - Moon 1 - Core Complexion Inc. Factory","sellStation":"Ibaria III - Thukker Mix Warehouse","roi":21.34,"volumeAvailable":8437,"maxProfit":557263.85},{"typeId":43,"itemName":"Antibiotics","buyPrice":309.45,"sellPrice":375.5,"profitPerUnit":66.05,"buyStation":"Narai IX - Moon 1 - Core Complexion Inc. Factory","sellStation":"Ibaria III - Thukker Mix Warehouse","roi":21.34,"volumeAvailable":8437,"maxProfit":557263.85},{"typeId":43,"itemName":"Antibiotics","buyPrice":309.45,"sellPrice":375.5,"profitPerUnit":66.05,"buyStation":"Vashkah VI - Moon 2 - Chemal Tech Research Center","sellStation":"Ibaria III - Thukker Mix Warehouse","roi":21.34,"volumeAvailable":8437,"maxProfit":557263.85},{"typeId":43,"itemName":"Antibiotics","buyPrice":309.45,"sellPrice":375.5,"profitPerUnit":66.05,"buyStation":"Nererut VIII - Moon 2 - Chemal Tech Factory","sellStation":"Ibaria III - Thukker Mix Warehouse","roi":21.34,"volumeAvailable":8437,"maxProfit":557263.85},{"typeId":43,"itemName":"Antibiotics","buyPrice":309.45,"sellPrice":375.5,"profitPerUnit":66.05,"buyStation":"Fahruni XII - Sisters of EVE Bureau","sellStation":"Ibaria III - Thukker Mix Warehouse","roi":21.34,"volumeAvailable":8437,"maxProfit":557263.85},{"typeId":43,"itemName":"Antibiotics","buyPrice":309.45,"sellPrice":375.5,"profitPerUnit":66.05,"buyStation":"Mikhir VI - Moon 1 - Core Complexion Inc. Factory","sellStation":"Ibaria III - Thukker Mix Warehouse","roi":21.34,"volumeAvailable":8437,"maxProfit":557263.85},{"typeId":15994,"itemName":"Federation Navy Sergeant Insignia II","buyPrice":20630,"sellPrice":25000,"profitPerUnit":4370,"buyStation":"Jerma VIII - Moon 3 - Theology Council Tribunal","sellStation":"Futzchag IX - Moon 9 - Thukker Mix Factory","roi":21.18,"volumeAvailable":1,"maxProfit":4370},{"typeId":3812,"itemName":"Data Sheets","buyPrice":141,"sellPrice":170.13,"profitPerUnit":29.13,"buyStation":"Pelkia III - Moon 2 - Amarr Certified News Publisher","sellStation":"Tanoo V - Moon 1 - Ammatar Consulate Bureau","roi":20.66,"volumeAvailable":107,"maxProfit":3116.91},{"typeId":3812,"itemName":"Data Sheets","buyPrice":141,"sellPrice":170.13,"profitPerUnit":29.13,"buyStation":"Sakhti IX - Moon 7 - Amarr Certified News Development Studio","sellStation":"Tanoo V - Moon 1 - Ammatar Consulate Bureau","roi":20.66,"volumeAvailable":107,"maxProfit":3116.91},{"typeId":3812,"itemName":"Data Sheets","buyPrice":141,"sellPrice":170.13,"profitPerUnit":29.13,"buyStation":"Sukirah VIII - Moon 5 - Amarr Trade Registry Archives","sellStation":"Tanoo V - Moon 1 - Ammatar Consulate Bureau","roi":20.66,"volumeAvailable":32,"maxProfit":932.16},{"typeId":3812,"itemName":"Data Sheets","buyPrice":141,"sellPrice":170.13,"profitPerUnit":29.13,"buyStation":"Mikhir V - Moon 8 - Amarr Trade Registry Bureau Offices","sellStation":"Tanoo V - Moon 1 - Ammatar Consulate Bureau","roi":20.66,"volumeAvailable":32,"maxProfit":932.16},{"typeId":3812,"itemName":"Data Sheets","buyPrice":141,"sellPrice":170.13,"profitPerUnit":29.13,"buyStation":"Fahruni XI - Moon 13 - Amarr Trade Registry Bureau Offices","sellStation":"Tanoo V - Moon 1 - Ammatar Consulate Bureau","roi":20.66,"volumeAvailable":32,"maxProfit":932.16},{"typeId":3812,"itemName":"Data Sheets","buyPrice":141,"sellPrice":170.13,"profitPerUnit":29.13,"buyStation":"Sahda IV - Moon 7 - Amarr Trade Registry Information Center","sellStation":"Tanoo V - Moon 1 - Ammatar Consulate Bureau","roi":20.66,"volumeAvailable":32,"maxProfit":932.16},{"typeId":3812,"itemName":"Data Sheets","buyPrice":141,"sellPrice":170.13,"profitPerUnit":29.13,"buyStation":"Fahruni VI - Amarr Trade Registry Bureau Offices","sellStation":"Tanoo V - Moon 1 - Ammatar Consulate Bureau","roi":20.66,"volumeAvailable":32,"maxProfit":932.16},{"typeId":3812,"itemName":"Data Sheets","buyPrice":141,"sellPrice":170.13,"profitPerUnit":29.13,"buyStation":"Amod V - Amarr Trade Registry Archives","sellStation":"Tanoo V - Moon 1 - Ammatar Consulate Bureau","roi":20.66,"volumeAvailable":32,"maxProfit":932.16},{"typeId":3812,"itemName":"Data Sheets","buyPrice":141,"sellPrice":170.13,"profitPerUnit":29.13,"buyStation":"Toshabia VI - Moon 6 - Emperor Family Bureau","sellStation":"Tanoo V - Moon 1 - Ammatar Consulate Bureau","roi":20.66,"volumeAvailable":32,"maxProfit":932.16},{"typeId":3812,"itemName":"Data Sheets","buyPrice":141,"sellPrice":170.13,"profitPerUnit":29.13,"buyStation":"Neziel I - DED Assembly Plant","sellStation":"Tanoo V - Moon 1 - Ammatar Consulate Bureau","roi":20.66,"volumeAvailable":28,"maxProfit":815.64},{"typeId":3812,"itemName":"Data Sheets","buyPrice":141,"sellPrice":170.13,"profitPerUnit":29.13,"buyStation":"Esteban VIII - Moon 4 - DED Logistic Support","sellStation":"Tanoo V - Moon 1 - Ammatar Consulate Bureau","roi":20.66,"volumeAvailable":28,"maxProfit":815.64},{"typeId":3812,"itemName":"Data Sheets","buyPrice":141,"sellPrice":170.13,"profitPerUnit":29.13,"buyStation":"Nalu VII - Moon 7 - DED Testing Facilities","sellStation":"Tanoo V - Moon 1 - Ammatar Consulate Bureau","roi":20.66,"volumeAvailable":28,"maxProfit":815.64},{"typeId":3812,"itemName":"Data Sheets","buyPrice":141,"sellPrice":170.13,"profitPerUnit":29.13,"buyStation":"Sahdil III - DED Logistic Support","sellStation":"Tanoo V - Moon 1 - Ammatar Consulate Bureau","roi":20.66,"volumeAvailable":28,"maxProfit":815.64},{"typeId":3812,"itemName":"Data Sheets","buyPrice":141,"sellPrice":170.13,"profitPerUnit":29.13,"buyStation":"Ziona VII - Moon 13 - Ministry of War Archives","sellStation":"Tanoo V - Moon 1 - Ammatar Consulate Bureau","roi":20.66,"volumeAvailable":32,"maxProfit":932.16},{"typeId":3812,"itemName":"Data Sheets","buyPrice":141,"sellPrice":170.13,"profitPerUnit":29.13,"buyStation":"Sukirah V - Moon 3 - Ministry of War Archives","sellStation":"Tanoo V - Moon 1 - Ammatar Consulate Bureau","roi":20.66,"volumeAvailable":32,"maxProfit":932.16},{"typeId":3812,"itemName":"Data Sheets","buyPrice":141,"sellPrice":170.13,"profitPerUnit":29.13,"buyStation":"Mikhir V - Moon 10 - Ministry of War Information Center","sellStation":"Tanoo V - Moon 1 - Ammatar Consulate Bureau","roi":20.66,"volumeAvailable":32,"maxProfit":932.16},{"typeId":3812,"itemName":"Data Sheets","buyPrice":141,"sellPrice":170.13,"profitPerUnit":29.13,"buyStation":"Sukirah VII - Moon 7 - Amarr Trade Registry Archives","sellStation":"Tanoo V - Moon 1 - Ammatar Consulate Bureau","roi":20.66,"volumeAvailable":32,"maxProfit":932.16},{"typeId":3812,"itemName":"Data Sheets","buyPrice":141,"sellPrice":170.13,"profitPerUnit":29.13,"buyStation":"Mikhir VII - Moon 2 - Amarr Trade Registry Information Center","sellStation":"Tanoo V - Moon 1 - Ammatar Consulate Bureau","roi":20.66,"volumeAvailable":32,"maxProfit":932.16},{"typeId":3812,"itemName":"Data Sheets","buyPrice":141,"sellPrice":170.13,"profitPerUnit":29.13,"buyStation":"Ruchy I - DED Testing Facilities","sellStation":"Tanoo V - Moon 1 - Ammatar Consulate Bureau","roi":20.66,"volumeAvailable":28,"maxProfit":815.64},{"typeId":3812,"itemName":"Data Sheets","buyPrice":141.01,"sellPrice":170.13,"profitPerUnit":29.12,"buyStation":"Kehour VIII - Moon 1 - Emperor Family Bureau","sellStation":"Tanoo V - Moon 1 - Ammatar Consulate Bureau","roi":20.65,"volumeAvailable":32,"maxProfit":931.84},{"typeId":3812,"itemName":"Data Sheets","buyPrice":141.01,"sellPrice":170.13,"profitPerUnit":29.12,"buyStation":"Mabnen IV - Moon 1 - Emperor Family Bureau","sellStation":"Tanoo V - Moon 1 - Ammatar Consulate Bureau","roi":20.65,"volumeAvailable":32,"maxProfit":931.84},{"typeId":3812,"itemName":"Data Sheets","buyPrice":141.01,"sellPrice":170.13,"profitPerUnit":29.12,"buyStation":"Mamenkhanar IX - Moon 11 - DED Logistic Support","sellStation":"Tanoo V - Moon 1 - Ammatar Consulate Bureau","roi":20.65,"volumeAvailable":28,"maxProfit":815.36},{"typeId":3812,"itemName":"Data Sheets","buyPrice":141.01,"sellPrice":170.13,"profitPerUnit":29.12,"buyStation":"Akhragan VIII - Ministry of War Archives","sellStation":"Tanoo V - Moon 1 - Ammatar Consulate Bureau","roi":20.65,"volumeAvailable":32,"maxProfit":931.84},{"typeId":3812,"itemName":"Data Sheets","buyPrice":141.01,"sellPrice":170.13,"profitPerUnit":29.12,"buyStation":"Faswiba VII - Moon 4 - The Scope Development Studio","sellStation":"Tanoo V - Moon 1 - Ammatar Consulate Bureau","roi":20.65,"volumeAvailable":107,"maxProfit":3115.84},{"typeId":3812,"itemName":"Data Sheets","buyPrice":141.02,"sellPrice":170.13,"profitPerUnit":29.11,"buyStation":"Toshabia VI - Moon 1 - The Scope Development Studio","sellStation":"Tanoo V - Moon 1 - Ammatar Consulate Bureau","roi":20.64,"volumeAvailable":107,"maxProfit":3114.77},{"typeId":16273,"itemName":"Liquid Ozone","buyPrice":100,"sellPrice":120,"profitPerUnit":20,"buyStation":"Hedion V - Moon 9 - Court Chamberlain Bureau","sellStation":"Jarizza II - Moon 1 - Ammatar Fleet Assembly Plant","roi":20,"volumeAvailable":462,"maxProfit":9240},{"typeId":3812,"itemName":"Data Sheets","buyPrice":142.44,"sellPrice":170.13,"profitPerUnit":27.69,"buyStation":"Artoun VII - Moon 2 - Amarr Certified News Development Studio","sellStation":"Tanoo V - Moon 1 - Ammatar Consulate Bureau","roi":19.44,"volumeAvailable":107,"maxProfit":2962.83},{"typeId":3812,"itemName":"Data Sheets","buyPrice":143.04,"sellPrice":170.13,"profitPerUnit":27.09,"buyStation":"Mabnen VIII - Moon 2 - The Scope Development Studio","sellStation":"Tanoo V - Moon 1 - Ammatar Consulate Bureau","roi":18.94,"volumeAvailable":107,"maxProfit":2898.63},{"typeId":5405,"itemName":"Initiated Compact Warp Disruptor","buyPrice":1701,"sellPrice":2000,"profitPerUnit":299,"buyStation":"Jerma VIII - Moon 3 - Theology Council Tribunal","sellStation":"Kasrasi IX - Moon 7 - DED Assembly Plant","roi":17.58,"volumeAvailable":1,"maxProfit":299},{"typeId":3812,"itemName":"Data Sheets","buyPrice":145.69,"sellPrice":170.13,"profitPerUnit":24.44,"buyStation":"Amarr VIII (Oris) - Emperor Family Academy","sellStation":"Tanoo V - Moon 1 - Ammatar Consulate Bureau","roi":16.78,"volumeAvailable":32,"maxProfit":782.08},{"typeId":9826,"itemName":"Carbon","buyPrice":332.5,"sellPrice":385.88,"profitPerUnit":53.38,"buyStation":"Ana VII - Moon 3 - Ducia Foundry Mineral Reserve","sellStation":"Uplingur III - Moon 8 - Nurtura Plantation","roi":16.05,"volumeAvailable":2310,"maxProfit":123307.8},{"typeId":9826,"itemName":"Carbon","buyPrice":332.5,"sellPrice":385.88,"profitPerUnit":53.38,"buyStation":"Maiah IV - Moon 1 - Ducia Foundry Refinery","sellStation":"Uplingur III - Moon 8 - Nurtura Plantation","roi":16.05,"volumeAvailable":2310,"maxProfit":123307.8},{"typeId":9826,"itemName":"Carbon","buyPrice":332.5,"sellPrice":385.88,"profitPerUnit":53.38,"buyStation":"Maiah VIII - Moon 3 - Ducia Foundry Refinery","sellStation":"Uplingur III - Moon 8 - Nurtura Plantation","roi":16.05,"volumeAvailable":2310,"maxProfit":123307.8},{"typeId":9826,"itemName":"Carbon","buyPrice":332.5,"sellPrice":385.88,"profitPerUnit":53.38,"buyStation":"Jambu VI - Moon 3 - CreoDron Factory","sellStation":"Uplingur III - Moon 8 - Nurtura Plantation","roi":16.05,"volumeAvailable":2219,"maxProfit":118450.22},{"typeId":9826,"itemName":"Carbon","buyPrice":332.5,"sellPrice":385.88,"profitPerUnit":53.38,"buyStation":"Arton II - CreoDron Factory","sellStation":"Uplingur III - Moon 8 - Nurtura Plantation","roi":16.05,"volumeAvailable":2219,"maxProfit":118450.22},{"typeId":9826,"itemName":"Carbon","buyPrice":332.5,"sellPrice":385.88,"profitPerUnit":53.38,"buyStation":"Bittanshal VII - Moon 9 - CreoDron Factory","sellStation":"Uplingur III - Moon 8 - Nurtura Plantation","roi":16.05,"volumeAvailable":2219,"maxProfit":118450.22},{"typeId":9826,"itemName":"Carbon","buyPrice":332.5,"sellPrice":385.88,"profitPerUnit":53.38,"buyStation":"Warouh VII - Moon 1 - CreoDron Factory","sellStation":"Uplingur III - Moon 8 - Nurtura Plantation","roi":16.05,"volumeAvailable":2219,"maxProfit":118450.22},{"typeId":9826,"itemName":"Carbon","buyPrice":332.5,"sellPrice":385.88,"profitPerUnit":53.38,"buyStation":"Bika III - CreoDron Factory","sellStation":"Uplingur III - Moon 8 - Nurtura Plantation","roi":16.05,"volumeAvailable":2219,"maxProfit":118450.22},{"typeId":9826,"itemName":"Carbon","buyPrice":332.5,"sellPrice":385.88,"profitPerUnit":53.38,"buyStation":"Bika VIII - Moon 11 - CreoDron Warehouse","sellStation":"Uplingur III - Moon 8 - Nurtura Plantation","roi":16.05,"volumeAvailable":2219,"maxProfit":118450.22},{"typeId":9826,"itemName":"Carbon","buyPrice":332.5,"sellPrice":385.88,"profitPerUnit":53.38,"buyStation":"Bika V - Moon 1 - CreoDron Warehouse","sellStation":"Uplingur III - Moon 8 - Nurtura Plantation","roi":16.05,"volumeAvailable":2219,"maxProfit":118450.22},{"typeId":9826,"itemName":"Carbon","buyPrice":332.5,"sellPrice":385.88,"profitPerUnit":53.38,"buyStation":"Bika VII - Moon 1 - CreoDron Factory","sellStation":"Uplingur III - Moon 8 - Nurtura Plantation","roi":16.05,"volumeAvailable":2219,"maxProfit":118450.22},{"typeId":9826,"itemName":"Carbon","buyPrice":332.5,"sellPrice":385.88,"profitPerUnit":53.38,"buyStation":"Avair X - Hedion University","sellStation":"Uplingur III - Moon 8 - Nurtura Plantation","roi":16.05,"volumeAvailable":305,"maxProfit":16280.9},{"typeId":9826,"itemName":"Carbon","buyPrice":332.5,"sellPrice":385.88,"profitPerUnit":53.38,"buyStation":"Mista VI - Moon 16 - Hedion University","sellStation":"Uplingur III - Moon 8 - Nurtura Plantation","roi":16.05,"volumeAvailable":305,"maxProfit":16280.9},{"typeId":9826,"itemName":"Carbon","buyPrice":332.5,"sellPrice":385.88,"profitPerUnit":53.38,"buyStation":"Ziona VII - Moon 13 - Ministry of War Archives","sellStation":"Uplingur III - Moon 8 - Nurtura Plantation","roi":16.05,"volumeAvailable":10,"maxProfit":533.8},{"typeId":9826,"itemName":"Carbon","buyPrice":332.5,"sellPrice":385.88,"profitPerUnit":53.38,"buyStation":"Penirgman IX - Moon 7 - Modern Finances Depository","sellStation":"Uplingur III - Moon 8 - Nurtura Plantation","roi":16.05,"volumeAvailable":3430,"maxProfit":183093.4},{"typeId":9826,"itemName":"Carbon","buyPrice":332.5,"sellPrice":385.88,"profitPerUnit":53.38,"buyStation":"Akhragan VIII - Ministry of War Archives","sellStation":"Uplingur III - Moon 8 - Nurtura Plantation","roi":16.05,"volumeAvailable":10,"maxProfit":533.8},{"typeId":9826,"itemName":"Carbon","buyPrice":332.5,"sellPrice":385.88,"profitPerUnit":53.38,"buyStation":"Sukirah V - Moon 3 - Ministry of War Archives","sellStation":"Uplingur III - Moon 8 - Nurtura Plantation","roi":16.05,"volumeAvailable":10,"maxProfit":533.8},{"typeId":9826,"itemName":"Carbon","buyPrice":332.5,"sellPrice":385.88,"profitPerUnit":53.38,"buyStation":"Mikhir V - Moon 10 - Ministry of War Information Center","sellStation":"Uplingur III - Moon 8 - Nurtura Plantation","roi":16.05,"volumeAvailable":10,"maxProfit":533.8},{"typeId":33475,"itemName":"Mobile Tractor Unit","buyPrice":8210000,"sellPrice":9500000,"profitPerUnit":1290000,"buyStation":"Amarr VIII (Oris) - Emperor Family Academy","sellStation":"Serad IV - Moon 12 - Ammatar Fleet Logistic Support","roi":15.71,"volumeAvailable":5,"maxProfit":6450000},{"typeId":4247,"itemName":"Helium Fuel Block","buyPrice":16990,"sellPrice":19500,"profitPerUnit":2510,"buyStation":"Amarr VIII (Oris) - Emperor Family Academy","sellStation":"Chidah VIII - Moon 17 - CONCORD Assembly Plant","roi":14.77,"volumeAvailable":1289,"maxProfit":3235390},{"typeId":16273,"itemName":"Liquid Ozone","buyPrice":105,"sellPrice":120,"profitPerUnit":15,"buyStation":"Clarelam VI - Moon 2 - Carthum Conglomerate Foundry","sellStation":"Jarizza II - Moon 1 - Ammatar Fleet Assembly Plant","roi":14.29,"volumeAvailable":5288,"maxProfit":79320},{"typeId":16273,"itemName":"Liquid Ozone","buyPrice":105,"sellPrice":120,"profitPerUnit":15,"buyStation":"Sibot XII - Carthum Conglomerate Production Plant","sellStation":"Jarizza II - Moon 1 - Ammatar Fleet Assembly Plant","roi":14.29,"volumeAvailable":8400,"maxProfit":126000},{"typeId":16273,"itemName":"Liquid Ozone","buyPrice":105,"sellPrice":120,"profitPerUnit":15,"buyStation":"Asoutar V - Moon 5 - Theology Council Accounting","sellStation":"Jarizza II - Moon 1 - Ammatar Fleet Assembly Plant","roi":14.29,"volumeAvailable":22125,"maxProfit":331875},{"typeId":62560,"itemName":"Compressed Crokite","buyPrice":6650,"sellPrice":7600,"profitPerUnit":950,"buyStation":"Amarr VIII (Oris) - Emperor Family Academy","sellStation":"Kiereend VII - Moon 3 - DED Assembly Plant","roi":14.29,"volumeAvailable":23043,"maxProfit":21890850},{"typeId":16433,"itemName":"Small I-ax Enduring Remote Armor Repairer","buyPrice":2204,"sellPrice":2500,"profitPerUnit":296,"buyStation":"Amarr VIII (Oris) - Emperor Family Academy","sellStation":"Kasrasi IX - Moon 7 - DED Assembly Plant","roi":13.43,"volumeAvailable":1,"maxProfit":296},{"typeId":16179,"itemName":"Khanid Rookie Insignia","buyPrice":3998,"sellPrice":4500,"profitPerUnit":502,"buyStation":"Amarr VIII (Oris) - Emperor Family Academy","sellStation":"Futzchag IX - Moon 9 - Thukker Mix Factory","roi":12.56,"volumeAvailable":7,"maxProfit":3514},{"typeId":43,"itemName":"Antibiotics","buyPrice":333.74,"sellPrice":375.5,"profitPerUnit":41.76,"buyStation":"Boranai VII - Moon 17 - Expert Distribution Retail Center","sellStation":"Ibaria III - Thukker Mix Warehouse","roi":12.51,"volumeAvailable":6989,"maxProfit":291860.64},{"typeId":43,"itemName":"Antibiotics","buyPrice":333.74,"sellPrice":375.5,"profitPerUnit":41.76,"buyStation":"Boranai VIII - Expert Distribution Warehouse","sellStation":"Ibaria III - Thukker Mix Warehouse","roi":12.51,"volumeAvailable":6989,"maxProfit":291860.64},{"typeId":43,"itemName":"Antibiotics","buyPrice":333.74,"sellPrice":375.5,"profitPerUnit":41.76,"buyStation":"Simbeloud IX - Moon 1 - Expert Distribution Warehouse","sellStation":"Ibaria III - Thukker Mix Warehouse","roi":12.51,"volumeAvailable":6989,"maxProfit":291860.64},{"typeId":43,"itemName":"Antibiotics","buyPrice":333.74,"sellPrice":375.5,"profitPerUnit":41.76,"buyStation":"Eba II - Expert Distribution Warehouse","sellStation":"Ibaria III - Thukker Mix Warehouse","roi":12.51,"volumeAvailable":6989,"maxProfit":291860.64},{"typeId":43,"itemName":"Antibiotics","buyPrice":333.74,"sellPrice":375.5,"profitPerUnit":41.76,"buyStation":"Eba VII - Moon 4 - Expert Distribution Retail Center","sellStation":"Ibaria III - Thukker Mix Warehouse","roi":12.51,"volumeAvailable":6989,"maxProfit":291860.64},{"typeId":43,"itemName":"Antibiotics","buyPrice":333.74,"sellPrice":375.5,"profitPerUnit":41.76,"buyStation":"Teshi V - Moon 6 - Core Complexion Inc. Storage","sellStation":"Ibaria III - Thukker Mix Warehouse","roi":12.51,"volumeAvailable":8437,"maxProfit":352329.12},{"typeId":43,"itemName":"Antibiotics","buyPrice":333.74,"sellPrice":375.5,"profitPerUnit":41.76,"buyStation":"Simbeloud VI - Expert Distribution Warehouse","sellStation":"Ibaria III - Thukker Mix Warehouse","roi":12.51,"volumeAvailable":6989,"maxProfit":291860.64},{"typeId":1403,"itemName":"Inertial Stabilizers I","buyPrice":12000,"sellPrice":13500,"profitPerUnit":1500,"buyStation":"Amarr VIII (Oris) - Emperor Family Academy","sellStation":"Kasrasi IX - Moon 7 - DED Assembly Plant","roi":12.5,"volumeAvailable":3,"maxProfit":4500},{"typeId":3812,"itemName":"Data Sheets","buyPrice":151.5,"sellPrice":170.13,"profitPerUnit":18.63,"buyStation":"Penirgman VII - Ministry of Internal Order Assembly Plant","sellStation":"Tanoo V - Moon 1 - Ammatar Consulate Bureau","roi":12.3,"volumeAvailable":10,"maxProfit":186.3},{"typeId":43,"itemName":"Antibiotics","buyPrice":336.36,"sellPrice":375.5,"profitPerUnit":39.14,"buyStation":"Naguton VIII - Moon 1 - Sisters of EVE Academy","sellStation":"Ibaria III - Thukker Mix Warehouse","roi":11.64,"volumeAvailable":8437,"maxProfit":330224.18},{"typeId":43,"itemName":"Antibiotics","buyPrice":336.34,"sellPrice":375.5,"profitPerUnit":39.16,"buyStation":"Amod VII - Moon 1 - Sisters of EVE Academy","sellStation":"Ibaria III - Thukker Mix Warehouse","roi":11.64,"volumeAvailable":8437,"maxProfit":330392.92},{"typeId":4247,"itemName":"Helium Fuel Block","buyPrice":17500,"sellPrice":19500,"profitPerUnit":2000,"buyStation":"Rayl X - Moon 3 - Carthum Conglomerate Factory","sellStation":"Chidah VIII - Moon 17 - CONCORD Assembly Plant","roi":11.43,"volumeAvailable":1289,"maxProfit":2578000},{"typeId":15999,"itemName":"Caldari Navy Captain Insignia V","buyPrice":45000,"sellPrice":50000,"profitPerUnit":5000,"buyStation":"Penirgman IX - Moon 3 - Ministry of Internal Order Assembly Plant","sellStation":"Hasateem VI - Moon 12 - Thukker Mix Factory","roi":11.11,"volumeAvailable":1,"maxProfit":5000},{"typeId":25604,"itemName":"Conductive Polymer","buyPrice":18030,"sellPrice":20000,"profitPerUnit":1970,"buyStation":"Amarr VIII (Oris) - Emperor Family Academy","sellStation":"Gelhan IX - Moon 6 - Ammatar Fleet Assembly Plant","roi":10.93,"volumeAvailable":28,"maxProfit":55160},{"typeId":20417,"itemName":"Datacore - Electromagnetic Physics","buyPrice":92210,"sellPrice":102100,"profitPerUnit":9890,"buyStation":"Misaba V - Moon 3 - Zoar and Sons Factory","sellStation":"Zemalu IX - Moon 2 - Thukker Mix Factory","roi":10.73,"volumeAvailable":8,"maxProfit":79120},{"typeId":15596,"itemName":"Caldari Navy Midshipman Insignia I","buyPrice":4070,"sellPrice":4500,"profitPerUnit":430,"buyStation":"Penirgman IX - Moon 3 - Ministry of Internal Order Assembly Plant","sellStation":"Nakah I - Moon 1 - Thukker Mix Factory","roi":10.57,"volumeAvailable":9,"maxProfit":3870},{"typeId":16262,"itemName":"Clear Icicle","buyPrice":201100,"sellPrice":222000,"profitPerUnit":20900,"buyStation":"Esteban VIII - Moon 4 - DED Logistic Support","sellStation":"Kasrasi IX - Moon 7 - DED Assembly Plant","roi":10.39,"volumeAvailable":404,"maxProfit":8443600},{"typeId":9826,"itemName":"Carbon","buyPrice":349.69,"sellPrice":385.88,"profitPerUnit":36.19,"buyStation":"Penirgman V - Moon 2 - Modern Finances Depository","sellStation":"Uplingur III - Moon 8 - Nurtura Plantation","roi":10.35,"volumeAvailable":3430,"maxProfit":124131.7},{"typeId":43,"itemName":"Antibiotics","buyPrice":344.5,"sellPrice":375.5,"profitPerUnit":31,"buyStation":"Amarr VIII (Oris) - Moon 4 - Expert Distribution Retail Center","sellStation":"Ibaria III - Thukker Mix Warehouse","roi":9,"volumeAvailable":6989,"maxProfit":216659},{"typeId":3812,"itemName":"Data Sheets","buyPrice":156.52,"sellPrice":170.13,"profitPerUnit":13.61,"buyStation":"Faswiba VIII - Moon 3 - The Scope Publisher","sellStation":"Tanoo V - Moon 1 - Ammatar Consulate Bureau","roi":8.7,"volumeAvailable":107,"maxProfit":1456.27},{"typeId":2464,"itemName":"Hornet I","buyPrice":9000,"sellPrice":9750,"profitPerUnit":750,"buyStation":"Penirgman VII - Ministry of Internal Order Assembly Plant","sellStation":"Alkez VI - Moon 1 - Nurtura Plantation","roi":8.33,"volumeAvailable":10,"maxProfit":7500},{"typeId":22542,"itemName":"Mining Laser Upgrade I","buyPrice":60000,"sellPrice":65000,"profitPerUnit":5000,"buyStation":"Clarelam IV - Moon 4 - Carthum Conglomerate Foundry","sellStation":"Dysa II - Ammatar Fleet Assembly Plant","roi":8.33,"volumeAvailable":4,"maxProfit":20000},{"typeId":9852,"itemName":"Tobacco","buyPrice":55,"sellPrice":59.34,"profitPerUnit":4.34,"buyStation":"Amarr VIII (Oris) - Emperor Family Academy","sellStation":"Hasateem V - Moon 11 - Imperial Armaments Factory","roi":7.89,"volumeAvailable":20,"maxProfit":86.8},{"typeId":3713,"itemName":"Vitoc","buyPrice":11200,"sellPrice":12071.4,"profitPerUnit":871.4,"buyStation":"Amod VII - Moon 1 - Sisters of EVE Academy","sellStation":"Berta VI - Moon 19 - Ammatar Consulate Bureau","roi":7.78,"volumeAvailable":22,"maxProfit":19170.8},{"typeId":3713,"itemName":"Vitoc","buyPrice":11200,"sellPrice":12071.4,"profitPerUnit":871.4,"buyStation":"Fahruni XII - Sisters of EVE Bureau","sellStation":"Berta VI - Moon 19 - Ammatar Consulate Bureau","roi":7.78,"volumeAvailable":22,"maxProfit":19170.8},{"typeId":3713,"itemName":"Vitoc","buyPrice":11200,"sellPrice":12071.4,"profitPerUnit":871.4,"buyStation":"Naguton VIII - Moon 1 - Sisters of EVE Academy","sellStation":"Berta VI - Moon 19 - Ammatar Consulate Bureau","roi":7.78,"volumeAvailable":22,"maxProfit":19170.8},{"typeId":16617,"itemName":"CONCORD Star Emblem","buyPrice":9340000,"sellPrice":10000000,"profitPerUnit":660000,"buyStation":"Amarr VIII (Oris) - Emperor Family Academy","sellStation":"Hasateem VI - Moon 12 - Thukker Mix Factory","roi":7.07,"volumeAvailable":1,"maxProfit":660000},{"typeId":3812,"itemName":"Data Sheets","buyPrice":158.95,"sellPrice":170.13,"profitPerUnit":11.18,"buyStation":"Eba VIII - Moon 9 - Amarr Certified News Publisher","sellStation":"Tanoo V - Moon 1 - Ammatar Consulate Bureau","roi":7.03,"volumeAvailable":107,"maxProfit":1196.26},{"typeId":62568,"itemName":"Compressed Arkonor","buyPrice":4675,"sellPrice":5000,"profitPerUnit":325,"buyStation":"Bittanshal I - Moon 1 - Inherent Implants Biotech Production","sellStation":"Kiereend VII - Moon 3 - DED Assembly Plant","roi":6.95,"volumeAvailable":56487,"maxProfit":18358275},{"typeId":62544,"itemName":"Compressed Hemorphite","buyPrice":1130,"sellPrice":1200,"profitPerUnit":70,"buyStation":"Amarr VIII (Oris) - Emperor Family Academy","sellStation":"Kiereend VII - Moon 3 - DED Assembly Plant","roi":6.19,"volumeAvailable":6433,"maxProfit":450310},{"typeId":15646,"itemName":"Federation Navy Command Sergeant Major Insignia I","buyPrice":47190,"sellPrice":50000,"profitPerUnit":2810,"buyStation":"Amarr VIII (Oris) - Emperor Family Academy","sellStation":"Hasateem VI - Moon 12 - Thukker Mix Factory","roi":5.95,"volumeAvailable":9,"maxProfit":25290},{"typeId":15998,"itemName":"Republic Fleet Private Insignia V","buyPrice":47420,"sellPrice":50000,"profitPerUnit":2580,"buyStation":"Amarr VIII (Oris) - Emperor Family Academy","sellStation":"Hasateem VI - Moon 12 - Thukker Mix Factory","roi":5.44,"volumeAvailable":3,"maxProfit":7740},{"typeId":15590,"itemName":"Federation Navy Sergeant Insignia I","buyPrice":18990,"sellPrice":20000,"profitPerUnit":1010,"buyStation":"Amarr VIII (Oris) - Emperor Family Academy","sellStation":"Thiarer VII - Moon 4 - Ammatar Fleet Assembly Plant","roi":5.32,"volumeAvailable":5,"maxProfit":5050},{"typeId":25604,"itemName":"Conductive Polymer","buyPrice":19000,"sellPrice":20000,"profitPerUnit":1000,"buyStation":"Afivad IX - Moon 2 - HZO Refinery","sellStation":"Gelhan IX - Moon 6 - Ammatar Fleet Assembly Plant","roi":5.26,"volumeAvailable":1,"maxProfit":1000},{"typeId":15674,"itemName":"Minmatar Freedom Fighter Insignia I","buyPrice":19000,"sellPrice":20000,"profitPerUnit":1000,"buyStation":"Amarr VIII (Oris) - Emperor Family Academy","sellStation":"Uzistoon VI - Moon 3 - Ammatar Fleet Assembly Plant","roi":5.26,"volumeAvailable":1,"maxProfit":1000},{"typeId":30744,"itemName":"Neural Network Analyzer","buyPrice":190100,"sellPrice":200000,"profitPerUnit":9900,"buyStation":"Misaba V - Moon 3 - Zoar and Sons Factory","sellStation":"Zemalu IX - Moon 2 - Thukker Mix Factory","roi":5.21,"volumeAvailable":10,"maxProfit":99000},{"typeId":15625,"itemName":"Republic Fleet Midshipman Insignia I","buyPrice":4290,"sellPrice":4500,"profitPerUnit":210,"buyStation":"Amarr VIII (Oris) - Emperor Family Academy","sellStation":"Hasateem VI - Moon 12 - Thukker Mix Factory","roi":4.9,"volumeAvailable":4,"maxProfit":840},{"typeId":15994,"itemName":"Federation Navy Sergeant Insignia II","buyPrice":23870,"sellPrice":25000,"profitPerUnit":1130,"buyStation":"Amarr VIII (Oris) - Emperor Family Academy","sellStation":"Futzchag IX - Moon 9 - Thukker Mix Factory","roi":4.73,"volumeAvailable":6,"maxProfit":6780},{"typeId":2351,"itemName":"Smartfab Units","buyPrice":90960,"sellPrice":95000,"profitPerUnit":4040,"buyStation":"Amarr VIII (Oris) - Emperor Family Academy","sellStation":"Kiereend VII - Moon 3 - DED Assembly Plant","roi":4.44,"volumeAvailable":500,"maxProfit":2020000},{"typeId":28237,"itemName":"Caldari Navy Fleet Rear-Admiral Insignia","buyPrice":4797000,"sellPrice":5000000,"profitPerUnit":203000,"buyStation":"Amarr VIII (Oris) - Emperor Family Academy","sellStation":"Hasateem VI - Moon 12 - Thukker Mix Factory","roi":4.23,"volumeAvailable":1,"maxProfit":203000},{"typeId":19404,"itemName":"5th Tier Overseer's Personal Effects","buyPrice":172700,"sellPrice":180000,"profitPerUnit":7300,"buyStation":"Amarr VIII (Oris) - Emperor Family Academy","sellStation":"Juddi VII - DED Logistic Support","roi":4.23,"volumeAvailable":1,"maxProfit":7300},{"typeId":15593,"itemName":"Federation Navy Fleet Major Insignia I","buyPrice":96000,"sellPrice":100000,"profitPerUnit":4000,"buyStation":"Amarr VIII (Oris) - Emperor Family Academy","sellStation":"Ishkad VIII - Ammatar Fleet Testing Facilities","roi":4.17,"volumeAvailable":26,"maxProfit":104000},{"typeId":19404,"itemName":"5th Tier Overseer's Personal Effects","buyPrice":172900,"sellPrice":180000,"profitPerUnit":7100,"buyStation":"Arshat VII - Moon 4 - Theology Council Law School","sellStation":"Juddi VII - DED Logistic Support","roi":4.11,"volumeAvailable":1,"maxProfit":7100},{"typeId":19404,"itemName":"5th Tier Overseer's Personal Effects","buyPrice":173100,"sellPrice":180000,"profitPerUnit":6900,"buyStation":"Zaimeth IX - Moon 15 - Amarr Navy Assembly Plant","sellStation":"Juddi VII - DED Logistic Support","roi":3.99,"volumeAvailable":1,"maxProfit":6900},{"typeId":19406,"itemName":"7th Tier Overseer's Personal Effects","buyPrice":578700,"sellPrice":600000,"profitPerUnit":21300,"buyStation":"Amarr VIII (Oris) - Emperor Family Academy","sellStation":"Gelhan V - Moon 10 - DED Logistic Support","roi":3.68,"volumeAvailable":1,"maxProfit":21300},{"typeId":15627,"itemName":"Republic Fleet Midshipman Insignia III","buyPrice":14490,"sellPrice":15000,"profitPerUnit":510,"buyStation":"Amarr VIII (Oris) - Emperor Family Academy","sellStation":"Nakah I - Moon 1 - Thukker Mix Factory","roi":3.52,"volumeAvailable":3,"maxProfit":1530},{"typeId":85179,"itemName":"Overseer Sabik Vial","buyPrice":966000,"sellPrice":1000000,"profitPerUnit":34000,"buyStation":"Amarr VIII (Oris) - Emperor Family Academy","sellStation":"Chidah V - CONCORD Assembly Plant","roi":3.52,"volumeAvailable":84,"maxProfit":2856000},{"typeId":15589,"itemName":"Federation Navy Midshipman Insignia III","buyPrice":14490,"sellPrice":15000,"profitPerUnit":510,"buyStation":"Bahromab V - Ministry of Assessment Bureau Offices","sellStation":"Hothomouh VII - Moon 2 - Ammatar Fleet Assembly Plant","roi":3.52,"volumeAvailable":7,"maxProfit":3570},{"typeId":19405,"itemName":"6th Tier Overseer's Personal Effects","buyPrice":347900,"sellPrice":360000,"profitPerUnit":12100,"buyStation":"Amarr VIII (Oris) - Emperor Family Academy","sellStation":"Gelhan V - Moon 10 - DED Logistic Support","roi":3.48,"volumeAvailable":4,"maxProfit":48400},{"typeId":91105,"itemName":"Nation Stormhive Shard","buyPrice":966400,"sellPrice":1000000,"profitPerUnit":33600,"buyStation":"Amarr VIII (Oris) - Emperor Family Academy","sellStation":"Rashy VI - DED Assembly Plant","roi":3.48,"volumeAvailable":133,"maxProfit":4468800},{"typeId":90072,"itemName":"Cybernetic Neural Lattice","buyPrice":96720,"sellPrice":100000,"profitPerUnit":3280,"buyStation":"Amarr VIII (Oris) - Emperor Family Academy","sellStation":"Asabona IX - Moon 5 - CONCORD Bureau","roi":3.39,"volumeAvailable":1123,"maxProfit":3683440},{"typeId":19405,"itemName":"6th Tier Overseer's Personal Effects","buyPrice":348200,"sellPrice":360000,"profitPerUnit":11800,"buyStation":"Sarum Prime III - Moon 2 - Imperial Academy","sellStation":"Gelhan V - Moon 10 - DED Logistic Support","roi":3.39,"volumeAvailable":1,"maxProfit":11800},{"typeId":48121,"itemName":"Triglavian Survey Database","buyPrice":96740,"sellPrice":100000,"profitPerUnit":3260,"buyStation":"Amarr VIII (Oris) - Emperor Family Academy","sellStation":"Shamahi IX - Moon 12 - CONCORD Bureau","roi":3.37,"volumeAvailable":219,"maxProfit":713940},{"typeId":19417,"itemName":"19th Tier Overseer's Personal Effects","buyPrice":50000000,"sellPrice":51680000,"profitPerUnit":1680000,"buyStation":"Deepari II - Imperial Academy","sellStation":"Asabona IX - Moon 5 - CONCORD Bureau","roi":3.36,"volumeAvailable":2,"maxProfit":3360000},{"typeId":19416,"itemName":"18th Tier Overseer's Personal Effects","buyPrice":41800000,"sellPrice":43200000,"profitPerUnit":1400000,"buyStation":"Amarr VIII (Oris) - Emperor Family Academy","sellStation":"Rashy VI - DED Assembly Plant","roi":3.35,"volumeAvailable":1,"maxProfit":1400000},{"typeId":15626,"itemName":"Republic Fleet Midshipman Insignia II","buyPrice":7750,"sellPrice":8000,"profitPerUnit":250,"buyStation":"Amarr VIII (Oris) - Emperor Family Academy","sellStation":"Hothomouh VII - Moon 2 - Ammatar Fleet Assembly Plant","roi":3.23,"volumeAvailable":3,"maxProfit":750},{"typeId":87952,"itemName":"Sleeper Protocol Subverter","buyPrice":97000,"sellPrice":100000,"profitPerUnit":3000,"buyStation":"Amarr VIII (Oris) - Emperor Family Academy","sellStation":"Gelhan V - Moon 1 - DED Assembly Plant","roi":3.09,"volumeAvailable":270,"maxProfit":810000},{"typeId":19400,"itemName":"1st Tier Overseer's Personal Effects","buyPrice":10690,"sellPrice":11000,"profitPerUnit":310,"buyStation":"Amarr VIII (Oris) - Emperor Family Academy","sellStation":"Asabona IX - Moon 5 - CONCORD Bureau","roi":2.9,"volumeAvailable":4,"maxProfit":1240},{"typeId":15996,"itemName":"Caldari Navy Captain Insignia IV","buyPrice":29200,"sellPrice":30000,"profitPerUnit":800,"buyStation":"Penirgman IX - Moon 3 - Ministry of Internal Order Assembly Plant","sellStation":"Nakah I - Moon 1 - Thukker Mix Factory","roi":2.74,"volumeAvailable":4,"maxProfit":3200},{"typeId":4247,"itemName":"Helium Fuel Block","buyPrice":18990,"sellPrice":19500,"profitPerUnit":510,"buyStation":"Fahruni VI - Amarr Trade Registry Bureau Offices","sellStation":"Chidah VIII - Moon 17 - CONCORD Assembly Plant","roi":2.69,"volumeAvailable":80,"maxProfit":40800},{"typeId":25594,"itemName":"Tangled Power Conduit","buyPrice":69210,"sellPrice":71000,"profitPerUnit":1790,"buyStation":"Amarr VIII (Oris) - Emperor Family Academy","sellStation":"Kasrasi IX - Moon 7 - DED Assembly Plant","roi":2.59,"volumeAvailable":36,"maxProfit":64440},{"typeId":15588,"itemName":"Federation Navy Midshipman Insignia II","buyPrice":7800,"sellPrice":8000,"profitPerUnit":200,"buyStation":"Amarr VIII (Oris) - Emperor Family Academy","sellStation":"Gamis X - Ammatar Fleet Logistic Support","roi":2.56,"volumeAvailable":6,"maxProfit":1200},{"typeId":19412,"itemName":"14th Tier Overseer's Personal Effects","buyPrice":16740000,"sellPrice":17160000,"profitPerUnit":420000,"buyStation":"Amarr VIII (Oris) - Emperor Family Academy","sellStation":"Asghatil IX - Moon 3 - DED Assembly Plant","roi":2.51,"volumeAvailable":1,"maxProfit":420000},{"typeId":15627,"itemName":"Republic Fleet Midshipman Insignia III","buyPrice":14670,"sellPrice":15000,"profitPerUnit":330,"buyStation":"Bahromab VIII - Moon 3 - Ministry of Assessment Information Center","sellStation":"Nakah I - Moon 1 - Thukker Mix Factory","roi":2.25,"volumeAvailable":1,"maxProfit":330},{"typeId":15627,"itemName":"Republic Fleet Midshipman Insignia III","buyPrice":14670,"sellPrice":15000,"profitPerUnit":330,"buyStation":"Penirgman VII - Ministry of Internal Order Assembly Plant","sellStation":"Nakah I - Moon 1 - Thukker Mix Factory","roi":2.25,"volumeAvailable":1,"maxProfit":330},{"typeId":90566,"itemName":"Proof of Transmission","buyPrice":1468000,"sellPrice":1500000,"profitPerUnit":32000,"buyStation":"Amarr VIII (Oris) - Emperor Family Academy","sellStation":"Asabona IX - Moon 5 - CONCORD Bureau","roi":2.18,"volumeAvailable":1,"maxProfit":32000},{"typeId":91773,"itemName":"Rampancy Data Dump","buyPrice":195900,"sellPrice":200000,"profitPerUnit":4100,"buyStation":"Amarr VIII (Oris) - Emperor Family Academy","sellStation":"Gelhan V - Moon 1 - DED Assembly Plant","roi":2.09,"volumeAvailable":270,"maxProfit":1107000},{"typeId":19417,"itemName":"19th Tier Overseer's Personal Effects","buyPrice":50700000,"sellPrice":51680000,"profitPerUnit":980000,"buyStation":"Amarr VIII (Oris) - Emperor Family Academy","sellStation":"Asabona IX - Moon 5 - CONCORD Bureau","roi":1.93,"volumeAvailable":1,"maxProfit":980000},{"typeId":19421,"itemName":"23rd Tier Overseer's Personal Effects","buyPrice":131400000,"sellPrice":133837000,"profitPerUnit":2437000,"buyStation":"Amarr VIII (Oris) - Emperor Family Academy","sellStation":"Asabona IX - Moon 5 - CONCORD Bureau","roi":1.85,"volumeAvailable":1,"maxProfit":2437000},{"typeId":55930,"itemName":"100K Bounty SCC Encrypted Bond","buyPrice":98380,"sellPrice":100000,"profitPerUnit":1620,"buyStation":"Misaba V - Moon 3 - Zoar and Sons Factory","sellStation":"Asabona IX - Moon 5 - CONCORD Bureau","roi":1.65,"volumeAvailable":8,"maxProfit":12960},{"typeId":16678,"itemName":"Sylramic Fibers","buyPrice":263.2,"sellPrice":267.5,"profitPerUnit":4.3,"buyStation":"Amarr VIII (Oris) - Emperor Family Academy","sellStation":"Jarizza II - Moon 1 - Ammatar Fleet Assembly Plant","roi":1.63,"volumeAvailable":150000,"maxProfit":645000},{"typeId":33522,"itemName":"'Yurt' Mobile Depot","buyPrice":25590000,"sellPrice":25990000,"profitPerUnit":400000,"buyStation":"Amarr VIII (Oris) - Emperor Family Academy","sellStation":"Yuzier V - Moon 1 - Ammatar Fleet Assembly Plant","roi":1.56,"volumeAvailable":1,"maxProfit":400000},{"typeId":19411,"itemName":"13th Tier Overseer's Personal Effects","buyPrice":13000000,"sellPrice":13200000,"profitPerUnit":200000,"buyStation":"Amarr VIII (Oris) - Emperor Family Academy","sellStation":"Asabona IX - Moon 5 - CONCORD Bureau","roi":1.54,"volumeAvailable":1,"maxProfit":200000},{"typeId":20417,"itemName":"Datacore - Electromagnetic Physics","buyPrice":100700,"sellPrice":102100,"profitPerUnit":1400,"buyStation":"Amarr VIII (Oris) - Emperor Family Academy","sellStation":"Zemalu IX - Moon 2 - Thukker Mix Factory","roi":1.39,"volumeAvailable":100,"maxProfit":140000},{"typeId":55931,"itemName":"10K Bounty SCC Encrypted Bond","buyPrice":9872,"sellPrice":10000,"profitPerUnit":128,"buyStation":"Misaba V - Moon 3 - Zoar and Sons Factory","sellStation":"Asabona IX - Moon 5 - CONCORD Bureau","roi":1.3,"volumeAvailable":9,"maxProfit":1152},{"typeId":25596,"itemName":"Broken Drone Transceiver","buyPrice":2502,"sellPrice":2534,"profitPerUnit":32,"buyStation":"Amarr VIII (Oris) - Emperor Family Academy","sellStation":"Sasta VI - Moon 3 - Ammatar Fleet Assembly Plant","roi":1.28,"volumeAvailable":10,"maxProfit":320},{"typeId":15589,"itemName":"Federation Navy Midshipman Insignia III","buyPrice":14810,"sellPrice":15000,"profitPerUnit":190,"buyStation":"Amarr VIII (Oris) - Emperor Family Academy","sellStation":"Hothomouh VII - Moon 2 - Ammatar Fleet Assembly Plant","roi":1.28,"volumeAvailable":4,"maxProfit":760},{"typeId":29337,"itemName":"Augoror Navy Issue","buyPrice":42490000,"sellPrice":43010000,"profitPerUnit":520000,"buyStation":"Amarr VIII (Oris) - Emperor Family Academy","sellStation":"Hothomouh VII - Moon 2 - Ammatar Fleet Assembly Plant","roi":1.22,"volumeAvailable":2,"maxProfit":1040000},{"typeId":25594,"itemName":"Tangled Power Conduit","buyPrice":70200,"sellPrice":71000,"profitPerUnit":800,"buyStation":"Amarr VIII (Oris) - Moon 4 - Expert Distribution Retail Center","sellStation":"Kasrasi IX - Moon 7 - DED Assembly Plant","roi":1.14,"volumeAvailable":29,"maxProfit":23200},{"typeId":15587,"itemName":"Federation Navy Midshipman Insignia I","buyPrice":4450,"sellPrice":4500,"profitPerUnit":50,"buyStation":"Amarr VIII (Oris) - Emperor Family Academy","sellStation":"Hasateem VI - Moon 12 - Thukker Mix Factory","roi":1.12,"volumeAvailable":25,"maxProfit":1250},{"typeId":19419,"itemName":"21st Tier Overseer's Personal Effects","buyPrice":79300000,"sellPrice":80000000,"profitPerUnit":700000,"buyStation":"Amarr VIII (Oris) - Emperor Family Academy","sellStation":"Asabona IX - Moon 5 - CONCORD Bureau","roi":0.88,"volumeAvailable":1,"maxProfit":700000},{"typeId":19422,"itemName":"10th Tier Overseer's Personal Effects","buyPrice":3332000,"sellPrice":3360000,"profitPerUnit":28000,"buyStation":"Amarr VIII (Oris) - Emperor Family Academy","sellStation":"Asabona IX - Moon 5 - CONCORD Bureau","roi":0.84,"volumeAvailable":4,"maxProfit":112000},{"typeId":5137,"itemName":"Small Knave Scoped Energy Nosferatu","buyPrice":2481,"sellPrice":2500,"profitPerUnit":19,"buyStation":"Amarr VIII (Oris) - Emperor Family Academy","sellStation":"Kasrasi IX - Moon 7 - DED Assembly Plant","roi":0.77,"volumeAvailable":2,"maxProfit":38},{"typeId":55933,"itemName":"1M Bounty SCC Encrypted Bond","buyPrice":993000,"sellPrice":1000000,"profitPerUnit":7000,"buyStation":"Misaba V - Moon 3 - Zoar and Sons Factory","sellStation":"Asabona IX - Moon 5 - CONCORD Bureau","roi":0.7,"volumeAvailable":16,"maxProfit":112000},{"typeId":9852,"itemName":"Tobacco","buyPrice":59.19,"sellPrice":59.34,"profitPerUnit":0.15,"buyStation":"Ebtesham V - Amarr Navy Assembly Plant","sellStation":"Hasateem V - Moon 11 - Imperial Armaments Factory","roi":0.25,"volumeAvailable":19,"maxProfit":2.85},{"typeId":28236,"itemName":"Federation Navy Fleet Rear-Admiral Insignia","buyPrice":4990000,"sellPrice":5000000,"profitPerUnit":10000,"buyStation":"Amarr VIII (Oris) - Emperor Family Academy","sellStation":"Nakah IV - Moon 1 - Ammatar Fleet Logistic Support","roi":0.2,"volumeAvailable":1,"maxProfit":10000},{"typeId":19407,"itemName":"8th Tier Overseer's Personal Effects","buyPrice":1198000,"sellPrice":1200000,"profitPerUnit":2000,"buyStation":"Amarr VIII (Oris) - Emperor Family Academy","sellStation":"Maspah IV - Moon 7 - DED Assembly Plant","roi":0.17,"volumeAvailable":20,"maxProfit":40000}]}