{"lastUpdated":"2026-03-29T16:28:33.447Z","buyRegion":10000030,"sellRegion":10000038,"buyRegionName":"Heimatar","sellRegionName":"The Bleak Lands","opportunities":[{"typeId":17366,"itemName":"Station Container","buyPrice":37000,"sellPrice":750000,"profitPerUnit":713000,"buyStation":"Eystur III - Moon 2 - Quafe Company Factory","sellStation":"Huola X - Moon 2 - Ishukone Corporation Factory","roi":1927.03,"volumeAvailable":5,"maxProfit":3565000},{"typeId":17366,"itemName":"Station Container","buyPrice":49000,"sellPrice":750000,"profitPerUnit":701000,"buyStation":"Alakgur VII - Moon 3 - Republic Security Services Assembly Plant","sellStation":"Huola X - Moon 2 - Ishukone Corporation Factory","roi":1430.61,"volumeAvailable":5,"maxProfit":3505000},{"typeId":17366,"itemName":"Station Container","buyPrice":50000,"sellPrice":750000,"profitPerUnit":700000,"buyStation":"Oremmulf IX - Moon 6 - CreoDron Factory","sellStation":"Huola X - Moon 2 - Ishukone Corporation Factory","roi":1400,"volumeAvailable":2,"maxProfit":1400000},{"typeId":17366,"itemName":"Station Container","buyPrice":59990,"sellPrice":750000,"profitPerUnit":690010,"buyStation":"Hadaugago II - Moon 1 - Republic Military School","sellStation":"Huola X - Moon 2 - Ishukone Corporation Factory","roi":1150.21,"volumeAvailable":4,"maxProfit":2760040},{"typeId":17366,"itemName":"Station Container","buyPrice":60000,"sellPrice":750000,"profitPerUnit":690000,"buyStation":"Dal III - Moon 1 - Republic Fleet Assembly Plant","sellStation":"Huola X - Moon 2 - Ishukone Corporation Factory","roi":1150,"volumeAvailable":5,"maxProfit":3450000},{"typeId":17366,"itemName":"Station Container","buyPrice":74000,"sellPrice":750000,"profitPerUnit":676000,"buyStation":"Isendeldik VIII - Moon 19 - Six Kin Development Warehouse","sellStation":"Huola X - Moon 2 - Ishukone Corporation Factory","roi":913.51,"volumeAvailable":5,"maxProfit":3380000},{"typeId":17366,"itemName":"Station Container","buyPrice":86000,"sellPrice":750000,"profitPerUnit":664000,"buyStation":"Rens VI - Moon 8 - Brutor Tribe Treasury","sellStation":"Huola X - Moon 2 - Ishukone Corporation Factory","roi":772.09,"volumeAvailable":2,"maxProfit":1328000},{"typeId":17366,"itemName":"Station Container","buyPrice":95000,"sellPrice":750000,"profitPerUnit":655000,"buyStation":"Gerek V - Moon 3 - Republic University","sellStation":"Huola X - Moon 2 - Ishukone Corporation Factory","roi":689.47,"volumeAvailable":1,"maxProfit":655000},{"typeId":17366,"itemName":"Station Container","buyPrice":99000,"sellPrice":750000,"profitPerUnit":651000,"buyStation":"Rens VI - Six Kin Development Warehouse","sellStation":"Huola X - Moon 2 - Ishukone Corporation Factory","roi":657.58,"volumeAvailable":5,"maxProfit":3255000},{"typeId":17366,"itemName":"Station Container","buyPrice":104300,"sellPrice":750000,"profitPerUnit":645700,"buyStation":"Malukker I - Republic University","sellStation":"Huola X - Moon 2 - Ishukone Corporation Factory","roi":619.08,"volumeAvailable":5,"maxProfit":3228500},{"typeId":17366,"itemName":"Station Container","buyPrice":106000,"sellPrice":750000,"profitPerUnit":644000,"buyStation":"Lustrevik VII - Moon 9 - Brutor Tribe Academy","sellStation":"Huola X - Moon 2 - Ishukone Corporation Factory","roi":607.55,"volumeAvailable":5,"maxProfit":3220000},{"typeId":17366,"itemName":"Station Container","buyPrice":126100,"sellPrice":750000,"profitPerUnit":623900,"buyStation":"Auga VI - Moon 13 - Six Kin Development Production Plant","sellStation":"Huola X - Moon 2 - Ishukone Corporation Factory","roi":494.77,"volumeAvailable":5,"maxProfit":3119500},{"typeId":17366,"itemName":"Station Container","buyPrice":136100,"sellPrice":750000,"profitPerUnit":613900,"buyStation":"Dammalin I - Quafe Company Factory","sellStation":"Huola X - Moon 2 - Ishukone Corporation Factory","roi":451.07,"volumeAvailable":1,"maxProfit":613900},{"typeId":17366,"itemName":"Station Container","buyPrice":150000,"sellPrice":750000,"profitPerUnit":600000,"buyStation":"Balginia II - Brutor Tribe Bureau","sellStation":"Huola X - Moon 2 - Ishukone Corporation Factory","roi":400,"volumeAvailable":5,"maxProfit":3000000},{"typeId":17366,"itemName":"Station Container","buyPrice":150000,"sellPrice":750000,"profitPerUnit":600000,"buyStation":"Tongofur VIII - Kaalakiota Corporation Warehouse","sellStation":"Huola X - Moon 2 - Ishukone Corporation Factory","roi":400,"volumeAvailable":3,"maxProfit":1800000},{"typeId":17366,"itemName":"Station Container","buyPrice":156100,"sellPrice":750000,"profitPerUnit":593900,"buyStation":"Ammold V - Republic Military School","sellStation":"Huola X - Moon 2 - Ishukone Corporation Factory","roi":380.46,"volumeAvailable":5,"maxProfit":2969500},{"typeId":17366,"itemName":"Station Container","buyPrice":250000,"sellPrice":750000,"profitPerUnit":500000,"buyStation":"Dammalin VI - CBD Corporation Storage","sellStation":"Huola X - Moon 2 - Ishukone Corporation Factory","roi":200,"volumeAvailable":5,"maxProfit":2500000},{"typeId":15626,"itemName":"Republic Fleet Midshipman Insignia II","buyPrice":3000,"sellPrice":8000,"profitPerUnit":5000,"buyStation":"Balginia II - Brutor Tribe Bureau","sellStation":"Oyonata IV - Moon 1 - Amarr Navy Assembly Plant","roi":166.67,"volumeAvailable":1,"maxProfit":5000},{"typeId":11132,"itemName":"Minmatar Shuttle","buyPrice":10000,"sellPrice":25000,"profitPerUnit":15000,"buyStation":"Dammalin I - Quafe Company Factory","sellStation":"Kamela V - 24th Imperial Crusade Logistic Support","roi":150,"volumeAvailable":1,"maxProfit":15000},{"typeId":11129,"itemName":"Gallente Shuttle","buyPrice":10510,"sellPrice":25000,"profitPerUnit":14490,"buyStation":"Rens VI - Moon 8 - Brutor Tribe Treasury","sellStation":"Kamela V - 24th Imperial Crusade Logistic Support","roi":137.87,"volumeAvailable":125,"maxProfit":1811250},{"typeId":672,"itemName":"Caldari Shuttle","buyPrice":10640,"sellPrice":25000,"profitPerUnit":14360,"buyStation":"Rens VI - Moon 8 - Brutor Tribe Treasury","sellStation":"Kamela V - 24th Imperial Crusade Logistic Support","roi":134.96,"volumeAvailable":35,"maxProfit":502600},{"typeId":11129,"itemName":"Gallente Shuttle","buyPrice":11000,"sellPrice":25000,"profitPerUnit":14000,"buyStation":"Ameinaka IX - Moon 21 - Six Kin Development Warehouse","sellStation":"Kamela V - 24th Imperial Crusade Logistic Support","roi":127.27,"volumeAvailable":10,"maxProfit":140000},{"typeId":17366,"itemName":"Station Container","buyPrice":350000,"sellPrice":750000,"profitPerUnit":400000,"buyStation":"Frarn VI - Moon 18 - Brutor Tribe Bureau","sellStation":"Huola X - Moon 2 - Ishukone Corporation Factory","roi":114.29,"volumeAvailable":4,"maxProfit":1600000},{"typeId":11129,"itemName":"Gallente Shuttle","buyPrice":12000,"sellPrice":25000,"profitPerUnit":13000,"buyStation":"Gerbold III - Moon 14 - Republic Military School","sellStation":"Kamela V - 24th Imperial Crusade Logistic Support","roi":108.33,"volumeAvailable":9,"maxProfit":117000},{"typeId":672,"itemName":"Caldari Shuttle","buyPrice":12870,"sellPrice":25000,"profitPerUnit":12130,"buyStation":"Hadaugago II - Moon 1 - Republic Military School","sellStation":"Kamela V - 24th Imperial Crusade Logistic Support","roi":94.25,"volumeAvailable":13,"maxProfit":157690},{"typeId":11129,"itemName":"Gallente Shuttle","buyPrice":13450,"sellPrice":25000,"profitPerUnit":11550,"buyStation":"Hadaugago II - Moon 1 - Republic Military School","sellStation":"Kamela V - 24th Imperial Crusade Logistic Support","roi":85.87,"volumeAvailable":22,"maxProfit":254100},{"typeId":17366,"itemName":"Station Container","buyPrice":405000,"sellPrice":750000,"profitPerUnit":345000,"buyStation":"Vullat VII - Moon 1 - Six Kin Development Foundry","sellStation":"Huola X - Moon 2 - Ishukone Corporation Factory","roi":85.19,"volumeAvailable":5,"maxProfit":1725000},{"typeId":17366,"itemName":"Station Container","buyPrice":405000,"sellPrice":750000,"profitPerUnit":345000,"buyStation":"Emolgranlan V - Moon 12 - Republic Justice Department Tribunal","sellStation":"Huola X - Moon 2 - Ishukone Corporation Factory","roi":85.19,"volumeAvailable":5,"maxProfit":1725000},{"typeId":11132,"itemName":"Minmatar Shuttle","buyPrice":14000,"sellPrice":25000,"profitPerUnit":11000,"buyStation":"Rens VI - Six Kin Development Warehouse","sellStation":"Kamela V - 24th Imperial Crusade Logistic Support","roi":78.57,"volumeAvailable":145,"maxProfit":1595000},{"typeId":11132,"itemName":"Minmatar Shuttle","buyPrice":14050,"sellPrice":25000,"profitPerUnit":10950,"buyStation":"Rens VI - Moon 8 - Brutor Tribe Treasury","sellStation":"Kamela V - 24th Imperial Crusade Logistic Support","roi":77.94,"volumeAvailable":162,"maxProfit":1773900},{"typeId":11132,"itemName":"Minmatar Shuttle","buyPrice":14270,"sellPrice":25000,"profitPerUnit":10730,"buyStation":"Hadaugago II - Moon 1 - Republic Military School","sellStation":"Kamela V - 24th Imperial Crusade Logistic Support","roi":75.19,"volumeAvailable":79,"maxProfit":847670},{"typeId":11134,"itemName":"Amarr Shuttle","buyPrice":14450,"sellPrice":25000,"profitPerUnit":10550,"buyStation":"Hadaugago II - Moon 1 - Republic Military School","sellStation":"Iesa VI - Moon 6 - Ministry of Assessment Information Center","roi":73.01,"volumeAvailable":44,"maxProfit":464200},{"typeId":11132,"itemName":"Minmatar Shuttle","buyPrice":14480,"sellPrice":25000,"profitPerUnit":10520,"buyStation":"Lustrevik VII - Moon 9 - Brutor Tribe Academy","sellStation":"Kamela V - 24th Imperial Crusade Logistic Support","roi":72.65,"volumeAvailable":14,"maxProfit":147280},{"typeId":11132,"itemName":"Minmatar Shuttle","buyPrice":14500,"sellPrice":25000,"profitPerUnit":10500,"buyStation":"Lustrevik VII - Moon 7 - Six Kin Development Warehouse","sellStation":"Kamela V - 24th Imperial Crusade Logistic Support","roi":72.41,"volumeAvailable":6,"maxProfit":63000},{"typeId":11132,"itemName":"Minmatar Shuttle","buyPrice":14700,"sellPrice":25000,"profitPerUnit":10300,"buyStation":"Ameinaka IX - Moon 21 - Six Kin Development Warehouse","sellStation":"Kamela V - 24th Imperial Crusade Logistic Support","roi":70.07,"volumeAvailable":2,"maxProfit":20600},{"typeId":11132,"itemName":"Minmatar Shuttle","buyPrice":14800,"sellPrice":25000,"profitPerUnit":10200,"buyStation":"Malukker I - Republic University","sellStation":"Kamela V - 24th Imperial Crusade Logistic Support","roi":68.92,"volumeAvailable":8,"maxProfit":81600},{"typeId":11132,"itemName":"Minmatar Shuttle","buyPrice":15000,"sellPrice":25000,"profitPerUnit":10000,"buyStation":"Dammalin VII - Moon 5 - Quafe Company Factory","sellStation":"Kamela V - 24th Imperial Crusade Logistic Support","roi":66.67,"volumeAvailable":26,"maxProfit":260000},{"typeId":11134,"itemName":"Amarr Shuttle","buyPrice":15210,"sellPrice":25000,"profitPerUnit":9790,"buyStation":"Emolgranlan V - Moon 12 - Republic Justice Department Tribunal","sellStation":"Iesa VI - Moon 6 - Ministry of Assessment Information Center","roi":64.37,"volumeAvailable":2,"maxProfit":19580},{"typeId":672,"itemName":"Caldari Shuttle","buyPrice":15400,"sellPrice":25000,"profitPerUnit":9600,"buyStation":"Malukker I - Republic University","sellStation":"Kamela V - 24th Imperial Crusade Logistic Support","roi":62.34,"volumeAvailable":4,"maxProfit":38400},{"typeId":672,"itemName":"Caldari Shuttle","buyPrice":15500,"sellPrice":25000,"profitPerUnit":9500,"buyStation":"Ameinaka IX - Moon 21 - Six Kin Development Warehouse","sellStation":"Kamela V - 24th Imperial Crusade Logistic Support","roi":61.29,"volumeAvailable":5,"maxProfit":47500},{"typeId":11134,"itemName":"Amarr Shuttle","buyPrice":16380,"sellPrice":25000,"profitPerUnit":8620,"buyStation":"Rens VI - Moon 8 - Brutor Tribe Treasury","sellStation":"Iesa VI - Moon 6 - Ministry of Assessment Information Center","roi":52.63,"volumeAvailable":41,"maxProfit":353420},{"typeId":17366,"itemName":"Station Container","buyPrice":500000,"sellPrice":750000,"profitPerUnit":250000,"buyStation":"Hurjafren VII - Moon 25 - Thukker Mix Factory","sellStation":"Huola X - Moon 2 - Ishukone Corporation Factory","roi":50,"volumeAvailable":5,"maxProfit":1250000},{"typeId":11132,"itemName":"Minmatar Shuttle","buyPrice":17000,"sellPrice":25000,"profitPerUnit":8000,"buyStation":"Endrulf VIII - Moon 1 - CreoDron Warehouse","sellStation":"Kamela V - 24th Imperial Crusade Logistic Support","roi":47.06,"volumeAvailable":98,"maxProfit":784000},{"typeId":11132,"itemName":"Minmatar Shuttle","buyPrice":17000,"sellPrice":25000,"profitPerUnit":8000,"buyStation":"Alakgur VII - Moon 3 - Republic Security Services Assembly Plant","sellStation":"Kamela V - 24th Imperial Crusade Logistic Support","roi":47.06,"volumeAvailable":91,"maxProfit":728000},{"typeId":11132,"itemName":"Minmatar Shuttle","buyPrice":17000,"sellPrice":25000,"profitPerUnit":8000,"buyStation":"Pator VII (Kulheim) - Moon 1 - Republic Fleet Testing Facilities","sellStation":"Kamela V - 24th Imperial Crusade Logistic Support","roi":47.06,"volumeAvailable":17,"maxProfit":136000},{"typeId":11129,"itemName":"Gallente Shuttle","buyPrice":17000,"sellPrice":25000,"profitPerUnit":8000,"buyStation":"Kronsur VI - Moon 2 - Republic Justice Department Tribunal","sellStation":"Kamela V - 24th Imperial Crusade Logistic Support","roi":47.06,"volumeAvailable":4,"maxProfit":32000},{"typeId":672,"itemName":"Caldari Shuttle","buyPrice":17000,"sellPrice":25000,"profitPerUnit":8000,"buyStation":"Dammalin I - Quafe Company Factory","sellStation":"Kamela V - 24th Imperial Crusade Logistic Support","roi":47.06,"volumeAvailable":73,"maxProfit":584000},{"typeId":672,"itemName":"Caldari Shuttle","buyPrice":17000,"sellPrice":25000,"profitPerUnit":8000,"buyStation":"Abudban VIII - Moon 19 - TransStellar Shipping Storage","sellStation":"Kamela V - 24th Imperial Crusade Logistic Support","roi":47.06,"volumeAvailable":1,"maxProfit":8000},{"typeId":11129,"itemName":"Gallente Shuttle","buyPrice":18000,"sellPrice":25000,"profitPerUnit":7000,"buyStation":"Tongofur VIII - Kaalakiota Corporation Warehouse","sellStation":"Kamela V - 24th Imperial Crusade Logistic Support","roi":38.89,"volumeAvailable":200,"maxProfit":1400000},{"typeId":11129,"itemName":"Gallente Shuttle","buyPrice":18500,"sellPrice":25000,"profitPerUnit":6500,"buyStation":"Malukker I - Republic University","sellStation":"Kamela V - 24th Imperial Crusade Logistic Support","roi":35.14,"volumeAvailable":16,"maxProfit":104000},{"typeId":3647,"itemName":"Holoreels","buyPrice":225,"sellPrice":302.5,"profitPerUnit":77.5,"buyStation":"Gerek V - Moon 3 - Republic University","sellStation":"Komaa V - Royal Amarr Institute School","roi":34.44,"volumeAvailable":1595,"maxProfit":123612.5},{"typeId":3647,"itemName":"Holoreels","buyPrice":225,"sellPrice":302.5,"profitPerUnit":77.5,"buyStation":"Gultratren V - Moon 4 - Republic University","sellStation":"Komaa V - Royal Amarr Institute School","roi":34.44,"volumeAvailable":1595,"maxProfit":123612.5},{"typeId":3647,"itemName":"Holoreels","buyPrice":225,"sellPrice":302.5,"profitPerUnit":77.5,"buyStation":"Todeko VII - Republic University","sellStation":"Komaa V - Royal Amarr Institute School","roi":34.44,"volumeAvailable":1595,"maxProfit":123612.5},{"typeId":3647,"itemName":"Holoreels","buyPrice":225,"sellPrice":302.5,"profitPerUnit":77.5,"buyStation":"Usteli V - Republic University","sellStation":"Komaa V - Royal Amarr Institute School","roi":34.44,"volumeAvailable":1595,"maxProfit":123612.5},{"typeId":3647,"itemName":"Holoreels","buyPrice":225.01,"sellPrice":302.5,"profitPerUnit":77.49,"buyStation":"Offugen VII - Moon 15 - The Leisure Group Development Studio","sellStation":"Komaa V - Royal Amarr Institute School","roi":34.44,"volumeAvailable":3122,"maxProfit":241923.78},{"typeId":3647,"itemName":"Holoreels","buyPrice":225,"sellPrice":302.5,"profitPerUnit":77.5,"buyStation":"Edmalbrurdus I - Republic University","sellStation":"Komaa V - Royal Amarr Institute School","roi":34.44,"volumeAvailable":1595,"maxProfit":123612.5},{"typeId":3647,"itemName":"Holoreels","buyPrice":225,"sellPrice":302.5,"profitPerUnit":77.5,"buyStation":"Rokofur IX - The Leisure Group Development Studio","sellStation":"Komaa V - Royal Amarr Institute School","roi":34.44,"volumeAvailable":3122,"maxProfit":241955},{"typeId":3647,"itemName":"Holoreels","buyPrice":225.01,"sellPrice":302.5,"profitPerUnit":77.49,"buyStation":"Eddar VIII - Moon 8 - The Leisure Group Development Studio","sellStation":"Komaa V - Royal Amarr Institute School","roi":34.44,"volumeAvailable":3122,"maxProfit":241923.78},{"typeId":3647,"itemName":"Holoreels","buyPrice":225.07,"sellPrice":302.5,"profitPerUnit":77.43,"buyStation":"Gerek VI - Moon 16 - The Leisure Group Development Studio","sellStation":"Komaa V - Royal Amarr Institute School","roi":34.4,"volumeAvailable":3122,"maxProfit":241736.46},{"typeId":3647,"itemName":"Holoreels","buyPrice":225.15,"sellPrice":302.5,"profitPerUnit":77.35,"buyStation":"Hulm VIII - Moon 2 - Republic University","sellStation":"Komaa V - Royal Amarr Institute School","roi":34.35,"volumeAvailable":1595,"maxProfit":123373.25},{"typeId":3647,"itemName":"Holoreels","buyPrice":225.15,"sellPrice":302.5,"profitPerUnit":77.35,"buyStation":"Malukker I - Republic University","sellStation":"Komaa V - Royal Amarr Institute School","roi":34.35,"volumeAvailable":1595,"maxProfit":123373.25},{"typeId":9852,"itemName":"Tobacco","buyPrice":44.4,"sellPrice":59.34,"profitPerUnit":14.94,"buyStation":"Olfeim V - Moon 3 - CBD Corporation Storage","sellStation":"Komaa IV - Freedom Extension Storage","roi":33.65,"volumeAvailable":12232,"maxProfit":182746.08},{"typeId":9852,"itemName":"Tobacco","buyPrice":44.4,"sellPrice":59.34,"profitPerUnit":14.94,"buyStation":"Lulm V - Moon 10 - Poteque Pharmaceuticals Biotech Production","sellStation":"Komaa IV - Freedom Extension Storage","roi":33.65,"volumeAvailable":12232,"maxProfit":182746.08},{"typeId":9852,"itemName":"Tobacco","buyPrice":44.4,"sellPrice":59.34,"profitPerUnit":14.94,"buyStation":"Gulmorogod VII - Moon 16 - Poteque Pharmaceuticals Biotech Research Center","sellStation":"Komaa IV - Freedom Extension Storage","roi":33.65,"volumeAvailable":12232,"maxProfit":182746.08},{"typeId":9852,"itemName":"Tobacco","buyPrice":44.4,"sellPrice":59.34,"profitPerUnit":14.94,"buyStation":"Amamake VI - Moon 8 - Pator Tech School","sellStation":"Komaa IV - Freedom Extension Storage","roi":33.65,"volumeAvailable":5265,"maxProfit":78659.1},{"typeId":9852,"itemName":"Tobacco","buyPrice":44.4,"sellPrice":59.34,"profitPerUnit":14.94,"buyStation":"Illinfrik VII - Moon 12 - Pator Tech School","sellStation":"Komaa IV - Freedom Extension Storage","roi":33.65,"volumeAvailable":5265,"maxProfit":78659.1},{"typeId":9852,"itemName":"Tobacco","buyPrice":44.4,"sellPrice":59.34,"profitPerUnit":14.94,"buyStation":"Gulmorogod VI - Moon 4 - CBD Corporation Storage","sellStation":"Komaa IV - Freedom Extension Storage","roi":33.65,"volumeAvailable":12232,"maxProfit":182746.08},{"typeId":9852,"itemName":"Tobacco","buyPrice":44.4,"sellPrice":59.34,"profitPerUnit":14.94,"buyStation":"Gulmorogod VIII - Moon 25 - CBD Corporation Storage","sellStation":"Komaa IV - Freedom Extension Storage","roi":33.65,"volumeAvailable":12232,"maxProfit":182746.08},{"typeId":15626,"itemName":"Republic Fleet Midshipman Insignia II","buyPrice":6000,"sellPrice":8000,"profitPerUnit":2000,"buyStation":"Frarn VI - Moon 18 - Brutor Tribe Bureau","sellStation":"Oyonata IV - Moon 1 - Amarr Navy Assembly Plant","roi":33.33,"volumeAvailable":3,"maxProfit":6000},{"typeId":3647,"itemName":"Holoreels","buyPrice":229.17,"sellPrice":302.5,"profitPerUnit":73.33,"buyStation":"Ebasgerdur III - Impetus Development Studio","sellStation":"Komaa V - Royal Amarr Institute School","roi":32,"volumeAvailable":3122,"maxProfit":228936.26},{"typeId":3647,"itemName":"Holoreels","buyPrice":229.21,"sellPrice":302.5,"profitPerUnit":73.29,"buyStation":"Gerek V - Moon 14 - Impetus Development Studio","sellStation":"Komaa V - Royal Amarr Institute School","roi":31.98,"volumeAvailable":3122,"maxProfit":228811.38},{"typeId":9852,"itemName":"Tobacco","buyPrice":45.06,"sellPrice":59.34,"profitPerUnit":14.28,"buyStation":"Gerek VI - Moon 16 - The Leisure Group Development Studio","sellStation":"Komaa IV - Freedom Extension Storage","roi":31.69,"volumeAvailable":12232,"maxProfit":174672.96},{"typeId":9852,"itemName":"Tobacco","buyPrice":45.06,"sellPrice":59.34,"profitPerUnit":14.28,"buyStation":"Offugen VII - Moon 15 - The Leisure Group Development Studio","sellStation":"Komaa IV - Freedom Extension Storage","roi":31.69,"volumeAvailable":12232,"maxProfit":174672.96},{"typeId":11132,"itemName":"Minmatar Shuttle","buyPrice":19000,"sellPrice":25000,"profitPerUnit":6000,"buyStation":"Tongofur VIII - Kaalakiota Corporation Warehouse","sellStation":"Kamela V - 24th Imperial Crusade Logistic Support","roi":31.58,"volumeAvailable":162,"maxProfit":972000},{"typeId":3647,"itemName":"Holoreels","buyPrice":230.7,"sellPrice":302.5,"profitPerUnit":71.8,"buyStation":"Rens VI - Moon 8 - Brutor Tribe Treasury","sellStation":"Komaa V - Royal Amarr Institute School","roi":31.12,"volumeAvailable":40,"maxProfit":2872},{"typeId":11129,"itemName":"Gallente Shuttle","buyPrice":19200,"sellPrice":25000,"profitPerUnit":5800,"buyStation":"Gerek V - Moon 3 - Republic University","sellStation":"Kamela V - 24th Imperial Crusade Logistic Support","roi":30.21,"volumeAvailable":3,"maxProfit":17400},{"typeId":9852,"itemName":"Tobacco","buyPrice":46.11,"sellPrice":59.34,"profitPerUnit":13.23,"buyStation":"Rokofur IX - The Leisure Group Development Studio","sellStation":"Komaa IV - Freedom Extension Storage","roi":28.69,"volumeAvailable":12232,"maxProfit":161829.36},{"typeId":11134,"itemName":"Amarr Shuttle","buyPrice":19500,"sellPrice":25000,"profitPerUnit":5500,"buyStation":"Tongofur VIII - Kaalakiota Corporation Warehouse","sellStation":"Iesa VI - Moon 6 - Ministry of Assessment Information Center","roi":28.21,"volumeAvailable":95,"maxProfit":522500},{"typeId":3647,"itemName":"Holoreels","buyPrice":236.8,"sellPrice":302.5,"profitPerUnit":65.7,"buyStation":"Hadaugago II - Moon 1 - Republic Military School","sellStation":"Komaa V - Royal Amarr Institute School","roi":27.74,"volumeAvailable":1,"maxProfit":65.7},{"typeId":3687,"itemName":"Electronic Parts","buyPrice":705.01,"sellPrice":894.37,"profitPerUnit":189.36,"buyStation":"Amamake VI - Moon 3 - Expert Distribution Warehouse","sellStation":"Kuomi VIII - Moon 22 - Ishukone Corporation Factory","roi":26.86,"volumeAvailable":10815,"maxProfit":2047928.4},{"typeId":3687,"itemName":"Electronic Parts","buyPrice":705,"sellPrice":894.37,"profitPerUnit":189.37,"buyStation":"Siseide VIII - Expert Distribution Warehouse","sellStation":"Kuomi VIII - Moon 22 - Ishukone Corporation Factory","roi":26.86,"volumeAvailable":10815,"maxProfit":2048036.55},{"typeId":3687,"itemName":"Electronic Parts","buyPrice":705,"sellPrice":894.37,"profitPerUnit":189.37,"buyStation":"Amamake VI - Moon 1 - Expert Distribution Warehouse","sellStation":"Kuomi VIII - Moon 22 - Ishukone Corporation Factory","roi":26.86,"volumeAvailable":10815,"maxProfit":2048036.55},{"typeId":3687,"itemName":"Electronic Parts","buyPrice":705,"sellPrice":894.37,"profitPerUnit":189.37,"buyStation":"Gultratren V - Moon 4 - Republic University","sellStation":"Kuomi VIII - Moon 22 - Ishukone Corporation Factory","roi":26.86,"volumeAvailable":3976,"maxProfit":752935.12},{"typeId":3687,"itemName":"Electronic Parts","buyPrice":705.09,"sellPrice":894.37,"profitPerUnit":189.28,"buyStation":"Usteli V - Republic University","sellStation":"Kuomi VIII - Moon 22 - Ishukone Corporation Factory","roi":26.84,"volumeAvailable":3976,"maxProfit":752577.28},{"typeId":3687,"itemName":"Electronic Parts","buyPrice":705.09,"sellPrice":894.37,"profitPerUnit":189.28,"buyStation":"Edmalbrurdus I - Republic University","sellStation":"Kuomi VIII - Moon 22 - Ishukone Corporation Factory","roi":26.84,"volumeAvailable":3976,"maxProfit":752577.28},{"typeId":3687,"itemName":"Electronic Parts","buyPrice":705.09,"sellPrice":894.37,"profitPerUnit":189.28,"buyStation":"Todeko VII - Republic University","sellStation":"Kuomi VIII - Moon 22 - Ishukone Corporation Factory","roi":26.84,"volumeAvailable":3976,"maxProfit":752577.28},{"typeId":3687,"itemName":"Electronic Parts","buyPrice":705.1,"sellPrice":894.37,"profitPerUnit":189.27,"buyStation":"Oremmulf V - Moon 20 - Thukker Mix Warehouse","sellStation":"Kuomi VIII - Moon 22 - Ishukone Corporation Factory","roi":26.84,"volumeAvailable":6722,"maxProfit":1272272.94},{"typeId":3687,"itemName":"Electronic Parts","buyPrice":705.23,"sellPrice":894.37,"profitPerUnit":189.14,"buyStation":"Lantorn VI - Moon 4 - Expert Distribution Warehouse","sellStation":"Kuomi VIII - Moon 22 - Ishukone Corporation Factory","roi":26.82,"volumeAvailable":10815,"maxProfit":2045549.1},{"typeId":3687,"itemName":"Electronic Parts","buyPrice":705.41,"sellPrice":894.37,"profitPerUnit":188.96,"buyStation":"Wiskeber VII - Moon 9 - Aliastra Warehouse","sellStation":"Kuomi VIII - Moon 22 - Ishukone Corporation Factory","roi":26.79,"volumeAvailable":17836,"maxProfit":3370290.56},{"typeId":3687,"itemName":"Electronic Parts","buyPrice":705.41,"sellPrice":894.37,"profitPerUnit":188.96,"buyStation":"Hurjafren VII - Moon 25 - Thukker Mix Factory","sellStation":"Kuomi VIII - Moon 22 - Ishukone Corporation Factory","roi":26.79,"volumeAvailable":6722,"maxProfit":1270189.12},{"typeId":3687,"itemName":"Electronic Parts","buyPrice":705.43,"sellPrice":894.37,"profitPerUnit":188.94,"buyStation":"Siseide VII - Expert Distribution Retail Center","sellStation":"Kuomi VIII - Moon 22 - Ishukone Corporation Factory","roi":26.78,"volumeAvailable":10815,"maxProfit":2043386.1},{"typeId":3687,"itemName":"Electronic Parts","buyPrice":705.82,"sellPrice":894.37,"profitPerUnit":188.55,"buyStation":"Amamake II - Expert Distribution Warehouse","sellStation":"Kuomi VIII - Moon 22 - Ishukone Corporation Factory","roi":26.71,"volumeAvailable":10815,"maxProfit":2039168.25},{"typeId":9826,"itemName":"Carbon","buyPrice":305,"sellPrice":385.88,"profitPerUnit":80.88,"buyStation":"Rens VI - Moon 8 - Brutor Tribe Treasury","sellStation":"Komaa VII - Moon 1 - Wiyrkomi Corporation Factory","roi":26.52,"volumeAvailable":4,"maxProfit":323.52},{"typeId":3687,"itemName":"Electronic Parts","buyPrice":707.25,"sellPrice":894.37,"profitPerUnit":187.12,"buyStation":"Aralgrund V - Moon 2 - Aliastra Warehouse","sellStation":"Kuomi VIII - Moon 22 - Ishukone Corporation Factory","roi":26.46,"volumeAvailable":17836,"maxProfit":3337472.32},{"typeId":9826,"itemName":"Carbon","buyPrice":305.4,"sellPrice":385.88,"profitPerUnit":80.48,"buyStation":"Odatrik V - Moon 1 - TransStellar Shipping Storage","sellStation":"Komaa VII - Moon 1 - Wiyrkomi Corporation Factory","roi":26.35,"volumeAvailable":10,"maxProfit":804.8},{"typeId":3687,"itemName":"Electronic Parts","buyPrice":709.54,"sellPrice":894.37,"profitPerUnit":184.83,"buyStation":"Malukker I - Republic University","sellStation":"Kuomi VIII - Moon 22 - Ishukone Corporation Factory","roi":26.05,"volumeAvailable":3976,"maxProfit":734884.08},{"typeId":3647,"itemName":"Holoreels","buyPrice":240,"sellPrice":302.5,"profitPerUnit":62.5,"buyStation":"Lustrevik V - Republic Justice Department Law School","sellStation":"Komaa V - Royal Amarr Institute School","roi":26.04,"volumeAvailable":10,"maxProfit":625},{"typeId":9826,"itemName":"Carbon","buyPrice":306.2,"sellPrice":385.88,"profitPerUnit":79.68,"buyStation":"Lustrevik VII - Moon 9 - Brutor Tribe Academy","sellStation":"Komaa VII - Moon 1 - Wiyrkomi Corporation Factory","roi":26.02,"volumeAvailable":10,"maxProfit":796.8},{"typeId":11132,"itemName":"Minmatar Shuttle","buyPrice":19900,"sellPrice":25000,"profitPerUnit":5100,"buyStation":"Abudban VIII - Moon 6 - Six Kin Development Production Plant","sellStation":"Kamela V - 24th Imperial Crusade Logistic Support","roi":25.63,"volumeAvailable":34,"maxProfit":173400},{"typeId":34,"itemName":"Tritanium","buyPrice":2.95,"sellPrice":3.7,"profitPerUnit":0.75,"buyStation":"Usteli V - Republic University","sellStation":"Huola VI - 24th Imperial Crusade Logistic Support","roi":25.42,"volumeAvailable":56760,"maxProfit":42570},{"typeId":3687,"itemName":"Electronic Parts","buyPrice":714.34,"sellPrice":894.37,"profitPerUnit":180.03,"buyStation":"Gerek V - Moon 3 - Republic University","sellStation":"Kuomi VIII - Moon 22 - Ishukone Corporation Factory","roi":25.2,"volumeAvailable":3976,"maxProfit":715799.28},{"typeId":43,"itemName":"Antibiotics","buyPrice":300,"sellPrice":375.51,"profitPerUnit":75.51,"buyStation":"Amamake VI - Moon 1 - Expert Distribution Warehouse","sellStation":"Hatori X - Moon 10 - CBD Corporation Storage","roi":25.17,"volumeAvailable":4991,"maxProfit":376870.41},{"typeId":9852,"itemName":"Tobacco","buyPrice":47.42,"sellPrice":59.34,"profitPerUnit":11.92,"buyStation":"Eddar VIII - Moon 8 - The Leisure Group Development Studio","sellStation":"Komaa IV - Freedom Extension Storage","roi":25.14,"volumeAvailable":12232,"maxProfit":145805.44},{"typeId":3687,"itemName":"Electronic Parts","buyPrice":715.36,"sellPrice":894.37,"profitPerUnit":179.01,"buyStation":"Bogelek IV - Moon 2 - Aliastra Warehouse","sellStation":"Kuomi VIII - Moon 22 - Ishukone Corporation Factory","roi":25.02,"volumeAvailable":17836,"maxProfit":3192822.36},{"typeId":11134,"itemName":"Amarr Shuttle","buyPrice":20000,"sellPrice":25000,"profitPerUnit":5000,"buyStation":"Malukker I - Republic University","sellStation":"Iesa VI - Moon 6 - Ministry of Assessment Information Center","roi":25,"volumeAvailable":20,"maxProfit":100000},{"typeId":11134,"itemName":"Amarr Shuttle","buyPrice":20000,"sellPrice":25000,"profitPerUnit":5000,"buyStation":"Emolgranlan VI - Republic Fleet Assembly Plant","sellStation":"Iesa VI - Moon 6 - Ministry of Assessment Information Center","roi":25,"volumeAvailable":2,"maxProfit":10000},{"typeId":11134,"itemName":"Amarr Shuttle","buyPrice":20000,"sellPrice":25000,"profitPerUnit":5000,"buyStation":"Rens VI - Six Kin Development Warehouse","sellStation":"Iesa VI - Moon 6 - Ministry of Assessment Information Center","roi":25,"volumeAvailable":5,"maxProfit":25000},{"typeId":11132,"itemName":"Minmatar Shuttle","buyPrice":20000,"sellPrice":25000,"profitPerUnit":5000,"buyStation":"Oremmulf IX - Moon 6 - CreoDron Factory","sellStation":"Kamela V - 24th Imperial Crusade Logistic Support","roi":25,"volumeAvailable":162,"maxProfit":810000},{"typeId":11132,"itemName":"Minmatar Shuttle","buyPrice":20000,"sellPrice":25000,"profitPerUnit":5000,"buyStation":"Osoggur VI - Urban Management Information Center","sellStation":"Kamela V - 24th Imperial Crusade Logistic Support","roi":25,"volumeAvailable":162,"maxProfit":810000},{"typeId":11132,"itemName":"Minmatar Shuttle","buyPrice":20000,"sellPrice":25000,"profitPerUnit":5000,"buyStation":"Oremmulf IX - Moon 2 - Imperial Armaments Warehouse","sellStation":"Kamela V - 24th Imperial Crusade Logistic Support","roi":25,"volumeAvailable":9,"maxProfit":45000},{"typeId":11129,"itemName":"Gallente Shuttle","buyPrice":20000,"sellPrice":25000,"profitPerUnit":5000,"buyStation":"Dammalin VI - CBD Corporation Storage","sellStation":"Kamela V - 24th Imperial Crusade Logistic Support","roi":25,"volumeAvailable":62,"maxProfit":310000},{"typeId":672,"itemName":"Caldari Shuttle","buyPrice":20000,"sellPrice":25000,"profitPerUnit":5000,"buyStation":"Dammalin VI - CBD Corporation Storage","sellStation":"Kamela V - 24th Imperial Crusade Logistic Support","roi":25,"volumeAvailable":73,"maxProfit":365000},{"typeId":672,"itemName":"Caldari Shuttle","buyPrice":20000,"sellPrice":25000,"profitPerUnit":5000,"buyStation":"Emolgranlan V - Moon 12 - Republic Justice Department Tribunal","sellStation":"Kamela V - 24th Imperial Crusade Logistic Support","roi":25,"volumeAvailable":2,"maxProfit":10000},{"typeId":11132,"itemName":"Minmatar Shuttle","buyPrice":20100,"sellPrice":25000,"profitPerUnit":4900,"buyStation":"Eystur III - Moon 1 - Republic Fleet Assembly Plant","sellStation":"Kamela V - 24th Imperial Crusade Logistic Support","roi":24.38,"volumeAvailable":162,"maxProfit":793800},{"typeId":34,"itemName":"Tritanium","buyPrice":3,"sellPrice":3.7,"profitPerUnit":0.7,"buyStation":"Eystur IV - Quafe Company Factory","sellStation":"Huola VI - 24th Imperial Crusade Logistic Support","roi":23.33,"volumeAvailable":306229,"maxProfit":214360.3},{"typeId":43,"itemName":"Antibiotics","buyPrice":305.5,"sellPrice":375.51,"profitPerUnit":70.01,"buyStation":"Amamake VI - Moon 3 - Expert Distribution Warehouse","sellStation":"Hatori X - Moon 10 - CBD Corporation Storage","roi":22.92,"volumeAvailable":6989,"maxProfit":489299.89},{"typeId":43,"itemName":"Antibiotics","buyPrice":305.5,"sellPrice":375.51,"profitPerUnit":70.01,"buyStation":"Lantorn VI - Moon 4 - Expert Distribution Warehouse","sellStation":"Hatori X - Moon 10 - CBD Corporation Storage","roi":22.92,"volumeAvailable":6989,"maxProfit":489299.89},{"typeId":43,"itemName":"Antibiotics","buyPrice":305.5,"sellPrice":375.51,"profitPerUnit":70.01,"buyStation":"Sotrenzur XI - Moon 1 - Chemal Tech Factory","sellStation":"Hatori X - Moon 10 - CBD Corporation Storage","roi":22.92,"volumeAvailable":15184,"maxProfit":1063031.84},{"typeId":43,"itemName":"Antibiotics","buyPrice":305.5,"sellPrice":375.51,"profitPerUnit":70.01,"buyStation":"Sotrenzur V - Chemal Tech Factory","sellStation":"Hatori X - Moon 10 - CBD Corporation Storage","roi":22.92,"volumeAvailable":15184,"maxProfit":1063031.84},{"typeId":43,"itemName":"Antibiotics","buyPrice":305.5,"sellPrice":375.51,"profitPerUnit":70.01,"buyStation":"Otraren IV - Moon 5 - Chemal Tech Warehouse","sellStation":"Hatori X - Moon 10 - CBD Corporation Storage","roi":22.92,"volumeAvailable":15184,"maxProfit":1063031.84},{"typeId":9850,"itemName":"Spirits","buyPrice":427.7,"sellPrice":525.71,"profitPerUnit":98.01,"buyStation":"Gultratren III - Moon 2 - Trust Partners Trading Post","sellStation":"Tuomuta III - Ducia Foundry Mining Outpost","roi":22.92,"volumeAvailable":4286,"maxProfit":420070.86},{"typeId":9850,"itemName":"Spirits","buyPrice":427.7,"sellPrice":525.71,"profitPerUnit":98.01,"buyStation":"Atgur VIII - Moon 1 - Trust Partners Warehouse","sellStation":"Tuomuta III - Ducia Foundry Mining Outpost","roi":22.92,"volumeAvailable":4286,"maxProfit":420070.86},{"typeId":9850,"itemName":"Spirits","buyPrice":427.7,"sellPrice":525.71,"profitPerUnit":98.01,"buyStation":"Sotrenzur IX - Moon 1 - Trust Partners Warehouse","sellStation":"Tuomuta III - Ducia Foundry Mining Outpost","roi":22.92,"volumeAvailable":4286,"maxProfit":420070.86},{"typeId":9850,"itemName":"Spirits","buyPrice":427.7,"sellPrice":525.71,"profitPerUnit":98.01,"buyStation":"Pator V (Vakir) - Republic Fleet Logistic Support","sellStation":"Tuomuta III - Ducia Foundry Mining Outpost","roi":22.92,"volumeAvailable":59,"maxProfit":5782.59},{"typeId":9850,"itemName":"Spirits","buyPrice":427.7,"sellPrice":525.71,"profitPerUnit":98.01,"buyStation":"Isendeldik IX - Moon 6 - Republic Fleet Logistic Support","sellStation":"Tuomuta III - Ducia Foundry Mining Outpost","roi":22.92,"volumeAvailable":59,"maxProfit":5782.59},{"typeId":9850,"itemName":"Spirits","buyPrice":427.7,"sellPrice":525.71,"profitPerUnit":98.01,"buyStation":"Emolgranlan VI - Republic Fleet Assembly Plant","sellStation":"Tuomuta III - Ducia Foundry Mining Outpost","roi":22.92,"volumeAvailable":59,"maxProfit":5782.59},{"typeId":9850,"itemName":"Spirits","buyPrice":427.7,"sellPrice":525.71,"profitPerUnit":98.01,"buyStation":"Eystur III - Moon 1 - Republic Fleet Assembly Plant","sellStation":"Tuomuta III - Ducia Foundry Mining Outpost","roi":22.92,"volumeAvailable":59,"maxProfit":5782.59},{"typeId":9850,"itemName":"Spirits","buyPrice":427.7,"sellPrice":525.71,"profitPerUnit":98.01,"buyStation":"Lustrevik VII - Moon 7 - Republic Fleet Logistic Support","sellStation":"Tuomuta III - Ducia Foundry Mining Outpost","roi":22.92,"volumeAvailable":59,"maxProfit":5782.59},{"typeId":9850,"itemName":"Spirits","buyPrice":427.7,"sellPrice":525.71,"profitPerUnit":98.01,"buyStation":"Amamake II - Moon 1 - Republic Fleet Logistic Support","sellStation":"Tuomuta III - Ducia Foundry Mining Outpost","roi":22.92,"volumeAvailable":59,"maxProfit":5782.59},{"typeId":9850,"itemName":"Spirits","buyPrice":427.7,"sellPrice":525.71,"profitPerUnit":98.01,"buyStation":"Amamake IV - Republic Fleet Assembly Plant","sellStation":"Tuomuta III - Ducia Foundry Mining Outpost","roi":22.92,"volumeAvailable":59,"maxProfit":5782.59},{"typeId":9850,"itemName":"Spirits","buyPrice":427.7,"sellPrice":525.71,"profitPerUnit":98.01,"buyStation":"Amamake VI - Moon 5 - Republic Fleet Logistic Support","sellStation":"Tuomuta III - Ducia Foundry Mining Outpost","roi":22.92,"volumeAvailable":59,"maxProfit":5782.59},{"typeId":9850,"itemName":"Spirits","buyPrice":427.7,"sellPrice":525.71,"profitPerUnit":98.01,"buyStation":"Auga VIII - Moon 2 - Republic Fleet Assembly Plant","sellStation":"Tuomuta III - Ducia Foundry Mining Outpost","roi":22.92,"volumeAvailable":59,"maxProfit":5782.59},{"typeId":9850,"itemName":"Spirits","buyPrice":427.7,"sellPrice":525.71,"profitPerUnit":98.01,"buyStation":"Dal III - Moon 1 - Republic Fleet Assembly Plant","sellStation":"Tuomuta III - Ducia Foundry Mining Outpost","roi":22.92,"volumeAvailable":59,"maxProfit":5782.59},{"typeId":9850,"itemName":"Spirits","buyPrice":427.7,"sellPrice":525.71,"profitPerUnit":98.01,"buyStation":"Amamake VI - Moon 10 - Republic Fleet Logistic Support","sellStation":"Tuomuta III - Ducia Foundry Mining Outpost","roi":22.92,"volumeAvailable":59,"maxProfit":5782.59},{"typeId":9850,"itemName":"Spirits","buyPrice":427.7,"sellPrice":525.71,"profitPerUnit":98.01,"buyStation":"Pator VII (Kulheim) - Moon 1 - Republic Fleet Testing Facilities","sellStation":"Tuomuta III - Ducia Foundry Mining Outpost","roi":22.92,"volumeAvailable":59,"maxProfit":5782.59},{"typeId":9850,"itemName":"Spirits","buyPrice":427.7,"sellPrice":525.71,"profitPerUnit":98.01,"buyStation":"Katugumur V - Moon 12 - Trust Partners Warehouse","sellStation":"Tuomuta III - Ducia Foundry Mining Outpost","roi":22.92,"volumeAvailable":4286,"maxProfit":420070.86},{"typeId":43,"itemName":"Antibiotics","buyPrice":305.63,"sellPrice":375.51,"profitPerUnit":69.88,"buyStation":"Lulm V - Moon 10 - Poteque Pharmaceuticals Biotech Production","sellStation":"Hatori X - Moon 10 - CBD Corporation Storage","roi":22.86,"volumeAvailable":26094,"maxProfit":1823448.72},{"typeId":43,"itemName":"Antibiotics","buyPrice":305.63,"sellPrice":375.51,"profitPerUnit":69.88,"buyStation":"Amamake II - Expert Distribution Warehouse","sellStation":"Hatori X - Moon 10 - CBD Corporation Storage","roi":22.86,"volumeAvailable":6989,"maxProfit":488391.32},{"typeId":43,"itemName":"Antibiotics","buyPrice":305.82,"sellPrice":375.51,"profitPerUnit":69.69,"buyStation":"Gulmorogod VII - Moon 16 - Poteque Pharmaceuticals Biotech Research Center","sellStation":"Hatori X - Moon 10 - CBD Corporation Storage","roi":22.79,"volumeAvailable":26094,"maxProfit":1818490.86},{"typeId":43,"itemName":"Antibiotics","buyPrice":305.82,"sellPrice":375.51,"profitPerUnit":69.69,"buyStation":"Siseide VII - Expert Distribution Retail Center","sellStation":"Hatori X - Moon 10 - CBD Corporation Storage","roi":22.79,"volumeAvailable":6989,"maxProfit":487063.41},{"typeId":43,"itemName":"Antibiotics","buyPrice":305.82,"sellPrice":375.51,"profitPerUnit":69.69,"buyStation":"Siseide VIII - Expert Distribution Warehouse","sellStation":"Hatori X - Moon 10 - CBD Corporation Storage","roi":22.79,"volumeAvailable":6989,"maxProfit":487063.41},{"typeId":34,"itemName":"Tritanium","buyPrice":3.02,"sellPrice":3.7,"profitPerUnit":0.68,"buyStation":"Malukker I - Republic University","sellStation":"Huola VI - 24th Imperial Crusade Logistic Support","roi":22.52,"volumeAvailable":527,"maxProfit":358.36},{"typeId":43,"itemName":"Antibiotics","buyPrice":307.14,"sellPrice":375.51,"profitPerUnit":68.37,"buyStation":"Osoggur VI - Urban Management Information Center","sellStation":"Hatori X - Moon 10 - CBD Corporation Storage","roi":22.26,"volumeAvailable":963,"maxProfit":65840.31},{"typeId":43,"itemName":"Antibiotics","buyPrice":307.14,"sellPrice":375.51,"profitPerUnit":68.37,"buyStation":"Rens VII - Moon 20 - Sisters of EVE Bureau","sellStation":"Hatori X - Moon 10 - CBD Corporation Storage","roi":22.26,"volumeAvailable":21193,"maxProfit":1448965.41},{"typeId":43,"itemName":"Antibiotics","buyPrice":307.37,"sellPrice":375.51,"profitPerUnit":68.14,"buyStation":"Rens VII - Moon 21 - Sisters of EVE Bureau","sellStation":"Hatori X - Moon 10 - CBD Corporation Storage","roi":22.17,"volumeAvailable":21193,"maxProfit":1444091.02},{"typeId":43,"itemName":"Antibiotics","buyPrice":307.83,"sellPrice":375.51,"profitPerUnit":67.68,"buyStation":"Rens VII - Moon 19 - Sisters of EVE Bureau","sellStation":"Hatori X - Moon 10 - CBD Corporation Storage","roi":21.99,"volumeAvailable":21193,"maxProfit":1434342.24},{"typeId":11134,"itemName":"Amarr Shuttle","buyPrice":20500,"sellPrice":25000,"profitPerUnit":4500,"buyStation":"Ameinaka IX - Moon 21 - Six Kin Development Warehouse","sellStation":"Iesa VI - Moon 6 - Ministry of Assessment Information Center","roi":21.95,"volumeAvailable":8,"maxProfit":36000},{"typeId":9850,"itemName":"Spirits","buyPrice":432.16,"sellPrice":525.71,"profitPerUnit":93.55,"buyStation":"Aralgrund IV - Moon 1 - Freedom Extension Storage","sellStation":"Tuomuta III - Ducia Foundry Mining Outpost","roi":21.65,"volumeAvailable":7931,"maxProfit":741945.05},{"typeId":9850,"itemName":"Spirits","buyPrice":432.16,"sellPrice":525.71,"profitPerUnit":93.55,"buyStation":"Aralgrund I - Moon 1 - Freedom Extension Storage","sellStation":"Tuomuta III - Ducia Foundry Mining Outpost","roi":21.65,"volumeAvailable":7931,"maxProfit":741945.05},{"typeId":9850,"itemName":"Spirits","buyPrice":432.16,"sellPrice":525.71,"profitPerUnit":93.55,"buyStation":"Aralgrund IV - Freedom Extension Retail Center","sellStation":"Tuomuta III - Ducia Foundry Mining Outpost","roi":21.65,"volumeAvailable":7931,"maxProfit":741945.05},{"typeId":9850,"itemName":"Spirits","buyPrice":432.16,"sellPrice":525.71,"profitPerUnit":93.55,"buyStation":"Aralgrund VI - Freedom Extension Warehouse","sellStation":"Tuomuta III - Ducia Foundry Mining Outpost","roi":21.65,"volumeAvailable":7931,"maxProfit":741945.05},{"typeId":11134,"itemName":"Amarr Shuttle","buyPrice":20600,"sellPrice":25000,"profitPerUnit":4400,"buyStation":"Gerek V - Moon 3 - Republic University","sellStation":"Iesa VI - Moon 6 - Ministry of Assessment Information Center","roi":21.36,"volumeAvailable":6,"maxProfit":26400},{"typeId":3647,"itemName":"Holoreels","buyPrice":249.72,"sellPrice":302.5,"profitPerUnit":52.78,"buyStation":"Klir VI - Moon 4 - Nugoeihuvi Corporation Development Studio","sellStation":"Komaa V - Royal Amarr Institute School","roi":21.14,"volumeAvailable":3122,"maxProfit":164779.16},{"typeId":3647,"itemName":"Holoreels","buyPrice":249.71,"sellPrice":302.5,"profitPerUnit":52.79,"buyStation":"Gerbold III - Moon 2 - The Scope Development Studio","sellStation":"Komaa V - Royal Amarr Institute School","roi":21.14,"volumeAvailable":3122,"maxProfit":164810.38},{"typeId":3647,"itemName":"Holoreels","buyPrice":249.72,"sellPrice":302.5,"profitPerUnit":52.78,"buyStation":"Rokofur VIII - Moon 11 - The Scope Development Studio","sellStation":"Komaa V - Royal Amarr Institute School","roi":21.14,"volumeAvailable":3122,"maxProfit":164779.16},{"typeId":3647,"itemName":"Holoreels","buyPrice":249.72,"sellPrice":302.5,"profitPerUnit":52.78,"buyStation":"Trer VII - Moon 9 - Nugoeihuvi Corporation Development Studio","sellStation":"Komaa V - Royal Amarr Institute School","roi":21.14,"volumeAvailable":3122,"maxProfit":164779.16},{"typeId":3647,"itemName":"Holoreels","buyPrice":249.73,"sellPrice":302.5,"profitPerUnit":52.77,"buyStation":"Trer VIII - Moon 7 - Nugoeihuvi Corporation Development Studio","sellStation":"Komaa V - Royal Amarr Institute School","roi":21.13,"volumeAvailable":3122,"maxProfit":164747.94},{"typeId":3647,"itemName":"Holoreels","buyPrice":249.73,"sellPrice":302.5,"profitPerUnit":52.77,"buyStation":"Trer VIII - Moon 11 - Nugoeihuvi Corporation Development Studio","sellStation":"Komaa V - Royal Amarr Institute School","roi":21.13,"volumeAvailable":3122,"maxProfit":164747.94},{"typeId":9852,"itemName":"Tobacco","buyPrice":49.11,"sellPrice":59.34,"profitPerUnit":10.23,"buyStation":"Alakgur IX - Moon 9 - CBD Corporation Storage","sellStation":"Komaa IV - Freedom Extension Storage","roi":20.83,"volumeAvailable":12232,"maxProfit":125133.36},{"typeId":9852,"itemName":"Tobacco","buyPrice":49.11,"sellPrice":59.34,"profitPerUnit":10.23,"buyStation":"Dammalin VI - CBD Corporation Storage","sellStation":"Komaa IV - Freedom Extension Storage","roi":20.83,"volumeAvailable":12232,"maxProfit":125133.36},{"typeId":9852,"itemName":"Tobacco","buyPrice":49.11,"sellPrice":59.34,"profitPerUnit":10.23,"buyStation":"Alakgur VIII - Moon 2 - CBD Corporation Storage","sellStation":"Komaa IV - Freedom Extension Storage","roi":20.83,"volumeAvailable":12232,"maxProfit":125133.36},{"typeId":43,"itemName":"Antibiotics","buyPrice":310.84,"sellPrice":375.51,"profitPerUnit":64.67,"buyStation":"Abudban X - Moon 10 - Urban Management Bureau Offices","sellStation":"Hatori X - Moon 10 - CBD Corporation Storage","roi":20.8,"volumeAvailable":963,"maxProfit":62277.21},{"typeId":43,"itemName":"Antibiotics","buyPrice":310.84,"sellPrice":375.51,"profitPerUnit":64.67,"buyStation":"Trytedald V - Moon 12 - Urban Management Archives","sellStation":"Hatori X - Moon 10 - CBD Corporation Storage","roi":20.8,"volumeAvailable":963,"maxProfit":62277.21},{"typeId":43,"itemName":"Antibiotics","buyPrice":310.84,"sellPrice":375.51,"profitPerUnit":64.67,"buyStation":"Odatrik IX - Moon 2 - Urban Management Storage","sellStation":"Hatori X - Moon 10 - CBD Corporation Storage","roi":20.8,"volumeAvailable":963,"maxProfit":62277.21},{"typeId":34,"itemName":"Tritanium","buyPrice":3.1,"sellPrice":3.7,"profitPerUnit":0.6,"buyStation":"Ammold V - AIR Laboratories","sellStation":"Huola VI - 24th Imperial Crusade Logistic Support","roi":19.35,"volumeAvailable":306229,"maxProfit":183737.4},{"typeId":672,"itemName":"Caldari Shuttle","buyPrice":21000,"sellPrice":25000,"profitPerUnit":4000,"buyStation":"Gerek V - Moon 3 - Republic University","sellStation":"Kamela V - 24th Imperial Crusade Logistic Support","roi":19.05,"volumeAvailable":4,"maxProfit":16000},{"typeId":34,"itemName":"Tritanium","buyPrice":3.13,"sellPrice":3.7,"profitPerUnit":0.57,"buyStation":"Kronsur III - Moon 1 - Republic Justice Department Tribunal","sellStation":"Huola VI - 24th Imperial Crusade Logistic Support","roi":18.21,"volumeAvailable":306229,"maxProfit":174550.53},{"typeId":9826,"itemName":"Carbon","buyPrice":329.1,"sellPrice":385.88,"profitPerUnit":56.78,"buyStation":"Lustrevik V - Republic Justice Department Law School","sellStation":"Komaa VII - Moon 1 - Wiyrkomi Corporation Factory","roi":17.25,"volumeAvailable":10,"maxProfit":567.8},{"typeId":11129,"itemName":"Gallente Shuttle","buyPrice":21350,"sellPrice":25000,"profitPerUnit":3650,"buyStation":"Alakgur VII - Moon 3 - Republic Security Services Assembly Plant","sellStation":"Kamela V - 24th Imperial Crusade Logistic Support","roi":17.1,"volumeAvailable":10,"maxProfit":36500},{"typeId":9826,"itemName":"Carbon","buyPrice":330,"sellPrice":385.88,"profitPerUnit":55.88,"buyStation":"Malukker I - Republic University","sellStation":"Komaa VII - Moon 1 - Wiyrkomi Corporation Factory","roi":16.93,"volumeAvailable":2,"maxProfit":111.76},{"typeId":9826,"itemName":"Carbon","buyPrice":332.5,"sellPrice":385.88,"profitPerUnit":53.38,"buyStation":"Endrulf VIII - Moon 1 - CreoDron Warehouse","sellStation":"Komaa VII - Moon 1 - Wiyrkomi Corporation Factory","roi":16.05,"volumeAvailable":2219,"maxProfit":118450.22},{"typeId":9826,"itemName":"Carbon","buyPrice":332.5,"sellPrice":385.88,"profitPerUnit":53.38,"buyStation":"Gultratren V - Moon 22 - CreoDron Factory","sellStation":"Komaa VII - Moon 1 - Wiyrkomi Corporation Factory","roi":16.05,"volumeAvailable":2219,"maxProfit":118450.22},{"typeId":9826,"itemName":"Carbon","buyPrice":332.5,"sellPrice":385.88,"profitPerUnit":53.38,"buyStation":"Oremmulf IX - Moon 6 - CreoDron Factory","sellStation":"Komaa VII - Moon 1 - Wiyrkomi Corporation Factory","roi":16.05,"volumeAvailable":2219,"maxProfit":118450.22},{"typeId":9826,"itemName":"Carbon","buyPrice":332.51,"sellPrice":385.88,"profitPerUnit":53.37,"buyStation":"Onga VI - CreoDron Factory","sellStation":"Komaa VII - Moon 1 - Wiyrkomi Corporation Factory","roi":16.05,"volumeAvailable":2219,"maxProfit":118428.03},{"typeId":9826,"itemName":"Carbon","buyPrice":332.5,"sellPrice":385.88,"profitPerUnit":53.38,"buyStation":"Endrulf IV - Moon 1 - CreoDron Warehouse","sellStation":"Komaa VII - Moon 1 - Wiyrkomi Corporation Factory","roi":16.05,"volumeAvailable":2219,"maxProfit":118450.22},{"typeId":9826,"itemName":"Carbon","buyPrice":332.5,"sellPrice":385.88,"profitPerUnit":53.38,"buyStation":"Ingunn V - Moon 21 - CreoDron Factory","sellStation":"Komaa VII - Moon 1 - Wiyrkomi Corporation Factory","roi":16.05,"volumeAvailable":2219,"maxProfit":118450.22},{"typeId":9826,"itemName":"Carbon","buyPrice":332.5,"sellPrice":385.88,"profitPerUnit":53.38,"buyStation":"Osaumuni VII - Moon 16 - CreoDron Factory","sellStation":"Komaa VII - Moon 1 - Wiyrkomi Corporation Factory","roi":16.05,"volumeAvailable":2219,"maxProfit":118450.22},{"typeId":9826,"itemName":"Carbon","buyPrice":332.51,"sellPrice":385.88,"profitPerUnit":53.37,"buyStation":"Onga X - Moon 11 - CreoDron Warehouse","sellStation":"Komaa VII - Moon 1 - Wiyrkomi Corporation Factory","roi":16.05,"volumeAvailable":2219,"maxProfit":118428.03},{"typeId":9826,"itemName":"Carbon","buyPrice":332.5,"sellPrice":385.88,"profitPerUnit":53.38,"buyStation":"Oremmulf VII - Moon 11 - Genolution Biohazard Containment Facility","sellStation":"Komaa VII - Moon 1 - Wiyrkomi Corporation Factory","roi":16.05,"volumeAvailable":2201,"maxProfit":117489.38},{"typeId":9826,"itemName":"Carbon","buyPrice":332.51,"sellPrice":385.88,"profitPerUnit":53.37,"buyStation":"Vullat VII - Moon 11 - Genolution Biotech Research Center","sellStation":"Komaa VII - Moon 1 - Wiyrkomi Corporation Factory","roi":16.05,"volumeAvailable":2201,"maxProfit":117467.37},{"typeId":9826,"itemName":"Carbon","buyPrice":332.5,"sellPrice":385.88,"profitPerUnit":53.38,"buyStation":"Hurjafren VII - Moon 10 - Genolution Biotech Production","sellStation":"Komaa VII - Moon 1 - Wiyrkomi Corporation Factory","roi":16.05,"volumeAvailable":2201,"maxProfit":117489.38},{"typeId":9826,"itemName":"Carbon","buyPrice":332.51,"sellPrice":385.88,"profitPerUnit":53.37,"buyStation":"Vullat VIII - Moon 1 - Genolution Biohazard Containment Facility","sellStation":"Komaa VII - Moon 1 - Wiyrkomi Corporation Factory","roi":16.05,"volumeAvailable":2201,"maxProfit":117467.37},{"typeId":34,"itemName":"Tritanium","buyPrice":3.2,"sellPrice":3.7,"profitPerUnit":0.5,"buyStation":"Vullat VII - Moon 1 - Six Kin Development Foundry","sellStation":"Huola VI - 24th Imperial Crusade Logistic Support","roi":15.63,"volumeAvailable":121420,"maxProfit":60710},{"typeId":9850,"itemName":"Spirits","buyPrice":455.39,"sellPrice":525.71,"profitPerUnit":70.32,"buyStation":"Illinfrik VIII - Moon 1 - Trust Partners Trading Post","sellStation":"Tuomuta III - Ducia Foundry Mining Outpost","roi":15.44,"volumeAvailable":4286,"maxProfit":301391.52},{"typeId":9850,"itemName":"Spirits","buyPrice":455.86,"sellPrice":525.71,"profitPerUnit":69.85,"buyStation":"Offugen VII - Moon 8 - Freedom Extension Storage","sellStation":"Tuomuta III - Ducia Foundry Mining Outpost","roi":15.32,"volumeAvailable":7931,"maxProfit":553980.35},{"typeId":9850,"itemName":"Spirits","buyPrice":455.86,"sellPrice":525.71,"profitPerUnit":69.85,"buyStation":"Eddar VI - Freedom Extension Storage","sellStation":"Tuomuta III - Ducia Foundry Mining Outpost","roi":15.32,"volumeAvailable":7931,"maxProfit":553980.35},{"typeId":9850,"itemName":"Spirits","buyPrice":455.86,"sellPrice":525.71,"profitPerUnit":69.85,"buyStation":"Gyng IV - Trust Partners Trading Post","sellStation":"Tuomuta III - Ducia Foundry Mining Outpost","roi":15.32,"volumeAvailable":4286,"maxProfit":299377.1},{"typeId":15626,"itemName":"Republic Fleet Midshipman Insignia II","buyPrice":7000,"sellPrice":8000,"profitPerUnit":1000,"buyStation":"Lustrevik VII - Moon 7 - Six Kin Development Warehouse","sellStation":"Oyonata IV - Moon 1 - Amarr Navy Assembly Plant","roi":14.29,"volumeAvailable":10,"maxProfit":10000},{"typeId":34,"itemName":"Tritanium","buyPrice":3.25,"sellPrice":3.7,"profitPerUnit":0.45,"buyStation":"Lustrevik VIII - Moon 9 - Brutor Tribe Bureau","sellStation":"Huola VI - 24th Imperial Crusade Logistic Support","roi":13.85,"volumeAvailable":306229,"maxProfit":137803.05},{"typeId":34,"itemName":"Tritanium","buyPrice":3.25,"sellPrice":3.7,"profitPerUnit":0.45,"buyStation":"Lustrevik VII - Moon 7 - Six Kin Development Warehouse","sellStation":"Huola VI - 24th Imperial Crusade Logistic Support","roi":13.85,"volumeAvailable":306229,"maxProfit":137803.05},{"typeId":3687,"itemName":"Electronic Parts","buyPrice":794.5,"sellPrice":894.37,"profitPerUnit":99.87,"buyStation":"Osoggur VI - Urban Management Information Center","sellStation":"Kuomi VIII - Moon 22 - Ishukone Corporation Factory","roi":12.57,"volumeAvailable":10,"maxProfit":998.7},{"typeId":3687,"itemName":"Electronic Parts","buyPrice":794.8,"sellPrice":894.37,"profitPerUnit":99.57,"buyStation":"Eddar VIII - Moon 7 - Aliastra Retail Center","sellStation":"Kuomi VIII - Moon 22 - Ishukone Corporation Factory","roi":12.53,"volumeAvailable":17836,"maxProfit":1775930.52},{"typeId":3687,"itemName":"Electronic Parts","buyPrice":795,"sellPrice":894.37,"profitPerUnit":99.37,"buyStation":"Hulm VIII - Moon 2 - Republic University","sellStation":"Kuomi VIII - Moon 22 - Ishukone Corporation Factory","roi":12.5,"volumeAvailable":3976,"maxProfit":395095.12},{"typeId":3687,"itemName":"Electronic Parts","buyPrice":795.8,"sellPrice":894.37,"profitPerUnit":98.57,"buyStation":"Rens VI - Moon 8 - Brutor Tribe Treasury","sellStation":"Kuomi VIII - Moon 22 - Ishukone Corporation Factory","roi":12.39,"volumeAvailable":10,"maxProfit":985.7},{"typeId":11134,"itemName":"Amarr Shuttle","buyPrice":22360,"sellPrice":25000,"profitPerUnit":2640,"buyStation":"Dumkirinur V - Republic Military School","sellStation":"Iesa VI - Moon 6 - Ministry of Assessment Information Center","roi":11.81,"volumeAvailable":1,"maxProfit":2640},{"typeId":19400,"itemName":"1st Tier Overseer's Personal Effects","buyPrice":9900,"sellPrice":11000,"profitPerUnit":1100,"buyStation":"Rens VI - Moon 8 - Brutor Tribe Treasury","sellStation":"Komaa V - Royal Amarr Institute School","roi":11.11,"volumeAvailable":4,"maxProfit":4400},{"typeId":90072,"itemName":"Cybernetic Neural Lattice","buyPrice":90020,"sellPrice":100000,"profitPerUnit":9980,"buyStation":"Rens VI - Moon 8 - Brutor Tribe Treasury","sellStation":"Netsalakka VII - Moon 2 - Chemal Tech Factory","roi":11.09,"volumeAvailable":1466,"maxProfit":14630680},{"typeId":34,"itemName":"Tritanium","buyPrice":3.34,"sellPrice":3.7,"profitPerUnit":0.36,"buyStation":"Ebodold X - Moon 17 - Kaalakiota Corporation Research Center","sellStation":"Huola VI - 24th Imperial Crusade Logistic Support","roi":10.78,"volumeAvailable":306229,"maxProfit":110242.44},{"typeId":34,"itemName":"Tritanium","buyPrice":3.35,"sellPrice":3.7,"profitPerUnit":0.35,"buyStation":"Trytedald VII - Moon 16 - Joint Harvesting Mining Outpost","sellStation":"Huola VI - 24th Imperial Crusade Logistic Support","roi":10.45,"volumeAvailable":81291,"maxProfit":28451.85},{"typeId":9826,"itemName":"Carbon","buyPrice":354.2,"sellPrice":385.88,"profitPerUnit":31.68,"buyStation":"Hadaugago II - Moon 1 - Republic Military School","sellStation":"Komaa VII - Moon 1 - Wiyrkomi Corporation Factory","roi":8.94,"volumeAvailable":10,"maxProfit":316.8},{"typeId":9826,"itemName":"Carbon","buyPrice":363.4,"sellPrice":385.88,"profitPerUnit":22.48,"buyStation":"Emolgranlan VI - Republic Fleet Assembly Plant","sellStation":"Komaa VII - Moon 1 - Wiyrkomi Corporation Factory","roi":6.19,"volumeAvailable":10,"maxProfit":224.8},{"typeId":3717,"itemName":"Dairy Products","buyPrice":197.8,"sellPrice":209.28,"profitPerUnit":11.48,"buyStation":"Rens VI - Moon 8 - Brutor Tribe Treasury","sellStation":"Gammel X - Moon 3 - Ministry of Assessment Bureau Offices","roi":5.8,"volumeAvailable":30,"maxProfit":344.4},{"typeId":9826,"itemName":"Carbon","buyPrice":365.5,"sellPrice":385.88,"profitPerUnit":20.38,"buyStation":"Osoggur VI - Urban Management Information Center","sellStation":"Komaa VII - Moon 1 - Wiyrkomi Corporation Factory","roi":5.58,"volumeAvailable":1,"maxProfit":20.38},{"typeId":9850,"itemName":"Spirits","buyPrice":498.5,"sellPrice":525.71,"profitPerUnit":27.21,"buyStation":"Eystur III - Moon 1 - Republic Security Services Assembly Plant","sellStation":"Tuomuta III - Ducia Foundry Mining Outpost","roi":5.46,"volumeAvailable":20,"maxProfit":544.2},{"typeId":3687,"itemName":"Electronic Parts","buyPrice":850,"sellPrice":894.37,"profitPerUnit":44.37,"buyStation":"Lustrevik VII - Moon 9 - Brutor Tribe Academy","sellStation":"Kuomi VIII - Moon 22 - Ishukone Corporation Factory","roi":5.22,"volumeAvailable":189,"maxProfit":8385.93},{"typeId":90072,"itemName":"Cybernetic Neural Lattice","buyPrice":96000,"sellPrice":100000,"profitPerUnit":4000,"buyStation":"Lustrevik VIII - Moon 7 - Six Kin Development Warehouse","sellStation":"Netsalakka VII - Moon 2 - Chemal Tech Factory","roi":4.17,"volumeAvailable":535,"maxProfit":2140000},{"typeId":3687,"itemName":"Electronic Parts","buyPrice":860.2,"sellPrice":894.37,"profitPerUnit":34.17,"buyStation":"Trytedald V - Moon 12 - Urban Management Archives","sellStation":"Kuomi VIII - Moon 22 - Ishukone Corporation Factory","roi":3.97,"volumeAvailable":10,"maxProfit":341.7},{"typeId":11132,"itemName":"Minmatar Shuttle","buyPrice":24100,"sellPrice":25000,"profitPerUnit":900,"buyStation":"Onga X - Moon 11 - CreoDron Warehouse","sellStation":"Kamela V - 24th Imperial Crusade Logistic Support","roi":3.73,"volumeAvailable":102,"maxProfit":91800},{"typeId":92149,"itemName":"Drone Iteration Data","buyPrice":969700,"sellPrice":1000000,"profitPerUnit":30300,"buyStation":"Rens VI - Moon 8 - Brutor Tribe Treasury","sellStation":"Komaa VII - Moon 7 - Ministry of Internal Order Assembly Plant","roi":3.12,"volumeAvailable":23,"maxProfit":696900},{"typeId":92149,"itemName":"Drone Iteration Data","buyPrice":970000,"sellPrice":1000000,"profitPerUnit":30000,"buyStation":"Malukker I - Republic University","sellStation":"Komaa VII - Moon 7 - Ministry of Internal Order Assembly Plant","roi":3.09,"volumeAvailable":20,"maxProfit":600000},{"typeId":92149,"itemName":"Drone Iteration Data","buyPrice":970900,"sellPrice":1000000,"profitPerUnit":29100,"buyStation":"Hadaugago II - Moon 1 - Republic Military School","sellStation":"Komaa VII - Moon 7 - Ministry of Internal Order Assembly Plant","roi":3,"volumeAvailable":8,"maxProfit":232800},{"typeId":34,"itemName":"Tritanium","buyPrice":3.67,"sellPrice":3.7,"profitPerUnit":0.03,"buyStation":"Rens VI - Moon 8 - Brutor Tribe Treasury","sellStation":"Huola VI - 24th Imperial Crusade Logistic Support","roi":0.82,"volumeAvailable":306229,"maxProfit":9186.87},{"typeId":3717,"itemName":"Dairy Products","buyPrice":209,"sellPrice":209.28,"profitPerUnit":0.28,"buyStation":"Lustrevik VII - Moon 9 - Brutor Tribe Academy","sellStation":"Gammel X - Moon 3 - Ministry of Assessment Bureau Offices","roi":0.13,"volumeAvailable":9,"maxProfit":2.52},{"typeId":90072,"itemName":"Cybernetic Neural Lattice","buyPrice":99900,"sellPrice":100000,"profitPerUnit":100,"buyStation":"Hadaugago II - Moon 1 - Republic Military School","sellStation":"Netsalakka VII - Moon 2 - Chemal Tech Factory","roi":0.1,"volumeAvailable":119,"maxProfit":11900},{"typeId":15589,"itemName":"Federation Navy Midshipman Insignia III","buyPrice":14990,"sellPrice":15000,"profitPerUnit":10,"buyStation":"Rens VI - Moon 8 - Brutor Tribe Treasury","sellStation":"Oyonata IV - Moon 1 - Amarr Navy Assembly Plant","roi":0.07,"volumeAvailable":1,"maxProfit":10},{"typeId":15627,"itemName":"Republic Fleet Midshipman Insignia III","buyPrice":14990,"sellPrice":15000,"profitPerUnit":10,"buyStation":"Rens VI - Moon 8 - Brutor Tribe Treasury","sellStation":"Sahtogas IV - Moon 2 - Amarr Navy Logistic Support","roi":0.07,"volumeAvailable":3,"maxProfit":30},{"typeId":92149,"itemName":"Drone Iteration Data","buyPrice":999400,"sellPrice":1000000,"profitPerUnit":600,"buyStation":"Oremmulf IX - Moon 2 - Imperial Armaments Warehouse","sellStation":"Komaa VII - Moon 7 - Ministry of Internal Order Assembly Plant","roi":0.06,"volumeAvailable":4,"maxProfit":2400},{"typeId":15590,"itemName":"Federation Navy Sergeant Insignia I","buyPrice":19990,"sellPrice":20000,"profitPerUnit":10,"buyStation":"Rens VI - Moon 8 - Brutor Tribe Treasury","sellStation":"Oyonata IV - Moon 1 - Amarr Navy Assembly Plant","roi":0.05,"volumeAvailable":3,"maxProfit":30},{"typeId":15587,"itemName":"Federation Navy Midshipman Insignia I","buyPrice":4498,"sellPrice":4500,"profitPerUnit":2,"buyStation":"Rens VI - Moon 8 - Brutor Tribe Treasury","sellStation":"Oyonata IV - Moon 1 - Amarr Navy Assembly Plant","roi":0.04,"volumeAvailable":1,"maxProfit":2},{"typeId":15626,"itemName":"Republic Fleet Midshipman Insignia II","buyPrice":7999,"sellPrice":8000,"profitPerUnit":1,"buyStation":"Rens VI - Moon 8 - Brutor Tribe Treasury","sellStation":"Oyonata IV - Moon 1 - Amarr Navy Assembly Plant","roi":0.01,"volumeAvailable":1,"maxProfit":1}]}