{"lastUpdated":"2026-04-27T07:55:01.589Z","buyRegion":10001004,"sellRegion":10000049,"buyRegionName":"Exordium","sellRegionName":"Khanid","opportunities":[{"typeId":3713,"itemName":"Vitoc","buyPrice":7626.78,"sellPrice":12071.4,"profitPerUnit":4444.62,"buyStation":"Ichorah VII - Moon 1 - Ministry of Internal Order Testing Facilities","sellStation":"Nahrneder VI - Moon 15 - Khanid Transport Storage","roi":58.28,"volumeAvailable":571,"maxProfit":2537878.02},{"typeId":9826,"itemName":"Carbon","buyPrice":332.52,"sellPrice":385.88,"profitPerUnit":53.36,"buyStation":"Kanta IV - Royal Amarr Institute","sellStation":"Neyi VII - Moon 7 - CONCORD Academy","roi":16.05,"volumeAvailable":6,"maxProfit":320.16},{"typeId":9826,"itemName":"Carbon","buyPrice":343.1,"sellPrice":385.88,"profitPerUnit":42.78,"buyStation":"Mazor V - Hedion University","sellStation":"Neyi VII - Moon 7 - CONCORD Academy","roi":12.47,"volumeAvailable":6,"maxProfit":256.68},{"typeId":9826,"itemName":"Carbon","buyPrice":343.1,"sellPrice":385.88,"profitPerUnit":42.78,"buyStation":"Lenity V - Genolution Biotech Research Center","sellStation":"Neyi VII - Moon 7 - CONCORD Academy","roi":12.47,"volumeAvailable":6,"maxProfit":256.68}]}