{"lastUpdated":"2026-04-13T02:47:12.917Z","buyRegion":10000049,"sellRegion":10000060,"buyRegionName":"Khanid","sellRegionName":"Delve","opportunities":[{"typeId":17366,"itemName":"Station Container","buyPrice":5000,"sellPrice":1000000,"profitPerUnit":995000,"buyStation":"Gehi IX - Moon 4 - Royal Khanid Navy Assembly Plant","sellStation":"Z3V-1W VII - Blood Raiders Assembly Plant","roi":19900,"volumeAvailable":10,"maxProfit":9950000},{"typeId":5399,"itemName":"J5 Enduring Warp Disruptor","buyPrice":1.01,"sellPrice":90,"profitPerUnit":88.99,"buyStation":"Irmalin VIII - Moon 13 - Royal Khanid Navy Testing Facilities","sellStation":"319-3D IX - Moon 22 - Blood Raiders Logistic Support","roi":8810.89,"volumeAvailable":1,"maxProfit":88.99},{"typeId":17366,"itemName":"Station Container","buyPrice":25000,"sellPrice":1000000,"profitPerUnit":975000,"buyStation":"Danera III - Moon 3 - Khanid Transport Storage","sellStation":"Z3V-1W VII - Blood Raiders Assembly Plant","roi":3900,"volumeAvailable":5,"maxProfit":4875000},{"typeId":17366,"itemName":"Station Container","buyPrice":30000,"sellPrice":1000000,"profitPerUnit":970000,"buyStation":"Khanid Prime V - Moon 1 - Khanid Innovation Factory","sellStation":"Z3V-1W VII - Blood Raiders Assembly Plant","roi":3233.33,"volumeAvailable":8,"maxProfit":7760000},{"typeId":17366,"itemName":"Station Container","buyPrice":35870,"sellPrice":1000000,"profitPerUnit":964130,"buyStation":"Kuhri III - Moon 13 - Royal Khanid Navy Testing Facilities","sellStation":"Z3V-1W VII - Blood Raiders Assembly Plant","roi":2687.84,"volumeAvailable":10,"maxProfit":9641300},{"typeId":17366,"itemName":"Station Container","buyPrice":36820,"sellPrice":1000000,"profitPerUnit":963180,"buyStation":"Irmalin VIII - Moon 13 - Royal Khanid Navy Testing Facilities","sellStation":"Z3V-1W VII - Blood Raiders Assembly Plant","roi":2615.92,"volumeAvailable":7,"maxProfit":6742260},{"typeId":17366,"itemName":"Station Container","buyPrice":90000,"sellPrice":1000000,"profitPerUnit":910000,"buyStation":"Danera IV - Moon 1 - Royal Khanid Navy Assembly Plant","sellStation":"Z3V-1W VII - Blood Raiders Assembly Plant","roi":1011.11,"volumeAvailable":10,"maxProfit":9100000},{"typeId":17366,"itemName":"Station Container","buyPrice":169000,"sellPrice":1000000,"profitPerUnit":831000,"buyStation":"Agil VI - Moon 2 - CONCORD Logistic Support","sellStation":"Z3V-1W VII - Blood Raiders Assembly Plant","roi":491.72,"volumeAvailable":10,"maxProfit":8310000},{"typeId":34,"itemName":"Tritanium","buyPrice":1.68,"sellPrice":4.2,"profitPerUnit":2.52,"buyStation":"Irmalin VIII - Moon 13 - Royal Khanid Navy Testing Facilities","sellStation":"I3Q-II VII - Moon 2 - Blood Raiders Assembly Plant","roi":150,"volumeAvailable":1915583,"maxProfit":4827269.16},{"typeId":22542,"itemName":"Mining Laser Upgrade I","buyPrice":130000,"sellPrice":300000,"profitPerUnit":170000,"buyStation":"Irmalin VIII - Moon 13 - Royal Khanid Navy Testing Facilities","sellStation":"319-3D IX - Moon 22 - Blood Raiders Logistic Support","roi":130.77,"volumeAvailable":1,"maxProfit":170000},{"typeId":34,"itemName":"Tritanium","buyPrice":2,"sellPrice":4.2,"profitPerUnit":2.2,"buyStation":"Arzieh V - Moon 3 - Royal Khanid Navy Testing Facilities","sellStation":"I3Q-II VII - Moon 2 - Blood Raiders Assembly Plant","roi":110,"volumeAvailable":1915583,"maxProfit":4214282.6},{"typeId":34,"itemName":"Tritanium","buyPrice":2,"sellPrice":4.2,"profitPerUnit":2.2,"buyStation":"Gehi IX - Moon 4 - Royal Khanid Navy Assembly Plant","sellStation":"I3Q-II VII - Moon 2 - Blood Raiders Assembly Plant","roi":110,"volumeAvailable":1499166,"maxProfit":3298165.2},{"typeId":22542,"itemName":"Mining Laser Upgrade I","buyPrice":150000,"sellPrice":300000,"profitPerUnit":150000,"buyStation":"Baratar X - Moon 9 - Royal Khanid Navy Logistic Support","sellStation":"319-3D IX - Moon 22 - Blood Raiders Logistic Support","roi":100,"volumeAvailable":1,"maxProfit":150000},{"typeId":2550,"itemName":"Storm Command Center","buyPrice":75000,"sellPrice":150000,"profitPerUnit":75000,"buyStation":"Irmalin VIII - Moon 13 - Royal Khanid Navy Testing Facilities","sellStation":"1DH-SX III - Moon 1 - Blood Raiders Logistic Support","roi":100,"volumeAvailable":2,"maxProfit":150000},{"typeId":37,"itemName":"Isogen","buyPrice":100.4,"sellPrice":185,"profitPerUnit":84.6,"buyStation":"Gehi IX - Moon 4 - Royal Khanid Navy Assembly Plant","sellStation":"1DH-SX III - Moon 1 - Blood Raiders Logistic Support","roi":84.26,"volumeAvailable":546,"maxProfit":46191.6},{"typeId":34,"itemName":"Tritanium","buyPrice":2.46,"sellPrice":4.2,"profitPerUnit":1.74,"buyStation":"Zephan VIII - Moon 1 - Khanid Transport Storage","sellStation":"I3Q-II VII - Moon 2 - Blood Raiders Assembly Plant","roi":70.73,"volumeAvailable":1915583,"maxProfit":3333114.42},{"typeId":34,"itemName":"Tritanium","buyPrice":2.66,"sellPrice":4.2,"profitPerUnit":1.54,"buyStation":"Khanid Prime V - Moon 1 - Khanid Innovation Factory","sellStation":"I3Q-II VII - Moon 2 - Blood Raiders Assembly Plant","roi":57.89,"volumeAvailable":12534,"maxProfit":19302.36},{"typeId":40,"itemName":"Megacyte","buyPrice":1557,"sellPrice":2350,"profitPerUnit":793,"buyStation":"Irmalin VIII - Moon 13 - Royal Khanid Navy Testing Facilities","sellStation":"1DH-SX III - Moon 1 - Blood Raiders Logistic Support","roi":50.93,"volumeAvailable":22,"maxProfit":17446},{"typeId":2254,"itemName":"Temperate Command Center","buyPrice":70000,"sellPrice":100000,"profitPerUnit":30000,"buyStation":"Irmalin VIII - Moon 13 - Royal Khanid Navy Testing Facilities","sellStation":"319-3D IX - Moon 22 - Blood Raiders Logistic Support","roi":42.86,"volumeAvailable":4,"maxProfit":120000},{"typeId":2549,"itemName":"Lava Command Center","buyPrice":75000,"sellPrice":100000,"profitPerUnit":25000,"buyStation":"Irmalin VIII - Moon 13 - Royal Khanid Navy Testing Facilities","sellStation":"319-3D IX - Moon 22 - Blood Raiders Logistic Support","roi":33.33,"volumeAvailable":4,"maxProfit":100000},{"typeId":35,"itemName":"Pyerite","buyPrice":13.02,"sellPrice":17,"profitPerUnit":3.98,"buyStation":"Khanid Prime V - Moon 1 - Khanid Innovation Factory","sellStation":"1DH-SX III - Moon 1 - Blood Raiders Logistic Support","roi":30.57,"volumeAvailable":3566,"maxProfit":14192.68},{"typeId":85178,"itemName":"Tetrimonic Warclone Blanks","buyPrice":800000,"sellPrice":1000000,"profitPerUnit":200000,"buyStation":"Agil VI - Moon 2 - CONCORD Logistic Support","sellStation":"A-ELE2 VI - Blood Raiders Assembly Plant","roi":25,"volumeAvailable":127,"maxProfit":25400000},{"typeId":37,"itemName":"Isogen","buyPrice":151.1,"sellPrice":185,"profitPerUnit":33.9,"buyStation":"Khanid Prime V - Moon 1 - Khanid Innovation Factory","sellStation":"1DH-SX III - Moon 1 - Blood Raiders Logistic Support","roi":22.44,"volumeAvailable":668,"maxProfit":22645.2},{"typeId":38,"itemName":"Nocxium","buyPrice":550.1,"sellPrice":670.1,"profitPerUnit":120,"buyStation":"Khanid Prime V - Moon 1 - Khanid Innovation Factory","sellStation":"1DH-SX III - Moon 1 - Blood Raiders Logistic Support","roi":21.81,"volumeAvailable":364,"maxProfit":43680},{"typeId":38,"itemName":"Nocxium","buyPrice":550.4,"sellPrice":670.1,"profitPerUnit":119.7,"buyStation":"Irmalin VIII - Moon 13 - Royal Khanid Navy Testing Facilities","sellStation":"1DH-SX III - Moon 1 - Blood Raiders Logistic Support","roi":21.75,"volumeAvailable":228,"maxProfit":27291.6},{"typeId":34,"itemName":"Tritanium","buyPrice":3.5,"sellPrice":4.2,"profitPerUnit":0.7,"buyStation":"Danera IV - Moon 1 - Royal Khanid Navy Assembly Plant","sellStation":"I3Q-II VII - Moon 2 - Blood Raiders Assembly Plant","roi":20,"volumeAvailable":1915583,"maxProfit":1340908.1},{"typeId":35,"itemName":"Pyerite","buyPrice":15,"sellPrice":17,"profitPerUnit":2,"buyStation":"Irmalin VIII - Moon 13 - Royal Khanid Navy Testing Facilities","sellStation":"1DH-SX III - Moon 1 - Blood Raiders Logistic Support","roi":13.33,"volumeAvailable":3439,"maxProfit":6878},{"typeId":2525,"itemName":"Oceanic Command Center","buyPrice":90000,"sellPrice":100000,"profitPerUnit":10000,"buyStation":"Irmalin VIII - Moon 13 - Royal Khanid Navy Testing Facilities","sellStation":"319-3D IX - Moon 22 - Blood Raiders Logistic Support","roi":11.11,"volumeAvailable":3,"maxProfit":30000},{"typeId":33577,"itemName":"Covert Research Tools","buyPrice":450000,"sellPrice":500000,"profitPerUnit":50000,"buyStation":"Gehi IX - Moon 4 - Royal Khanid Navy Assembly Plant","sellStation":"UHKL-N V - Moon 1 - Blood Raiders Testing Facilities","roi":11.11,"volumeAvailable":1058,"maxProfit":52900000},{"typeId":33577,"itemName":"Covert Research Tools","buyPrice":450000,"sellPrice":500000,"profitPerUnit":50000,"buyStation":"Arzieh V - Moon 3 - Royal Khanid Navy Testing Facilities","sellStation":"UHKL-N V - Moon 1 - Blood Raiders Testing Facilities","roi":11.11,"volumeAvailable":12,"maxProfit":600000},{"typeId":2534,"itemName":"Gas Command Center","buyPrice":90000,"sellPrice":100000,"profitPerUnit":10000,"buyStation":"Irmalin VIII - Moon 13 - Royal Khanid Navy Testing Facilities","sellStation":"319-3D IX - Moon 22 - Blood Raiders Logistic Support","roi":11.11,"volumeAvailable":1,"maxProfit":10000},{"typeId":34,"itemName":"Tritanium","buyPrice":3.79,"sellPrice":4.2,"profitPerUnit":0.41,"buyStation":"Badivefi VI - Moon 2 - Royal Khanid Navy Logistic Support","sellStation":"I3Q-II VII - Moon 2 - Blood Raiders Assembly Plant","roi":10.82,"volumeAvailable":275,"maxProfit":112.75},{"typeId":33697,"itemName":"Prospect","buyPrice":18500000,"sellPrice":20000000,"profitPerUnit":1500000,"buyStation":"Parses VI - Moon 11 - Royal Khanid Navy Assembly Plant","sellStation":"A-ELE2 VI - Blood Raiders Assembly Plant","roi":8.11,"volumeAvailable":1,"maxProfit":1500000},{"typeId":35,"itemName":"Pyerite","buyPrice":16,"sellPrice":17,"profitPerUnit":1,"buyStation":"Badivefi VI - Moon 2 - Royal Khanid Navy Logistic Support","sellStation":"1DH-SX III - Moon 1 - Blood Raiders Logistic Support","roi":6.25,"volumeAvailable":545819,"maxProfit":545819},{"typeId":37,"itemName":"Isogen","buyPrice":175,"sellPrice":185,"profitPerUnit":10,"buyStation":"Irmalin VIII - Moon 13 - Royal Khanid Navy Testing Facilities","sellStation":"1DH-SX III - Moon 1 - Blood Raiders Logistic Support","roi":5.71,"volumeAvailable":499839,"maxProfit":4998390},{"typeId":34,"itemName":"Tritanium","buyPrice":3.99,"sellPrice":4.2,"profitPerUnit":0.21,"buyStation":"Baratar X - Moon 9 - Royal Khanid Navy Logistic Support","sellStation":"I3Q-II VII - Moon 2 - Blood Raiders Assembly Plant","roi":5.26,"volumeAvailable":1915583,"maxProfit":402272.43},{"typeId":34,"itemName":"Tritanium","buyPrice":3.99,"sellPrice":4.2,"profitPerUnit":0.21,"buyStation":"Bashyam X - Moon 7 - Khanid Transport Storage","sellStation":"I3Q-II VII - Moon 2 - Blood Raiders Assembly Plant","roi":5.26,"volumeAvailable":1528910,"maxProfit":321071.1},{"typeId":2533,"itemName":"Ice Command Center","buyPrice":95000,"sellPrice":100000,"profitPerUnit":5000,"buyStation":"Irmalin VIII - Moon 13 - Royal Khanid Navy Testing Facilities","sellStation":"319-3D IX - Moon 22 - Blood Raiders Logistic Support","roi":5.26,"volumeAvailable":4,"maxProfit":20000},{"typeId":34,"itemName":"Tritanium","buyPrice":4,"sellPrice":4.2,"profitPerUnit":0.2,"buyStation":"Danera III - Moon 3 - Khanid Transport Storage","sellStation":"I3Q-II VII - Moon 2 - Blood Raiders Assembly Plant","roi":5,"volumeAvailable":573457,"maxProfit":114691.4},{"typeId":34,"itemName":"Tritanium","buyPrice":4.03,"sellPrice":4.2,"profitPerUnit":0.17,"buyStation":"Chamemi VI - Moon 1 - Royal Khanid Navy Assembly Plant","sellStation":"I3Q-II VII - Moon 2 - Blood Raiders Assembly Plant","roi":4.22,"volumeAvailable":687194,"maxProfit":116822.98},{"typeId":34,"itemName":"Tritanium","buyPrice":4.1,"sellPrice":4.2,"profitPerUnit":0.1,"buyStation":"Ibani VI - Moon 15 - Khanid Transport Storage","sellStation":"I3Q-II VII - Moon 2 - Blood Raiders Assembly Plant","roi":2.44,"volumeAvailable":1915583,"maxProfit":191558.3},{"typeId":34,"itemName":"Tritanium","buyPrice":4.1,"sellPrice":4.2,"profitPerUnit":0.1,"buyStation":"Kahah I - Khanid Transport Storage","sellStation":"I3Q-II VII - Moon 2 - Blood Raiders Assembly Plant","roi":2.44,"volumeAvailable":1915583,"maxProfit":191558.3},{"typeId":34,"itemName":"Tritanium","buyPrice":4.1,"sellPrice":4.2,"profitPerUnit":0.1,"buyStation":"Vezila IV - Royal Khanid Navy Assembly Plant","sellStation":"I3Q-II VII - Moon 2 - Blood Raiders Assembly Plant","roi":2.44,"volumeAvailable":1915583,"maxProfit":191558.3},{"typeId":34,"itemName":"Tritanium","buyPrice":4.15,"sellPrice":4.2,"profitPerUnit":0.05,"buyStation":"Kihtaled VIII - CONCORD Bureau","sellStation":"I3Q-II VII - Moon 2 - Blood Raiders Assembly Plant","roi":1.2,"volumeAvailable":1915583,"maxProfit":95779.15},{"typeId":2549,"itemName":"Lava Command Center","buyPrice":99990,"sellPrice":100000,"profitPerUnit":10,"buyStation":"Goudiyah VIII - Moon 1 - Royal Khanid Navy Logistic Support","sellStation":"319-3D IX - Moon 22 - Blood Raiders Logistic Support","roi":0.01,"volumeAvailable":4,"maxProfit":40},{"typeId":2533,"itemName":"Ice Command Center","buyPrice":99990,"sellPrice":100000,"profitPerUnit":10,"buyStation":"Nandeza IX - Moon 13 - Royal Khanid Navy Assembly Plant","sellStation":"319-3D IX - Moon 22 - Blood Raiders Logistic Support","roi":0.01,"volumeAvailable":2,"maxProfit":20},{"typeId":2533,"itemName":"Ice Command Center","buyPrice":99990,"sellPrice":100000,"profitPerUnit":10,"buyStation":"Goudiyah VIII - Moon 1 - Royal Khanid Navy Logistic Support","sellStation":"319-3D IX - Moon 22 - Blood Raiders Logistic Support","roi":0.01,"volumeAvailable":2,"maxProfit":20}]}